{"KEY": "ACORDAO-COMPLETO-2415597", "TIPO": "AC\u00d3RD\u00c3O DE RELA\u00c7\u00c3O", "TITULO": "AC\u00d3RD\u00c3O DE RELA\u00c7\u00c3O 6773/2020 ATA 20/2020 - PRIMEIRA C\u00c2MARA", "FAVORITO": false, "NUMACORDAO": "6773", "ANOACORDAO": "2020", "NUMATA": "20/2020", "ACORDAO": "<a href=\"https://pesquisa.apps.tcu.gov.br/#/doc/acordao-completo/6773/2020/Primeira C\u00e2mara\" target=\"_blank\">Ac\u00f3rd\u00e3o 6773/2020-TCU-Primeira C\u00e2mara</a></b></p><p class=\"tCU_-__Ac_-_item_9_-_1\u00aa_Linha\"/><p>Os Ministros do Tribunal de Contas da Uni\u00e3o ACORDAM, por unanimidade, com fundamento no art. 71, inciso III, da Constitui\u00e7\u00e3o Federal/1988, c/c os arts. 1\u00ba, inciso V, e 39, inciso I, da Lei 8.443/1992, c/c os arts. 1\u00ba, inciso VIII, 17, inciso II, 143, inciso II, 259, inciso I, e 260, \u00a7 5\u00ba, do Regimento Interno do TCU, em considerar<b> prejudicado</b>, <b>por perda de objeto</b>, o exame de m\u00e9rito dos <b>atos de admiss\u00e3o</b> dos interessados a seguir relacionados, de acordo com os pareceres emitidos nos autos.</p><p class=\"tCU_-__Ac_-_item_9_-_1\u00aa_Linha\"><b>1. Processo TC-<a href=\"https://pesquisa.apps.tcu.gov.br/#/doc/processo/2055820201\" target=\"_blank\">Processo 020.558/2020-1</a> (ATOS DE ADMISS\u00c3O) </b></p><p class=\"tCU_-__Ac_-_item_9_-_1\u00aa_Linha\">\t1.1. Interessados: Andreza Magro Moraes (XXX.630.956-XX) ; Bernardo Dorsch Benevides Martins (XXX.208.707-XX) ; Bruna Fernandes da Silva (XXX.576.637-XX) ; Bruna Luiza dos Santos Almeida (XXX.372.426-XX) ; Danila Carvalho Santana (XXX.266.506-XX) ; David Gabriel Campos Pereira (XXX.962.956-XX) ; Ederson Coelho Boldrini (XXX.972.057-XX) ; Eduardo Ribeiro Santana (XXX.400.276-XX) ; Elvis Mendes Carvalho (XXX.003.247-XX) ; Fabiola Pinto Pereira (XXX.926.497-XX) ; Fernanda Goncalves de Lima (XXX.878.746-XX) ; Guilherme Nery Cavalcante (XXX.142.877-XX) ; Guilherme Rocha Ferreira (XXX.508.716-XX) ; Jose Eduardo Mantovanelli Dazzi (XXX.804.197-XX) ; Marina Alves Assis (XXX.739.916-XX) ; Renato Sielemann Falqueto (XXX.619.027-XX) ; Sergio Zambon da Silva (XXX.773.187-XX) ; Sueli Tomazelli Suave (XXX.385.257-XX) ; Thamyres Sabrina Goncalves (XXX.941.226-XX) ; Vinicius Alves Dias (XXX.812.727-XX) .</p><p class=\"tCU_-__Ac_-_item_9_-_1\u00aa_Linha\">\t1.2. Entidade: Funda\u00e7\u00e3o Instituto Brasileiro de Geografia e Estat\u00edstica.</p><p class=\"tCU_-__Ac_-_item_9_-_1\u00aa_Linha\">\t1.3. Relator: Ministro Vital do R\u00eago.</p><p class=\"tCU_-__Ac_-_item_9_-_1\u00aa_Linha\">\t1.4. Representante do Minist\u00e9rio P\u00fablico: Procuradora-Geral Cristina Machado da Costa e Silva.</p><p class=\"tCU_-__Ac_-_item_9_-_1\u00aa_Linha\">\t1.5. Unidade T\u00e9cnica: Secretaria de Fiscaliza\u00e7\u00e3o de Pessoal (Sefip) .</p><p class=\"tCU_-__Ac_-_item_9_-_1\u00aa_Linha\">\t1.6. Representa\u00e7\u00e3o legal: n\u00e3o h\u00e1.</p><p class=\"tCU_-__Ac_-_item_9_-_1\u00aa_Linha\">\t1.7. Determina\u00e7\u00f5es/Recomenda\u00e7\u00f5es/Orienta\u00e7\u00f5es: n\u00e3o h\u00e1.</p><p class=\"tCU_-__Ac_-_item_9_-_1\u00aa_Linha\"/><p class=\"footer\"/>", "COLEGIADO": "Primeira C\u00e2mara", "DATASESSAO": "23/06/2020", "ENTIDADE": " Funda\u00e7\u00e3o Instituto Brasileiro de Geografia e Estat\u00edstica.", "INTERESSADOS": " Andreza Magro Moraes (XXX.630.956-XX); Bernardo Dorsch Benevides Martins (XXX.208.707-XX); Bruna Fernandes da Silva (XXX.576.637-XX); Bruna Luiza dos Santos Almeida (XXX.372.426-XX); Danila Carvalho Santana (XXX.266.506-XX); David Gabriel Campos Pereira (XXX.962.956-XX); Ederson Coelho Boldrini (XXX.972.057-XX); Eduardo Ribeiro Santana (XXX.400.276-XX); Elvis Mendes Carvalho (XXX.003.247-XX); Fabiola Pinto Pereira (XXX.926.497-XX); Fernanda Goncalves de Lima (XXX.878.746-XX); Guilherme Nery Cavalcante (XXX.142.877-XX); Guilherme Rocha Ferreira (XXX.508.716-XX); Jose Eduardo Mantovanelli Dazzi (XXX.804.197-XX); Marina Alves Assis (XXX.739.916-XX); Renato Sielemann Falqueto (XXX.619.027-XX); Sergio Zambon da Silva (XXX.773.187-XX); Sueli Tomazelli Suave (XXX.385.257-XX); Thamyres Sabrina Goncalves (XXX.941.226-XX); Vinicius Alves Dias (XXX.812.727-XX).", "PROC": "<a href=\"https://pesquisa.apps.tcu.gov.br/#/push/processo?numero=02055820201\" target=\"_blank\">020.558/2020-1</a>", "RELATOR": "VITAL DO R\u00caGO", "ADVOGADO": " n\u00e3o h\u00e1.", "REPRESENTANTEMP": "Procuradora-Geral Cristina Machado da Costa e Silva.", "SITUACAO": "OFICIALIZADO", "TIPOPROCESSO": "ATOS DE ADMISS\u00c3O (ADS)", "UNIDADETECNICA": " Secretaria de Fiscaliza\u00e7\u00e3o de Pessoal (Sefip).", "DTATUALIZACAO": "20210620", "URLARQUIVO": "https://contas.tcu.gov.br/sisdoc/ObterDocumentoSisdoc?codVersao=editavel&codArqCatalogado=20244913", "URLARQUIVOPDF": "https://contas.tcu.gov.br/sisdoc/ObterDocumentoSisdoc?codArqCatalogado=20244913", "EXTENSAOARQUIVO": "doc", "CODPROCESSO": "64828949"}