{"KEY": "ACORDAO-COMPLETO-2349874", "TIPO": "AC\u00d3RD\u00c3O DE RELA\u00c7\u00c3O", "TITULO": "AC\u00d3RD\u00c3O DE RELA\u00c7\u00c3O 2719/2019 ATA 9/2019 - PRIMEIRA C\u00c2MARA", "FAVORITO": false, "NUMACORDAO": "2719", "ANOACORDAO": "2019", "NUMATA": "9/2019", "ACORDAO": "<a href=\"https://pesquisa.apps.tcu.gov.br/#/doc/acordao-completo/2719/2019/Primeira C\u00e2mara\" target=\"_blank\">Ac\u00f3rd\u00e3o 2719/2019-TCU-Primeira C\u00e2mara</a></b></p><p class=\"tCU_-__Ac_-_item_9_-_1\u00aa_Linha\"/><p class=\"tCU_-_Rel/Voto_-_1\u00ba_\u00a7\">Os Ministros do Tribunal de Contas da Uni\u00e3o, reunidos em Sess\u00e3o da Primeira C\u00e2mara, ACORDAM, por unanimidade, com fulcro nos arts. 1\u00ba, inciso I, 16, inciso II, 18 e 23, inciso II, da Lei 8.443/1992 c/c os arts. 1\u00ba, inciso I, 208 e 214, inciso II, do Regimento Interno do TCU, julgar regulares com ressalvas, decorrente das falhas arroladas no item 1.7, as contas de Wyllys Abel Farkatt Tabosa e Marcos Ant\u00f4nio de Oliveira, dando-lhes quita\u00e7\u00e3o; com fundamento nos arts. 1\u00ba, inciso I, 16, inciso I, 17 e 23, inciso I, da Lei 8.443/92, c/c os arts. 143, inciso I, \"a\", 207 e 214, inciso I, do Regimento Interno/TCU, julgar regulares as contas dos demais respons\u00e1veis arrolados no item 1.1, dando-lhes quita\u00e7\u00e3o plena; expedir as determina\u00e7\u00f5es, ci\u00eancias e recomenda\u00e7\u00f5es descritas nos itens 1.8 a 1.10 e arquivar o processo, de acordo com os pareceres emitidos nos autos (pe\u00e7as 13-16) :</p><p class=\"tCU_-__Ac_-_item_9_-_1\u00aa_Linha\"/><p class=\"tCU_-__Ac_-_item_9_-_1\u00aa_Linha\"><b>1. Processo TC-<a href=\"https://pesquisa.apps.tcu.gov.br/#/doc/processo/3358320188\" target=\"_blank\">Processo 033.583/2018-8</a> (PRESTA\u00c7\u00c3O DE CONTAS - Exerc\u00edcio: 2017) </b></p><p class=\"tCU_-__Ac_-_item_9_-_1\u00aa_Linha\">\t1.1. Respons\u00e1veis: Agamenon Henrique de Carvalho Tavares (XXX.347.444-XX) ; Alailson de Freitas Braz (XXX.957.574-XX) ; Albino Oliveira Nunes (XXX.593.424-XX) ; Allan David Garcia de Araujo (XXX.178.164-XX) ; Ambr\u00f3sio Lins do Nascimento (XXX.155.544-XX) ; Ana Carolina Bezerra de Melo Costa (XXX.141.085-XX) ; Ana Maria Cardoso de Oliveira Bezerra (XXX.528.804-XX) ; Ana Maria da Silva (XXX.762.724-XX) ; Andre Gustavo Duarte de Almeida (XXX.867.564-XX) ; Andreilson Oliveira da Silva (XXX.002.674-XX) ; Annaterra Teixeira de Lima (XXX.054.154-XX) ; Anne Gabrielle Lima dos Santos (XXX.115.304-XX) ; Antenor Mario da Silva (XXX.802.634-XX) ; Auridan Dantas de Ara\u00fajo (XXX.839.904-XX) ; Bernardo Eneas de Araujo Nascimento (XXX.632.364-XX) ; Brenda Maria Pessoa de Carvalho (XXX.480.034-XX) ; Bruna Lais Campos do Nascimento (XXX.940.404-XX) ; Bruno Gomes de Araujo (XXX.452.224-XX) ; Camila Nascimento de Oliveira Taumaturgo (XXX.189.084-XX) ; Camilo Soares de Medeiros Junior (XXX.735.424-XX) ; Carlos Andre de Oliveira (XXX.646.604-XX) ; Cintia Gouveia Costa (XXX.877.824-XX) ; Daniela Karina Candido (XXX.382.014-XX) ; Darlyne Fontes Virginio (XXX.955.881-XX) ; Diderot Franco Sampaio Junior (XXX.254.024-XX) ; Ednaldo de Paiva Pereira (XXX.118.334-XX) ; Elizomar de Assis Nobre (XXX.859.397-XX) ; Emanuel Gomes Lourenco (XXX.715.262-XX) ; Emerson da Cunha Batista (XXX.684.464-XX) ; Eraldy Kennedy de Sousa Chagas (XXX.311.094-XX) ; Erasmo Jose Pereira de Oliveira (XXX.932.774-XX) ; Erico Cadineli Braz (XXX.240.254-XX) ; Fellipe Neri de Oliveira Arrais (XXX.174.484-XX) ; Fernanda Ferreira da Costa Nunes (XXX.328.355-XX) ; Fernando Henrique da Silva (XXX.292.174-XX) ; Flavia Roberta Monteiro de Souza (XXX.394.504-XX) ; Francisco Fernandes de Oliveira (XXX.849.374-XX) ; Gustavo Henrique de Almeida Barbalho (XXX.465.144-XX) ; Isaias Amancio dos Santos (XXX.529.594-XX) ; Ivanilson Franca Vieira Junior (XXX.471.524-XX) ; Joao Bosco Cabral Freire (XXX.864.064-XX) ; Joao Henrique de Melo Ferraz (XXX.174.574-XX) ; Joao Marcos Ribeiro Martins (XXX.014.203-XX) ; Joao Maria Paiva Palhano (XXX.471.304-XX) ; Joao Maria de Oliveira (XXX.112.674-XX) ; Joao Rodrigo Silva de Carvalho (XXX.687.184-XX) ; Jose Cleyton Neves Lopes (XXX.310.064-XX) ; Jose Diego Cirne Santos (XXX.659.864-XX) ; Jose Ferreira da Silva Junior (XXX.183.664-XX) ; Jose Geraldo Bezerra Galvao Junior (XXX.107.604-XX) ; Jose Xavier da Camara Neto (XXX.267.044-XX) ; Jose de Ribamar Silva Oliveira (XXX.595.203-XX) ; Jos\u00e9 Arn\u00f3bio de Ara\u00fajo Filho (XXX.031.024-XX) ; Juan Carlo da Cruz Silva (XXX.317.584-XX) ; Juscelino Cardoso de Medeiros (XXX.066.944-XX) ; Karina Bezerra da Fonseca e Silva Martins (XXX.859.764-XX) ; Karolayne Paiva Bezerra de Lima (XXX.160.484-XX) ; Ligia Mara Gonzaga (XXX.705.064-XX) ; Luisa de Marilac de Castro Silva (XXX.593.453-XX) ; Luiz Carlos do Rego (XXX.315.051-XX) ; Maluh Brito Madruga (XXX.506.364-XX) ; Manoel Jusselino de Almeida e Silva (XXX.774.344-XX) ; Marcel Lucio Matias Ribeiro (XXX.596.374-XX) ; Marcelo Henrique Carneiro Camilo (XXX.748.534-XX) ; Marcio Adriano de Azevedo (XXX.017.014-XX) ; Marcones Marinho da Silva (XXX.939.744-XX) ; Marcos Antonio de Oliveira (XXX.622.154-XX) ; Maria Clara Fernandes Bezerra (XXX.506.354-XX) ; Maria Eduarda da Costa Andrade (XXX.893.194-XX) ; Maria Vitoria Torquato Pessoa (XXX.275.014-XX) ; Maria das Gracas de Araujo Varela (XXX.015.074-XX) ; Maria das Vitorias Dantas de Gois (XXX.385.104-XX) ; Maria dos Navegantes dos Santos da Silva (XXX.167.854-XX) ; Marlucia Viana Raposo Caldas (XXX.079.624-XX) ; Mikael Lucas da Silva Dionisio (XXX.328.764-XX) ; Nadir Arruda Skeete (XXX.079.064-XX) ; Pedro Brendo de La Sales Silas Felix de Medeiros (XXX.632.574-XX) ; Phelipe da Rocha Guimaraes (XXX.634.654-XX) ; Raquel Priscyla da Silva Costa (XXX.825.704-XX) ; Raul Aleixandre Fernandes de Queiroz (XXX.329.884-XX) ; Rinaldo Medeiros Alves de Oliveira (XXX.552.404-XX) ; Roberto Gomes Cavalcante Junior (XXX.648.744-XX) ; Rodrigo Siqueira Martins (XXX.042.434-XX) ; Romulo Flavio de Oliveira Santos (XXX.111.844-XX) ; Roseanne Azevedo de Albuquerque (XXX.787.134-XX) ; R\u00e9gia L\u00facia Lopes (XXX.560.944-XX) ; Samira Fernandes Delgado (XXX.480.361-XX) ; Sandoval Villaverde Monteiro (XXX.939.104-XX) ; Sandra Maria da Nobrega (XXX.706.574-XX) ; Sebastiao Bezerra (XXX.716.637-XX) ; Solange Marlene Thomaz (XXX.693.200-XX) ; Sonia Cristina Ferreira Maia (XXX.671.774-XX) ; Thiago Augusto Braz de Medeiros (XXX.916.334-XX) ; Thiago Fernando de Araujo Silva (XXX.672.634-XX) ; Thiago Jose de Azevedo Loureiro (XXX.330.784-XX) ; Thiago Lima de Oliveira (XXX.600.774-XX) ; Ticiana Patricia da Silveira Cunha (XXX.583.744-XX) ; Valdel\u00facio Pereira Ribeiro (XXX.484.314-XX) ; Valdemberg Magno do Nascimento Pessoa (XXX.976.603-XX) ; Valeria Oliveira Pontes Alencar de Carvalho (XXX.375.784-XX) ; Victor Varela Ferreira Medeiros de Oliveira (XXX.651.074-XX) ; Wyllys Abel Farkatt Tabosa (XXX.775.204-XX) ; Yarianne Melo de Sousa Gama (XXX.384.324-XX) </p><p class=\"tCU_-__Ac_-_item_9_-_1\u00aa_Linha\">\t1.2. Entidade: Instituto Federal de Educa\u00e7\u00e3o, Ci\u00eancia e Tecnologia do Rio Grande do Norte</p><p class=\"tCU_-__Ac_-_item_9_-_1\u00aa_Linha\">\t1.3. Relator: Ministro Walton Alencar Rodrigues</p><p class=\"tCU_-__Ac_-_item_9_-_1\u00aa_Linha\">\t1.4. Representante do Minist\u00e9rio P\u00fablico: Subprocurador-Geral Paulo Soares Bugarin</p><p class=\"tCU_-__Ac_-_item_9_-_1\u00aa_Linha\">\t1.5. Unidade T\u00e9cnica: Secretaria do TCU no Estado do Rio Grande do Norte (Sec-RN) .</p><p class=\"tCU_-__Ac_-_item_9_-_1\u00aa_Linha\">\t1.6. Representa\u00e7\u00e3o legal: n\u00e3o h\u00e1.</p><p class=\"tCU_-__Ac_-_item_9_-_1\u00aa_Linha\">\t1.7. Ressalvas:</p><p class=\"tCU_-_Ac_-_item_9_-_\u00a7\u00a7\">1.7.1. inconsist\u00eancias na jornada flexibilizada concedida aos servidores do quadro t\u00e9cnico-administrativo, a saber, portarias de autoriza\u00e7\u00e3o inv\u00e1lidas; hor\u00e1rios constantes em quadros afixados divergentes dos hor\u00e1rios constantes em portaria de autoriza\u00e7\u00e3o; aus\u00eancia de quadro afixado com o hor\u00e1rio dos servidores;</p><p class=\"tCU_-_Ac_-_item_9_-_\u00a7\u00a7\">1.7.2. execu\u00e7\u00e3o irregular de atividades na jornada flexibilizada concedida aos servidores do quadro t\u00e9cnico-administrativo com apenas seis horas de servi\u00e7o por dia, e n\u00e3o doze horas ininterruptas, por n\u00e3o haver outros servidores para revezamento da escala e/ou revezamento irregular com o chefe do setor;</p><p class=\"tCU_-_Ac_-_item_9_-_\u00a7\u00a7\">1.7.3. aus\u00eancia de diplomas e diverg\u00eancia significativa entre os pareceres emitidos no processo n. 23424.046185.2017-70 de RSC indicam fragilidades no processo avaliativo; </p><p class=\"tCU_-_Ac_-_item_9_-_\u00a7\u00a7\">1.7.4. aus\u00eancia de normativo interno que estabele\u00e7a crit\u00e9rios para carga hor\u00e1ria e pagamentos de bolsas no modelo Bolsa Forma\u00e7\u00e3o da Rede e-Tec, contrariando o item 5.2 do Manual de Gest\u00e3o da Rede e-Tec Brasil e do Perfuncion\u00e1rio de 2016;</p><p class=\"tCU_-_Ac_-_item_9_-_\u00a7\u00a7\">1.7.5. aus\u00eancia de relat\u00f3rios gerenciais para fins de verifica\u00e7\u00e3o do cumprimento da carga hor\u00e1ria dos bolsistas no Ambiente Virtual de Aprendizagem (AVA) e de identifica\u00e7\u00e3o de desvio de fun\u00e7\u00e3o de bolsistas da Rede e-Tec;</p><p class=\"tCU_-_Ac_-_item_9_-_\u00a7\u00a7\">1.7.6. pagamento de bolsas da Rede e-Tec a dois benefici\u00e1rios do Sistema de Gest\u00e3o de Bolsas, para fins de repasse dos valores a outros bolsistas que n\u00e3o teriam recebido na \u00e9poca devida;</p><p class=\"tCU_-_Ac_-_item_9_-_\u00a7\u00a7\">1.7.7. contrata\u00e7\u00e3o de bolsistas do Sistema de Gest\u00e3o de Bolsas da Rede e-Tec sem a publica\u00e7\u00e3o de edital, contrariando o art. 6\u00ba da Resolu\u00e7\u00e3o-CD/FNDE  36/2009;</p><p class=\"tCU_-_Ac_-_item_9_-_\u00a7\u00a7\">1.7.8. inconsist\u00eancias na contrata\u00e7\u00e3o de bolsistas professores-pesquisadores conteudistas via Sistema de Gest\u00e3o de Bolsas da Rede e-Tec, a saber, contrata\u00e7\u00e3o sem edital, em desobedi\u00eancia ao art. 6\u00ba da Resolu\u00e7\u00e3o-CD/FNDE  36/2009; aus\u00eancia de documenta\u00e7\u00e3o comprobat\u00f3ria do cumprimento dos requisitos exigidos pela Resolu\u00e7\u00e3o-CD/FNDE 18/2010 para contrata\u00e7\u00e3o; pagamento pela produ\u00e7\u00e3o de material sem a correspondente entrega; e pagamentos efetuados em valores diferentes ao contratado;</p><p class=\"tCU_-_Ac_-_item_9_-_\u00a7\u00a7\">1.7.9. inexist\u00eancia de informa\u00e7\u00e3o gerencial que permita verificar o cumprimento da carga hor\u00e1ria dos bolsistas no Ambiente Virtual de Aprendizagem do sistema Universidade Aberta do Brasil; e</p><p class=\"tCU_-_Ac_-_item_9_-_\u00a7\u00a7\">1.7.10. contrata\u00e7\u00e3o de professores conteudistas pelo sistema UAB sem publica\u00e7\u00e3o de edital, contrariando o art. 7\u00ba da Portaria-Capes 183/2016;</p><p class=\"tCU_-__Ac_-_item_9_-_1\u00aa_Linha\">\t1.8. determinar ao Instituto Federal de Educa\u00e7\u00e3o, Ci\u00eancia e Tecnologia do Rio Grande do Norte (IFRN) , com fulcro no art. 18 da Lei 8.443/1992 c/c art. 208, \u00a7 2\u00ba, do Regimento Interno do TCU, que, no prazo de 120 dias,  instaure tomada de contas especial para apurar irregularidades na condu\u00e7\u00e3o do Preg\u00e3o 45/2014, a seguir listadas, e encaminhe os resultados obtidos a este Tribunal:</p><p class=\"tCU_-_Ac_-_item_9_-_\u00a7\u00a7\">1.8.1. aus\u00eancia de motiva\u00e7\u00e3o para instalar o Preg\u00e3o 45/2014, que resultou no Contrato 028/2014, uma vez que o pre\u00e7o m\u00e9dio de mercado se encontrava em patamar superior ao contratado em decorr\u00eancia do Preg\u00e3o 66/2013 e havia a possiblidade de prorrogar o contrato vigente com respaldo no art. 57, inciso II, da Lei 8.666/1993;</p><p class=\"tCU_-_Ac_-_item_9_-_\u00a7\u00a7\">1.8.2. frustra\u00e7\u00e3o do car\u00e1ter competitivo do Preg\u00e3o 45/2014, ante a exist\u00eancia de cl\u00e1sulas restritivas \u00e0 competi\u00e7\u00e3o e uma vez que duas empresas participantes tinham o mesmo endere\u00e7o e s\u00f3cios em comum;</p><p class=\"tCU_-_Ac_-_item_9_-_\u00a7\u00a7\">1.8.3. acr\u00e9scimo de despesas, embora as especifica\u00e7\u00f5es e quantidades dos servi\u00e7os contratadas a partir do Preg\u00e3o 45/2014 fossem as mesmas do contrato anterior;</p><p class=\"tCU_-_Ac_-_item_9_-_\u00a7\u00a7\">1.9. dar ci\u00eancia ao Instituto Federal de Educa\u00e7\u00e3o, Ci\u00eancia e Tecnologia do Rio Grande do Norte sobre as impropriedades a seguir arroladas, indicadas no Relat\u00f3rio de Auditoria Anual 201800583, da Controladoria Regional da Uni\u00e3o no Estado do Rio Grande do Norte, relativo ao exerc\u00edcio de 2017, para que sejam informadas, no pr\u00f3ximo relat\u00f3rio de gest\u00e3o da entidade, as medidas corretivas adotadas:</p><p class=\"tCU_-_Ac_-_item_9_-_\u00a7\u00a7\">1.9.1. aus\u00eancia do planejamento exigido pelo art. 18 da IN-MP/SLTI 04/2010, alterada pela IN MP/SLTI 04/2014, para as contrata\u00e7\u00f5es de bens e servi\u00e7os de inform\u00e1tica decorrentes dos Preg\u00f5es 85/2013, 31/2014, 240/2014 e 05/2015;</p><p class=\"tCU_-_Ac_-_item_9_-_\u00a7\u00a7\">1.9.2. aus\u00eancia de comprova\u00e7\u00e3o de vantagem em ades\u00f5es a atas de registro de pre\u00e7o dos Preg\u00f5es 58/2014, 78/2014, 240/2014, 05/2015 e 85/2015, o que contraria o disposto no art. 22 do Decreto 7.892/2013 e entendimentos deste Tribunal;</p><p class=\"tCU_-_Ac_-_item_9_-_\u00a7\u00a7\">1.9.3. inobserv\u00e2ncia de exig\u00eancias previstas nos arts. 8\u00ba e 9\u00ba da IN-MP/SLTI 04/2010, art. 1\u00ba do Decreto 7.903/2013 e art. 3\u00ba, inciso II, do Decreto 7.174/2010, que versam sobre aquisi\u00e7\u00e3o de equipamentos de tecnologia da informa\u00e7\u00e3o e comunica\u00e7\u00e3o, quando do lan\u00e7amento do Preg\u00e3o 36/2013, destinado \u00e0 aquisi\u00e7\u00e3o de equipamentos de videoconfer\u00eancia no valor de R$ 638.288,51;</p><p class=\"tCU_-_Ac_-_item_9_-_\u00a7\u00a7\">1.9.4. aus\u00eancia de normativo interno estabelecendo crit\u00e9rios para carga hor\u00e1ria exigida dos bolsistas e pagamentos no modelo Bolsa Forma\u00e7\u00e3o da Rede e-Tec, contrariando o item 5.2 do Manual de Gest\u00e3o da Rede e-Tec Brasil e do Perfuncion\u00e1rio de 2016;</p><p class=\"tCU_-_Ac_-_item_9_-_\u00a7\u00a7\">1.9.5. aus\u00eancia de relat\u00f3rios gerenciais para verifica\u00e7\u00e3o do cumprimento da carga hor\u00e1ria dos bolsistas no Ambiente Virtual de Aprendizagem e identifica\u00e7\u00e3o de desvio de fun\u00e7\u00e3o de bolsistas da Rede e-Tec;</p><p class=\"tCU_-_Ac_-_item_9_-_\u00a7\u00a7\">1.9.6. pagamento de bolsas da Rede e-Tec a benefici\u00e1rios do Sistema de Gest\u00e3o de Bolsas, para fins de repasse dos valores a outros bolsistas que n\u00e3o teriam recebido na \u00e9poca devida;</p><p class=\"tCU_-_Ac_-_item_9_-_\u00a7\u00a7\">1.9.7. contrata\u00e7\u00e3o de bolsistas do Sistema de Gest\u00e3o de Bolsas da Rede e-Tec sem a publica\u00e7\u00e3o de edital, contrariando o art. 6\u00ba da Resolu\u00e7\u00e3o-CD/FNDE  36/2009;</p><p class=\"tCU_-_Ac_-_item_9_-_\u00a7\u00a7\">1.9.8. inconsist\u00eancias na contrata\u00e7\u00e3o de bolsistas professores-pesquisadores conteudistas via Sistema de Gest\u00e3o de Bolsas da Rede e-Tec, a saber, contrata\u00e7\u00e3o sem edital, em desobedi\u00eancia ao art. 6\u00ba da Resolu\u00e7\u00e3o-CD/FNDE  36/2009; aus\u00eancia de documenta\u00e7\u00e3o comprobat\u00f3ria do cumprimento dos requisitos exigidos pela Resolu\u00e7\u00e3o-CD/FNDE 18/2010 para contrata\u00e7\u00e3o; pagamento pela produ\u00e7\u00e3o de material sem a correspondente entrega; e pagamentos efetuados em valores diferentes ao contratado;</p><p class=\"tCU_-_Ac_-_item_9_-_\u00a7\u00a7\">1.9.9. inexist\u00eancia de informa\u00e7\u00e3o gerencial que permita verificar o cumprimento da carga hor\u00e1ria dos bolsistas no Ambiente Virtual de Aprendizagem do sistema Universidade Aberta do Brasil; </p><p class=\"tCU_-_Ac_-_item_9_-_\u00a7\u00a7\">1.9.10. contrata\u00e7\u00e3o de professores conteudistas do sistema UAB sem publica\u00e7\u00e3o de edital, contrariando o art. 7\u00ba da Portaria-Capes 183/2016; e</p><p class=\"tCU_-_Ac_-_item_9_-_\u00a7\u00a7\">1.9.11. aus\u00eancia de diplomas e diverg\u00eancia significativa entre os pareceres emitidos no processo 23424.046185.2017-70, de Retribui\u00e7\u00e3o por Titula\u00e7\u00e3o por Reconhecimento de Saberes e Compet\u00eancias, o que indica fragilidades no processo avaliativo;</p><p class=\"tCU_-_Ac_-_item_9_-_\u00a7\u00a7\">1.10. determinar \u00e0 Controladoria Regional da Uni\u00e3o no Estado do Rio Grande do Norte que inclua no pr\u00f3ximo relat\u00f3rio de auditoria anual de contas a ser encaminhado a este Tribunal as provid\u00eancias adotadas pelo Instituto Federal de Educa\u00e7\u00e3o, Ci\u00eancia e Tecnologia do Rio Grande do Norte em vista dos fatos apontados no item 1.9. desta delibera\u00e7\u00e3o.</p><p class=\"tCU_-__Ac_-_item_9_-_1\u00aa_Linha\"/><p class=\"tCU_-__Ac_-_item_9_-_1\u00aa_Linha\"/><p class=\"footer\"/>", "COLEGIADO": "Primeira C\u00e2mara", "DATASESSAO": "02/04/2019", "ENTIDADE": " Instituto Federal de Educa\u00e7\u00e3o, Ci\u00eancia e Tecnologia do Rio Grande do Norte", "INTERESSADOS": " Agamenon Henrique de Carvalho Tavares (XXX.347.444-XX); Alailson de Freitas Braz (XXX.957.574-XX); Albino Oliveira Nunes (XXX.593.424-XX); Allan David Garcia de Araujo (XXX.178.164-XX); Ambr\u00f3sio Lins do Nascimento (XXX.155.544-XX); Ana Carolina Bezerra de Melo Costa (XXX.141.085-XX); Ana Maria Cardoso de Oliveira Bezerra (XXX.528.804-XX); Ana Maria da Silva (XXX.762.724-XX); Andre Gustavo Duarte de Almeida (XXX.867.564-XX); Andreilson Oliveira da Silva (XXX.002.674-XX); Annaterra Teixeira de Lima (XXX.054.154-XX); Anne Gabrielle Lima dos Santos (XXX.115.304-XX); Antenor Mario da Silva (XXX.802.634-XX); Auridan Dantas de Ara\u00fajo (XXX.839.904-XX); Bernardo Eneas de Araujo Nascimento (XXX.632.364-XX); Brenda Maria Pessoa de Carvalho (XXX.480.034-XX); Bruna Lais Campos do Nascimento (XXX.940.404-XX); Bruno Gomes de Araujo (XXX.452.224-XX); Camila Nascimento de Oliveira Taumaturgo (XXX.189.084-XX); Camilo Soares de Medeiros Junior (XXX.735.424-XX); Carlos Andre de Oliveira (XXX.646.604-XX); Cintia Gouveia Costa (XXX.877.824-XX); Daniela Karina Candido (XXX.382.014-XX); Darlyne Fontes Virginio (XXX.955.881-XX); Diderot Franco Sampaio Junior (XXX.254.024-XX); Ednaldo de Paiva Pereira (XXX.118.334-XX); Elizomar de Assis Nobre (XXX.859.397-XX); Emanuel Gomes Lourenco (XXX.715.262-XX); Emerson da Cunha Batista (XXX.684.464-XX); Eraldy Kennedy de Sousa Chagas (XXX.311.094-XX); Erasmo Jose Pereira de Oliveira (XXX.932.774-XX); Erico Cadineli Braz (XXX.240.254-XX); Fellipe Neri de Oliveira Arrais (XXX.174.484-XX); Fernanda Ferreira da Costa Nunes (XXX.328.355-XX); Fernando Henrique da Silva (XXX.292.174-XX); Flavia Roberta Monteiro de Souza (XXX.394.504-XX); Francisco Fernandes de Oliveira (XXX.849.374-XX); Gustavo Henrique de Almeida Barbalho (XXX.465.144-XX); Isaias Amancio dos Santos (XXX.529.594-XX); Ivanilson Franca Vieira Junior (XXX.471.524-XX); Joao Bosco Cabral Freire (XXX.864.064-XX); Joao Henrique de Melo Ferraz (XXX.174.574-XX); Joao Marcos Ribeiro Martins (XXX.014.203-XX); Joao Maria Paiva Palhano (XXX.471.304-XX); Joao Maria de Oliveira (XXX.112.674-XX); Joao Rodrigo Silva de Carvalho (XXX.687.184-XX); Jose Cleyton Neves Lopes (XXX.310.064-XX); Jose Diego Cirne Santos (XXX.659.864-XX); Jose Ferreira da Silva Junior (XXX.183.664-XX); Jose Geraldo Bezerra Galvao Junior (XXX.107.604-XX); Jose Xavier da Camara Neto (XXX.267.044-XX); Jose de Ribamar Silva Oliveira (XXX.595.203-XX); Jos\u00e9 Arn\u00f3bio de Ara\u00fajo Filho (XXX.031.024-XX); Juan Carlo da Cruz Silva (XXX.317.584-XX); Juscelino Cardoso de Medeiros (XXX.066.944-XX); Karina Bezerra da Fonseca e Silva Martins (XXX.859.764-XX); Karolayne Paiva Bezerra de Lima (XXX.160.484-XX); Ligia Mara Gonzaga (XXX.705.064-XX); Luisa de Marilac de Castro Silva (XXX.593.453-XX); Luiz Carlos do Rego (XXX.315.051-XX); Maluh Brito Madruga (XXX.506.364-XX); Manoel Jusselino de Almeida e Silva (XXX.774.344-XX); Marcel Lucio Matias Ribeiro (XXX.596.374-XX); Marcelo Henrique Carneiro Camilo (XXX.748.534-XX); Marcio Adriano de Azevedo (XXX.017.014-XX); Marcones Marinho da Silva (XXX.939.744-XX); Marcos Antonio de Oliveira (XXX.622.154-XX); Maria Clara Fernandes Bezerra (XXX.506.354-XX); Maria Eduarda da Costa Andrade (XXX.893.194-XX); Maria Vitoria Torquato Pessoa (XXX.275.014-XX); Maria das Gracas de Araujo Varela (XXX.015.074-XX); Maria das Vitorias Dantas de Gois (XXX.385.104-XX); Maria dos Navegantes dos Santos da Silva (XXX.167.854-XX); Marlucia Viana Raposo Caldas (XXX.079.624-XX); Mikael Lucas da Silva Dionisio (XXX.328.764-XX); Nadir Arruda Skeete (XXX.079.064-XX); Pedro Brendo de La Sales Silas Felix de Medeiros (XXX.632.574-XX); Phelipe da Rocha Guimaraes (XXX.634.654-XX); Raquel Priscyla da Silva Costa (XXX.825.704-XX); Raul Aleixandre Fernandes de Queiroz (XXX.329.884-XX); Rinaldo Medeiros Alves de Oliveira (XXX.552.404-XX); Roberto Gomes Cavalcante Junior (XXX.648.744-XX); Rodrigo Siqueira Martins (XXX.042.434-XX); Romulo Flavio de Oliveira Santos (XXX.111.844-XX); Roseanne Azevedo de Albuquerque (XXX.787.134-XX); R\u00e9gia L\u00facia Lopes (XXX.560.944-XX); Samira Fernandes Delgado (XXX.480.361-XX); Sandoval Villaverde Monteiro (XXX.939.104-XX); Sandra Maria da Nobrega (XXX.706.574-XX); Sebastiao Bezerra (XXX.716.637-XX); Solange Marlene Thomaz (XXX.693.200-XX); Sonia Cristina Ferreira Maia (XXX.671.774-XX); Thiago Augusto Braz de Medeiros (XXX.916.334-XX); Thiago Fernando de Araujo Silva (XXX.672.634-XX); Thiago Jose de Azevedo Loureiro (XXX.330.784-XX); Thiago Lima de Oliveira (XXX.600.774-XX); Ticiana Patricia da Silveira Cunha (XXX.583.744-XX); Valdel\u00facio Pereira Ribeiro (XXX.484.314-XX); Valdemberg Magno do Nascimento Pessoa (XXX.976.603-XX); Valeria Oliveira Pontes Alencar de Carvalho (XXX.375.784-XX); Victor Varela Ferreira Medeiros de Oliveira (XXX.651.074-XX); Wyllys Abel Farkatt Tabosa (XXX.775.204-XX); Yarianne Melo de Sousa Gama (XXX.384.324-XX)", "PROC": "<a href=\"https://pesquisa.apps.tcu.gov.br/#/push/processo?numero=03358320188\" target=\"_blank\">033.583/2018-8</a>", "RECURSOS": [{"key": "ACORDAO-COMPLETO-2355137", "titulo": "Ac\u00f3rd\u00e3o 8535/2019 - Primeira C\u00e2mara", "tipo": "Ac\u00f3rd\u00e3o", "ano": "2019", "numero": "8535", "colegiado": "Primeira C\u00e2mara"}], "ACORDAOSRELACIONADOS": [{"key": "ACORDAO-COMPLETO-2355137", "titulo": "Ac\u00f3rd\u00e3o 8535/2019 - Primeira C\u00e2mara", "tipo": "Ac\u00f3rd\u00e3o", "ano": "2019", "numero": "8535", "colegiado": "Primeira C\u00e2mara"}], "RELATOR": "WALTON ALENCAR RODRIGUES", "ADVOGADO": " n\u00e3o h\u00e1.", "REPRESENTANTEMP": "Subprocurador-Geral Paulo Soares Bugarin", "SITUACAO": "OFICIALIZADO", "TIPOPROCESSO": "PRESTA\u00c7\u00c3O DE CONTAS (PC)", "UNIDADETECNICA": " Secretaria do TCU no Estado do Rio Grande do Norte (Sec-RN).", "DTATUALIZACAO": "20220925", "URLARQUIVO": "https://contas.tcu.gov.br/sisdoc/ObterDocumentoSisdoc?codVersao=editavel&codArqCatalogado=16514891", "URLARQUIVOPDF": "https://contas.tcu.gov.br/sisdoc/ObterDocumentoSisdoc?codArqCatalogado=16514891", "EXTENSAOARQUIVO": "doc"}