{"KEY": "ACORDAO-COMPLETO-2350049", "TIPO": "AC\u00d3RD\u00c3O", "TITULO": "AC\u00d3RD\u00c3O 3978/2019 ATA 17/2019 - PRIMEIRA C\u00c2MARA", "FAVORITO": false, "NUMACORDAO": "3978", "ANOACORDAO": "2019", "NUMATA": "17/2019", "ACORDAO": "<p class=\"tCU_-_Ac_-_item_9_-_\u00a7\u00a7\">VISTOS, relatados e discutidos estes autos de tomada de contas especial instaurada pela Funda\u00e7\u00e3o Nacional de Sa\u00fade (Funasa) , em desfavor de Luiz Ant\u00f4nio Pulch\u00e9rio Lopes Conde Bastos Rego Matos Souza, prefeito do Munic\u00edpio de V\u00e1rzea da Palma/MG durante o per\u00edodo de 2005 a 2012, em raz\u00e3o de omiss\u00e3o no dever de prestar contas do Termo de Compromisso 1.870/2008 (pe\u00e7a 1, p. 23-27) , Siafi 648843, celebrado com a referida municipalidade, com o objetivo de executar a\u00e7\u00e3o de melhoria habitacional para controle da doen\u00e7a de chagas, entre 31/12/2008 e 30/11/2011.</p><p class=\"tCU_-_Ac_-_item_9_-_\u00a7\u00a7\">ACORDAM os Ministros do Tribunal de Contas da Uni\u00e3o, reunidos em sess\u00e3o da Primeira C\u00e2mara e ante as raz\u00f5es expostas pelo Relator, em:</p><p class=\"tCU_-_Ac_-_item_9_-_\u00a7\u00a7\">9.1. declarar a revelia de Luiz Ant\u00f4nio Pulcherio Lopes Conde Bastos Rego Matos Souza (CPF XXX.191.686-XX) , e do Munic\u00edpio de V\u00e1rzea da Palma/MG (CNPJ 18.279.059/0001-26) nos termos do art. 12, \u00a7 3\u00ba  da Lei 8.443, de 16 de julho de 1992;</p><p class=\"tCU_-_Ac_-_item_9_-_\u00a7\u00a7\">9.2. excluir o Munic\u00edpio de V\u00e1rzea da Palma/MG (CNPJ 18.279.059/0001-26) do p\u00f3lo passivo da rela\u00e7\u00e3o jur\u00eddico-processual;</p><p class=\"tCU_-_Ac_-_item_9_-_\u00a7\u00a7\">9.3. julgar irregulares as contas de Luiz Ant\u00f4nio Pulch\u00e9rio Lopes Conde Bastos Rego Matos Souza (CPF XXX.191.686-XX) , com fundamento nos arts. 1\u00ba, inciso I, 16, inciso III, al\u00edneas \u201ca\u201d e \u201cc\u201d, 19, caput, e 23, inciso III, da Lei 8.443/1992 c/c com os arts. 1\u00ba, inciso I, 202, \u00a7 6\u00ba, 209, inciso I, 210 e 214, inciso III, do RI/TCU, condenando-o ao pagamento da import\u00e2ncia a seguir especificada, fixando-lhe o prazo de 15 dias para que comprove perante este Tribunal, em respeito ao art. 214, inciso III, al\u00ednea \u201ca\u201d, do RI/TCU, o recolhimento da d\u00edvida \u00e0 Funda\u00e7\u00e3o Nacional de Sa\u00fade (Funasa) , atualizada monetariamente e acrescida de juros de mora calculados a partir da data indicada at\u00e9 a data do efetivo recolhimento e com o abatimento de valores acaso j\u00e1 satisfeitos, nos termos da legisla\u00e7\u00e3o vigente:</p><p class=\"tCU_-_Ac_-_item_9_-_\u00a7\u00a7\"/><table><tbody><tr>\t<td><p class=\"tCU_-_Ac_-_item_9_-_\u00a7\u00a7\">VALOR ORIGINAL (R$) </p></td>\t<td><p class=\"tCU_-_Ac_-_item_9_-_\u00a7\u00a7\">DATA DA OCORR\u00caNCIA</p></td>\t<td><p class=\"tCU_-_Ac_-_item_9_-_\u00a7\u00a7\">D\u00e9bito/Cr\u00e9dito</p></td></tr><tr>\t<td><p class=\"tCU_-_Ac_-_item_9_-_\u00a7\u00a7\">205.767,86</p></td>\t<td><p class=\"tCU_-_Ac_-_item_9_-_\u00a7\u00a7\">24/6/2011</p></td>\t<td><p class=\"tCU_-_Ac_-_item_9_-_\u00a7\u00a7\">D\u00e9bito</p></td></tr><tr>\t<td><p class=\"tCU_-_Ac_-_item_9_-_\u00a7\u00a7\">3,01</p></td>\t<td><p class=\"tCU_-_Ac_-_item_9_-_\u00a7\u00a7\">14/08/2014</p></td>\t<td><p class=\"tCU_-_Ac_-_item_9_-_\u00a7\u00a7\">Cr\u00e9dito</p></td></tr></tbody></table><p class=\"tCU_-_Ac_-_item_9_-_\u00a7\u00a7\"/><p class=\"tCU_-_Ac_-_item_9_-_\u00a7\u00a7\">9.4. aplicar, com fundamento no art. 57 da Lei 8.443/1992 c/c o art. 267 do RI/TCU, multa a Luiz Ant\u00f4nio Pulch\u00e9rio Lopes Conde Bastos Rego Matos Souza (CPF XXX.191.686-XX) , no valor de R$ 257.000,00 (duzentos e cinquenta e sete mil reais) , fixando-lhe prazo de 15 dias, a partir da notifica\u00e7\u00e3o, para que, nos termos do art. 214, inciso III, al\u00ednea \u201ca\u201d, do RI/TCU, comprove perante este Tribunal o recolhimento aos cofres do Tesouro Nacional do valor atualizado monetariamente desde a data do ac\u00f3rd\u00e3o at\u00e9 a data do efetivo recolhimento, se for pago ap\u00f3s o vencimento, na forma da legisla\u00e7\u00e3o em vigor.</p><p class=\"tCU_-_Ac_-_item_9_-_\u00a7\u00a7\">9.5. autorizar, desde logo, a cobran\u00e7a judicial das d\u00edvidas nos termos do art. 28, inciso II, da Lei 8.443/1992 c/c o art. 219, inciso II, do RI/TCU, caso n\u00e3o seja atendida a notifica\u00e7\u00e3o.</p><p class=\"tCU_-_Ac_-_item_9_-_\u00a7\u00a7\">9.6. encaminhar c\u00f3pia da delibera\u00e7\u00e3o ao Procurador-Chefe da Procuradoria da Rep\u00fablica no estado de Minas Gerais, nos termos do \u00a7 3\u00ba do art. 16 da Lei 8.443/1992 c/c o \u00a7 7\u00ba do art. 209 do RI/TCU, para ado\u00e7\u00e3o das medidas que entender cab\u00edveis.</p>", "ASSUNTO": "Tomada de contas especial instaurada em raz\u00e3o de irregularidades na execu\u00e7\u00e3o de Termo de Compromisso firmado entre a Funda\u00e7\u00e3o Nacional de Sa\u00fade-Funasa e o Munic\u00edpio de V\u00e1rzea da  Palma-MG. An\u00e1lise de defesa.", "COLEGIADO": "Primeira C\u00e2mara", "DATASESSAO": "28/05/2019", "ENTIDADE": " Munic\u00edpio de V\u00e1rzea da Palma - MG.", "INTERESSADOS": "3. Interessados/Respons\u00e1veis:<br>3.1. Interessado: Funda\u00e7\u00e3o Nacional de Sa\u00fade (26.989.350/0001-16)<br>3.2. Respons\u00e1veis: Luiz Antonio Pulch\u00e9rio Lopes Conde Bastos Rego Matos de Souza (XXX.191.686-XX); Munic\u00edpio de V\u00e1rzea da Palma - MG (18.279.059/0001-26).", "PROC": "<a href=\"https://pesquisa.apps.tcu.gov.br/#/push/processo?numero=01665720152\" target=\"_blank\">016.657/2015-2</a>", "QUORUM": " <br>13.1. Ministros presentes: Benjamin Zymler (na Presid\u00eancia) e Walton Alencar Rodrigues (Relator).<br>13.2. Ministros-Substitutos convocados: Marcos Bemquerer Costa e Andr\u00e9 Lu\u00eds de Carvalho.<br>13.3. Ministro-Substituto presente: Weder de Oliveira.", "RELATOR": "WALTON ALENCAR RODRIGUES", "RELATORIO": "<p class=\"tCU_-_Rel/Voto_-_1\u00ba_\u00a7\"/><p class=\"tCU_-_Rel/Voto_-_1\u00ba_\u00a7\">Transcrevo, com os ajustes de forma, instru\u00e7\u00e3o cuja proposta foi acolhida pelo escal\u00e3o dirigente da Secretaria de Controle Externo no Estado de Minas Gerais e pelo Minist\u00e9rio P\u00fablico junto ao TCU (pe\u00e7as 77/79) :</p><p class=\"tCU_-_Transcri\u00e7\u00e3o\">INTRODU\u00c7\u00c3O</p><p class=\"tCU_-_Transcri\u00e7\u00e3o\">Cuidam os autos de tomada de contas especial instaurada pela Funda\u00e7\u00e3o Nacional de Sa\u00fade (Funasa) , em desfavor do Sr. Luiz Ant\u00f4nio Pulch\u00e9rio Lopes Conde Bastos Rego Matos Souza, prefeito municipal no per\u00edodo de 2005 a 2012, em raz\u00e3o de omiss\u00e3o no dever de prestar contas do Termo de Compromisso 1.870/2008 (pe\u00e7a 1, p. 23-27) , Siafi 648843, celebrado com o munic\u00edpio de V\u00e1rzea da Palma/MG, com o objetivo de executar a\u00e7\u00e3o de melhoria habitacional para controle da doen\u00e7a de chagas, entre 31/12/2008 e 30/11/2011.</p><p class=\"tCU_-_Transcri\u00e7\u00e3o\">HIST\u00d3RICO </p><p class=\"tCU_-_Transcri\u00e7\u00e3o\">2.\tO Exmo. Ministro Relator Walton Alencar Rodrigues, por meio de despacho (pe\u00e7a 33) , determinou o retorno dos presentes autos, \u201cpara que adote medidas para localiza\u00e7\u00e3o e nova cita\u00e7\u00e3o, t\u00e3o somente, do Sr. Luiz Ant\u00f4nio Pulch\u00e9rio Lopes Conde Bastos Rego Matos Souza, observadas as diretrizes tra\u00e7adas no voto condutor do <a href=\"https://pesquisa.apps.tcu.gov.br/#/doc/acordao-completo/1323/2016/Plen\u00e1rio\" target=\"_blank\">Ac\u00f3rd\u00e3o 1323/2016-TCU-Plen\u00e1rio</a> e no art. 6\u00ba, inciso II, al\u00ednea \u2018a\u2019, da Resolu\u00e7\u00e3o TCU 170/2004.</p><p class=\"tCU_-_Transcri\u00e7\u00e3o\">3.\tSobre o aludido assunto, o Ilmo. Procurador Rodrigo Medeiros de Lima consignou o seguinte (pe\u00e7a 32) :</p><p class=\"tCU_-_Transcri\u00e7\u00e3o\"> Quanto \u00e0 cita\u00e7\u00e3o ficta do Sr. Luiz Ant\u00f4nio Pulch\u00e9rio Lopes Conde Bastos Rego Matos Souza, percebe-se que os esfor\u00e7os para sua localiza\u00e7\u00e3o consistiram em consulta a sistema (pe\u00e7a 25) e \u00e0 p\u00e1gina da internet \u201cTeleListas.net\u201d (pe\u00e7a 26) \u2013 iniciativas aqu\u00e9m das preconizadas pelo <a href=\"https://pesquisa.apps.tcu.gov.br/#/doc/acordao-completo/1323/2016/Plen\u00e1rio\" target=\"_blank\">Ac\u00f3rd\u00e3o 1323/2016-TCU-Plen\u00e1rio</a> (Rel. Min. Benjamin Zymler) e seu Voto condutor:</p><p class=\"tCU_-_Transcri\u00e7\u00e3o\">\t\u201c21. Nessa linha, o atual C\u00f3digo de Processo Civil, aplicado subsidiariamente no \u00e2mbito desta Corte de Contas (art. 298 do Regimento Interno do TCU) , estabelece que:</p><p class=\"tCU_-_Transcri\u00e7\u00e3o\">\t(...) </p><p class=\"tCU_-_Transcri\u00e7\u00e3o\">\t\u00a7 3\u00ba O r\u00e9u ser\u00e1 considerado em local ignorado ou incerto se infrut\u00edferas as tentativas de sua localiza\u00e7\u00e3o, inclusive mediante requisi\u00e7\u00e3o pelo ju\u00edzo de informa\u00e7\u00f5es sobre seu endere\u00e7o nos cadastros de \u00f3rg\u00e3os p\u00fablicos ou de concession\u00e1rias de servi\u00e7os p\u00fablicos.</p><p class=\"tCU_-_Transcri\u00e7\u00e3o\">\t22. No caso concreto, verifica-se que n\u00e3o foram esgotados os meios para a localiza\u00e7\u00e3o da respons\u00e1vel, pois n\u00e3o foram efetuadas pesquisas junto a cadastros de \u00f3rg\u00e3os p\u00fablicos (v.g. departamento de tr\u00e2nsito) ou concession\u00e1rias de servi\u00e7os p\u00fablicos (v.g. empresas de telefonia e de fornecimento de energia el\u00e9trica) . Mesmo pesquisas na internet com maior densidade, incluindo redes sociais, poderia ter contribu\u00eddo para desvendar o paradeiro da respons\u00e1vel.\u201d</p><p class=\"tCU_-_Transcri\u00e7\u00e3o\"> No mesmo sentido, a Resolu\u00e7\u00e3o TCU n\u00ba 170/2004, em seu art. 6\u00ba, inciso II, al\u00ednea \u2018a\u2019, prescreve para o caso a \u201cconsulta a outros cadastros mantidos por institui\u00e7\u00f5es p\u00fablicas ou privadas que possam oferecer subs\u00eddios \u00e0 obten\u00e7\u00e3o do endere\u00e7o do destinat\u00e1rio\u201d.</p><p class=\"tCU_-_Transcri\u00e7\u00e3o\"> Em r\u00e1pida consulta realizada por este Minist\u00e9rio P\u00fablico na internet, percebe-se que o referido respons\u00e1vel concorreu \u00e0s elei\u00e7\u00f5es para prefeito, realizadas em 2016, no munic\u00edpio de V\u00e1rzea da Palma. Al\u00e9m disso, houve impugna\u00e7\u00e3o ao registro de sua candidatura junto ao Tribunal Regional Eleitoral de Minas Gerais (TRE/MG) , conforme consulta ao s\u00edtio deste Tribunal (http://apps.tre-mg.jus.br/aplicativos/php/divulga_plenario/index.php?acao=processo&nomenu=true&protocolo=3650512016) , sendo que o respons\u00e1vel foi corretamente notificado nesta a\u00e7\u00e3o. Assim, uma das poss\u00edveis maneiras de se obter o seu endere\u00e7o seria diligenciar ao Cart\u00f3rio Eleitoral da 310\u00aa ZE de V\u00e1rzea da Palma ou ao TRE/MG, solicitando informa\u00e7\u00f5es sobre o endere\u00e7o atualizado do aludido respons\u00e1vel.</p><p class=\"tCU_-_Transcri\u00e7\u00e3o\"> Diante das considera\u00e7\u00f5es apresentadas, este representante do Minist\u00e9rio P\u00fablico junto ao Tribunal de Contas da Uni\u00e3o, com as v\u00eanias de praxe, opina por que sejam os autos remetidos \u00e0 Unidade de origem a fim de que renove as medidas para localiza\u00e7\u00e3o e cita\u00e7\u00e3o do Sr. Luiz Ant\u00f4nio Pulch\u00e9rio Lopes Conde Bastos Rego Matos Souza, desta feita observando as diretrizes tra\u00e7adas pelo Voto condutor do <a href=\"https://pesquisa.apps.tcu.gov.br/#/doc/acordao-completo/1323/2016/Plen\u00e1rio\" target=\"_blank\">Ac\u00f3rd\u00e3o 1323/2016-TCU-Plen\u00e1rio</a> e no art. 6\u00ba, inciso II, al\u00ednea \u2018a\u2019, da Resolu\u00e7\u00e3o TCU n\u00ba 170/2004.</p><p class=\"tCU_-_Transcri\u00e7\u00e3o\">4.\tAp\u00f3s consulta ao sistema DGI Consultas, verificou-se que o endere\u00e7o utilizado para a cita\u00e7\u00e3o (Rua Dr. Ensch, 1101, Centro, V\u00e1rzea da Palma/MG, CEP 39.319-220) , conforme pe\u00e7as 18 e 19, \u00e9 o mesmo que consta nos cadastros do CPF-Receita Federal, TSE \u2013 Cadastro Eleitoral e RENACH \u2013 Registro Nacional de Carteira de Habilita\u00e7\u00e3o.</p><p class=\"tCU_-_Transcri\u00e7\u00e3o\">4.1\tO aludido respons\u00e1vel n\u00e3o possu\u00eda nenhum registro atual na base da RAIS \u2013 Rela\u00e7\u00e3o Anual de Informa\u00e7\u00f5es Sociais, mas foram encontrados os seguintes endere\u00e7os eletr\u00f4nicos: luci_apl_conde@hotmail.com e luizsoft@hotmail.com.</p><p class=\"tCU_-_Transcri\u00e7\u00e3o\">5.\tNo sentido de conferir maior seguran\u00e7a ao julgado a ser proferido por este Tribunal, conforme preconiza o Ilmo. Membro do MP/TCU, ratificado pelo despacho do Exmo. Ministro Relator, realizou-se dilig\u00eancia ao Cart\u00f3rio Eleitoral da 310\u00aa ZE de V\u00e1rzea da Palma ou ao TRE/MG, e \u00e0s concession\u00e1rias de fornecimento de \u00c1gua e Energia, respectivamente COPASA e CEMIG, bem como, junto aos aludidos endere\u00e7os eletr\u00f4nicos obtidos para que o respons\u00e1vel informe o endere\u00e7o atual.</p><p class=\"tCU_-_Transcri\u00e7\u00e3o\">6.\tEm resposta aos Of\u00edcios de Dilig\u00eancia 280/2017 (Copasa \u2013 pe\u00e7a 37) , 281/2017 (Cemig \u2013 pe\u00e7a 38) , 279/2017 (310\u00aa Zona Eleitoral de V\u00e1rzea da Palma \u2013 pe\u00e7a 39) e o pr\u00f3prio respons\u00e1vel (pe\u00e7a 40) , mas somente a 310\u00aa Zona Eleitoral de V\u00e1rzea da Palma apresentou novo endere\u00e7o do respons\u00e1vel, que \u00e9 Rua Esmeraldas, 1.056, bairro planalto, CEP: 39.260-000, V\u00e1rzea da Palma/MG. A Cemig e a Copasa, por meio dos documentos constantes das pe\u00e7as 48 e 51, informaram que o aludido respons\u00e1vel n\u00e3o est\u00e3o na base cadastral das respectivas empresas. O Sr. Luiz Ant\u00f4nio Pulch\u00e9rio Lopes Conde Bastos Rego Matos Souza n\u00e3o atendeu \u00e0 comunica\u00e7\u00e3o eletr\u00f4nica que lhe foi encaminhada (pe\u00e7a 45) .</p><p class=\"tCU_-_Transcri\u00e7\u00e3o\">6.1\tEm raz\u00e3o da obten\u00e7\u00e3o de novo endere\u00e7o obtido, junto a 310\u00aa Zona Eleitoral de V\u00e1rzea da Palma, e dos endere\u00e7os eletr\u00f4nicos obtidos (luci_apl_conde@hotmail.com e luizsoft@hotmail.com) , foram expedidos os of\u00edcios de cita\u00e7\u00e3o somente do respons\u00e1vel, Sr. Luiz Ant\u00f4nio Pulch\u00e9rio Lopes Conde Bastos Rego Matos Souza, na forma proposta na instru\u00e7\u00e3o constante da pe\u00e7a 15, par os seguintes endere\u00e7os:</p><p class=\"tCU_-_Transcri\u00e7\u00e3o\">Rua Esmeraldas, 1.056, bairro planalto, CEP: 39.260-000, V\u00e1rzea da Palma/MG.</p><p class=\"tCU_-_Transcri\u00e7\u00e3o\"> (luci_apl_conde@hotmail.com e luizsoft@hotmail.com) </p><p class=\"tCU_-_Transcri\u00e7\u00e3o\">6.2\tN\u00e3o obstante a expedi\u00e7\u00e3o dos Of\u00edcios 1.743/2018 (pe\u00e7as 54 e 57) , 2.408/2018 (pe\u00e7as 63 e 66) e 2.710/2018 (pe\u00e7as 67 e 70) que foram devolvidos, em raz\u00e3o do motivo \u201cn\u00e3o procurado\u201d, o encaminhamento da mensagem eletr\u00f4nica para os aludidos endere\u00e7os eletr\u00f4nicos (pe\u00e7as 68 e 76) , e ainda a publica\u00e7\u00e3o do Edital 0011/2018 (pe\u00e7a 75) , o respons\u00e1vel permaneceu silente, motivo pelo qual se deve promover o prosseguimento do   presente processo.</p><p class=\"tCU_-_Transcri\u00e7\u00e3o\">EXAME T\u00c9CNICO</p><p class=\"tCU_-_Transcri\u00e7\u00e3o\">7.\tPor oportuno, o presente processo j\u00e1 foi objeto de instru\u00e7\u00e3o t\u00e9cnica (pe\u00e7a 30) , por parte desta secretaria.</p><p class=\"tCU_-_Transcri\u00e7\u00e3o\">2.\t Conforme disposto na cl\u00e1usula terceira do termo de compromisso, foram previstos o valor de R$ 571.577,40 para a execu\u00e7\u00e3o do objeto, dos quais R$ 514.419,65 seriam repassados pelo concedente e R$ 57.157,75 corresponderiam \u00e0 contrapartida (pe\u00e7a 1, p. 62) . </p><p class=\"tCU_-_Transcri\u00e7\u00e3o\">3. \tOs recursos federais foram repassados parcialmente em duas parcelas, mediante as Ordens Banc\u00e1rias 2011OB804180 e 2011OB804181, nos respectivos valores de R$ 110.000,00 e R$ 95.767,86, emitidas em 21/6/2011, resultando no valor total de R$ 205.767,86. Os recursos foram creditados na conta espec\u00edfica 18.386-5, da ag\u00eancia 2765-0, do Banco do Brasil S/A em 24/6/2011 (pe\u00e7a 12, p. 23) . </p><p class=\"tCU_-_Transcri\u00e7\u00e3o\">4. \tO ajuste vigeu no per\u00edodo de 31/12/2008 a 30/11/2011, tendo o prazo final para a apresenta\u00e7\u00e3o da presta\u00e7\u00e3o de contas expirado em 29/1/2012, conforme extrato Siafi (pe\u00e7a 1, p. 371) . \t\t\t</p><p class=\"tCU_-_Transcri\u00e7\u00e3o\">5.\t Em cumprimento ao Despacho do diretor (pe\u00e7a 16) , foi promovida a cita\u00e7\u00e3o solid\u00e1ria do Sr. Luiz Ant\u00f4nio Pulch\u00e9rio Lopes Conde Bastos Rego Matos Souza, CPF XXX.191.686-XX, e do munic\u00edpio de V\u00e1rzea da Palma/MG, CNPJ: 18.279.059/0001-26, mediante o Edital 0068/2016 (pe\u00e7a 27) , publicado no DOU de 3/6/2016 (pe\u00e7a 28) , e o Of\u00edcio 888/2016 (pe\u00e7a 17) , datado de 19/4/2016, respectivamente.  </p><p class=\"tCU_-_Transcri\u00e7\u00e3o\">6.\tApesar de o munic\u00edpio de V\u00e1rzea da Palma/MG ter tomado ci\u00eancia do expediente que lhe foi encaminhado, conforme atesta o aviso de recebimento (AR) que comp\u00f5e a pe\u00e7a 23, constata-se que o mesmo n\u00e3o atendeu a cita\u00e7\u00e3o e nem se manifestou quanto \u00e0s irregularidades verificadas.</p><p class=\"tCU_-_Transcri\u00e7\u00e3o\">7.\tO Sr. Luiz Ant\u00f4nio Pulch\u00e9rio Lopes Conde Bastos Rego Matos Souza, citado regularmente por via edital\u00edcia, n\u00e3o atendeu a cita\u00e7\u00e3o e n\u00e3o se manifestou quanto \u00e0s irregularidades verificadas. Destaca-se que antes da cita\u00e7\u00e3o por edital foram adotadas provid\u00eancias que esgotaram as tentativas de localiza\u00e7\u00e3o do aludido respons\u00e1vel. De fato, diante do fato do respons\u00e1vel n\u00e3o ter sido localizado (v. pe\u00e7a 20, 24 e 25) o mesmo foi notificado, conforme despacho da subunidade (pe\u00e7a 26) , por meio do Edital 0068/2016 conforme art. 179, inciso III, do Regimento Interno do TCU.</p><p class=\"tCU_-_Transcri\u00e7\u00e3o\">8.\t Transcorrido o prazo regimental fixado e mantendo-se inerte os aludidos respons\u00e1veis, imp\u00f5e-se que sejam considerados rev\u00e9is, dando-se prosseguimento ao processo, de acordo com o art. 12, \u00a7 3\u00ba, da Lei 8.443/1992.</p><p class=\"tCU_-_Transcri\u00e7\u00e3o\">9.\tConforme consolidada jurisprud\u00eancia desta Corte de Contas, a exemplo dos Ac\u00f3rd\u00e3os 1.179/2011, 1.713/2015, 5.996/2014 e 5.118/2014, todos da 1\u00aa C\u00e2mara e 4.213/2016, 6.229/2016, 4.213/2016, 1.449/2013, todos da 2\u00aa C\u00e2mara, a presun\u00e7\u00e3o de boa-f\u00e9 de que goza a pessoa jur\u00eddica de direito p\u00fablico, nada obstante a revelia do Munic\u00edpio de V\u00e1rzea da Palma/MG, deve gerar como consequ\u00eancia a abertura de novo e improrrog\u00e1vel prazo para recolhimento do d\u00e9bito, na forma do disposto no artigo 202, \u00a7 3\u00ba, do Regimento Interno do TCU.</p><p class=\"tCU_-_Transcri\u00e7\u00e3o\">8.\tNo que diz respeito \u00e0 responsabiliza\u00e7\u00e3o do munic\u00edpio de V\u00e1rzea da Palma/MG, o MP/TCU entende que n\u00e3o caberia a sua responsabiliza\u00e7\u00e3o, com o que se concorda na presente instru\u00e7\u00e3o, tendo em vista o entendimento constante excerto do voto condutor do <a href=\"https://pesquisa.apps.tcu.gov.br/#/doc/acordao-completo/7783/2015/Primeira C\u00e2mara\" target=\"_blank\">Ac\u00f3rd\u00e3o 7783/2015-TCU-Primeira C\u00e2mara</a>, Rel. Min. Bruno Dantas:</p><p class=\"tCU_-_Transcri\u00e7\u00e3o\">\u201cA partir da transfer\u00eancia dos recursos da conta do conv\u00eanio para contas da prefeitura, torna-se imposs\u00edvel acompanhar a movimenta\u00e7\u00e3o financeira do conv\u00eanio. Portanto, se \u00e9 certo que os recursos repassados entraram nos cofres da prefeitura, sendo transferidos para outras contas movimento, a partir da qual eram feitos quase todos os pagamentos da entidade, n\u00e3o h\u00e1 qualquer ind\u00edcio seguro sobre qual o destino que lhes foi dado. N\u00e3o h\u00e1, ent\u00e3o, como presumir que tenham sido utilizados em benef\u00edcio do munic\u00edpio, nem como afastar acima de qualquer d\u00favida a possibilidade de desvio ou locupletamento do gestor municipal.'</p><p class=\"tCU_-_Transcri\u00e7\u00e3o\">\tA responsabiliza\u00e7\u00e3o de entes federados no \u00e2mbito do Tribunal depende da comprova\u00e7\u00e3o de que os recursos federais empregados em finalidade distinta daquela prevista no ajuste pactuado foram efetivamente utilizados em favor da comunidade. A simples realiza\u00e7\u00e3o de transfer\u00eancias da conta espec\u00edfica do conv\u00eanio para diversas contas da prefeitura n\u00e3o \u00e9 suficiente para atestar que o munic\u00edpio se beneficiou, de alguma forma, dos recursos federais envolvidos (<a href=\"https://pesquisa.apps.tcu.gov.br/#/doc/acordao-completo/1637/2015/Primeira C\u00e2mara\" target=\"_blank\">Ac\u00f3rd\u00e3o 1637/2015-TCU-Primeira C\u00e2mara</a>, 6.256/2014-Segunda C\u00e2mara) .\u201d.</p><p class=\"tCU_-_Transcri\u00e7\u00e3o\">9. \tNo que diz respeito a motiva\u00e7\u00e3o para a responsabiliza\u00e7\u00e3o do Sr. Luiz Ant\u00f4nio Pulch\u00e9rio Lopes Conde Bastos Rego Matos Souza, a instru\u00e7\u00e3o constante da pe\u00e7a 15 evidenciou os fatos atribu\u00edveis ao citado respons\u00e1vel e quantificou o d\u00e9bito, conforme transcri\u00e7\u00e3o abaixo.</p><p class=\"tCU_-_Transcri\u00e7\u00e3o\">5. \t Em resposta \u00e0s dilig\u00eancias promovidas por esta Secretaria, por meio dos Of\u00edcios 3.049/2015 e 3.050/2015, ambos datados de 17/11/2015 (pe\u00e7as 5 e 6) , a Prefeitura Municipal de V\u00e1rzea da Palma/MG e o Banco do Brasil apresentaram as informa\u00e7\u00f5es e/ou esclarecimentos a seguir, constantes das pe\u00e7as 11-14.</p><p class=\"tCU_-_Transcri\u00e7\u00e3o\">5.1\tO Banco do Brasil (pe\u00e7as 11 e 14) informou que os recursos do ajuste, sob exame, n\u00e3o transitaram pela conta da qual foi solicitado o extrato (17.052-6) , que foi aberta em 28/07/2010 e encerrada em 7/11/2011, sem receber qualquer recurso. </p><p class=\"tCU_-_Transcri\u00e7\u00e3o\">5.2\t O atual prefeito de V\u00e1rzea da Palma/MG respondeu \u00e0 dilig\u00eancia mediante o Of\u00edcio 001/2016, de 4/1/2016 (pe\u00e7a 12) , e encaminhou documenta\u00e7\u00e3o complementar (pe\u00e7as 12-13) . Verifica-se que as informa\u00e7\u00f5es enviadas suprem a aus\u00eancia de informa\u00e7\u00f5es do Banco do Brasil, visto que foi informada outra conta espec\u00edfica do conv\u00eanio, em que os recursos foram movimentados, e apresentado o extrato correspondente ao per\u00edodo de vig\u00eancia do ajuste, possibilitando o prosseguimento do processo.</p><p class=\"tCU_-_Transcri\u00e7\u00e3o\">6.\t  Em sua resposta, o gestor atual, que foi empossado ap\u00f3s a execu\u00e7\u00e3o do ajuste e o encerramento do prazo para presta\u00e7\u00e3o de contas, informou que constituiu Comiss\u00e3o Municipal, por meio da Portaria 17/2013, para proceder o levantamento de dados referentes ao ajuste em quest\u00e3o, tendo em vista o desvio de finalidade dos recursos, aus\u00eancia de presta\u00e7\u00e3o de contas final e o n\u00e3o cumprimento do objeto do termo de compromisso. Informou, tamb\u00e9m, que ao final dos trabalhos da Comiss\u00e3o, protocolou junto ao Minist\u00e9rio P\u00fablico Estadual, den\u00fancia contra os ex-gestores, para que fossem apuradas as responsabilidades na esfera penal, sem preju\u00edzo de san\u00e7\u00f5es na esfera c\u00edvel e administrativa, anexando c\u00f3pia da inicial (pe\u00e7a 12, p. 3-10) . Foram juntados ainda os seguintes documentos: </p><p class=\"tCU_-_Transcri\u00e7\u00e3o\">6.1 \tRelat\u00f3rio da Comiss\u00e3o Municipal, de 16/8/2013, com os respectivos anexos (pe\u00e7a 12, p. 12-16) , do qual se extrai:</p><p class=\"tCU_-_Transcri\u00e7\u00e3o\">\t- as verbas foram transferidas para a conta 18.386-5, ag\u00eancia 2.765-0 do Banco do Brasil, no dia 24/6/2011, em dois repasses de R$ 110.000,00 e R$ 95.767,86, totalizando R$ 205.767,86;</p><p class=\"tCU_-_Transcri\u00e7\u00e3o\">\t- os recursos permaneceram aplicados at\u00e9 o dia 5/9/2012, quando foram transferidos                 R$ 220.000,00 para a conta 57.323-X, ag\u00eancia 2.765-0 do Banco do Brasil (conta de movimento geral da prefeitura) e R$ 140,00 para a conta 7.650-3, da mesma ag\u00eancia (conta de movimento da Secretaria Municipal de Sa\u00fade) , restando o saldo de R$ 2,83 (corrigido at\u00e9 17/6/2013) ; </p><p class=\"tCU_-_Transcri\u00e7\u00e3o\">\t- informa\u00e7\u00e3o repassada pela Sra. Rosangely Martins Ferro, de que a verba de R$ 220.000,00 foi usada para pagamentos diversos da administra\u00e7\u00e3o geral, sendo quase imposs\u00edvel a sua identifica\u00e7\u00e3o;</p><p class=\"tCU_-_Transcri\u00e7\u00e3o\">\t- segundo o relat\u00f3rio, a Comiss\u00e3o Municipal concluiu que as constru\u00e7\u00f5es n\u00e3o foram feitas e os recursos foram desviados para outros fins.</p><p class=\"tCU_-_Transcri\u00e7\u00e3o\">6.2\t O Extrato da conta corrente e de aplica\u00e7\u00e3o financeira 18.386-5, ag\u00eancia 2765-0 do Banco do Brasil, relativo ao per\u00edodo 24/6/2011 a 31/5/2013, e os comprovantes de transfer\u00eancia (pe\u00e7a 12, p. 26-27) atestam o destino dado aos recursos, bem como o comprovante de pagamento de pe\u00e7a 13, p. 22, atesta a devolu\u00e7\u00e3o do saldo ao concedente, em 14/8/2014.</p><p class=\"tCU_-_Transcri\u00e7\u00e3o\">7.\tA an\u00e1lise dos autos permitiu identificar os seguintes aspectos com respeito \u00e0 execu\u00e7\u00e3o do ajuste: </p><p class=\"tCU_-_Transcri\u00e7\u00e3o\">\ta) n\u00e3o comprova\u00e7\u00e3o da boa e regular aplica\u00e7\u00e3o dos recursos federais configurada por omiss\u00e3o no dever de prestar contas. Segundo o Parecer Financeiro 190, de 2/7/2014, em visita t\u00e9cnica ao munic\u00edpio, em 18/10/2012, foi verificado que o processo licitat\u00f3rio para a execu\u00e7\u00e3o do objeto n\u00e3o havia sido conclu\u00eddo, bem como, n\u00e3o houve a apresenta\u00e7\u00e3o da presta\u00e7\u00e3o de contas parcial, fato que impediu os repasses seguintes. Segundo os extratos juntados ao presente processo, observa-se que os recursos permaneceram na aplica\u00e7\u00e3o vinculada \u00e0 conta espec\u00edfica at\u00e9 5/9/2012, quando foi transferido o valor de R$ 220.140,00 (pe\u00e7a 12, p. 25-27) , sendo R$ 220.000,00 para a conta 57.323-X, ag\u00eancia 2.765-0, do Banco do Brasil (conta de movimento geral da prefeitura) e R$ 140,00 para a conta 7.650-3, da mesma ag\u00eancia (conta de movimento da Secretaria Municipal de Sa\u00fade) . Em 14/8/2014, o munic\u00edpio convenente restituiu o saldo da conta espec\u00edfica, no valor de R$ 3,01 (pe\u00e7a 1, p. 333) ; </p><p class=\"tCU_-_Transcri\u00e7\u00e3o\">\tb) o objeto no qual foi identificada a constata\u00e7\u00e3o: Termo de Compromisso 1.870/2008 (pe\u00e7a 1, p. 23-27) , Siafi 648843; </p><p class=\"tCU_-_Transcri\u00e7\u00e3o\">\tc) os crit\u00e9rios: art. 37, caput c/c o art. 70, par\u00e1grafo \u00fanico, da Constitui\u00e7\u00e3o da Rep\u00fablica Federativa do Brasil, art. 93 do Decreto- lei 200/67, art. 66 do Decreto 93.872/1986, art. 28 da IN STN 1/1997 ou art. 56 da Portaria Interministerial 127/2008 ou art. 72 da Portaria Interministerial 507/2011 e cl\u00e1usula terceira e quarta do Termo de Compromisso 1.870/2008; </p><p class=\"tCU_-_Transcri\u00e7\u00e3o\">\td) as evid\u00eancias: o Parecer Financeiro 190 (pe\u00e7a 1, p. 219-220) , de 2/7/2014, o Parecer T\u00e9cnico Final (pe\u00e7a 1, p. 209-211) , e o Relat\u00f3rio de Visita T\u00e9cnica (pe\u00e7a 1, p. 213-215) , de 3/12/2012; </p><p class=\"tCU_-_Transcri\u00e7\u00e3o\">\te) Efeito potencial: impossibilidade de aferir a regularidade na aplica\u00e7\u00e3o dos recursos federais transferidos, por conseguinte, caracterizando o dano ao er\u00e1rio.</p><p class=\"tCU_-_Transcri\u00e7\u00e3o\">\tf) o desfecho sucinto: propor a cita\u00e7\u00e3o do Sr. Luiz Ant\u00f4nio Pulch\u00e9rio Lopes Conde Bastos Rego Matos Souza, em solidariedade com o munic\u00edpio de V\u00e1rzea da Palma/MG, que se beneficiou da transfer\u00eancia da totalidade dos recursos (R$ 205.767,86, em valores originais) para sua conta de movimento geral e a conta de movimento da Secretaria Municipal de Sa\u00fade, possibilitando seu uso para fins diversos. O prefeito sucessor n\u00e3o deve ser responsabilizado pelo d\u00e9bito, visto n\u00e3o haver participado da execu\u00e7\u00e3o do ajuste e n\u00e3o ser respons\u00e1vel pela presta\u00e7\u00e3o de contas, tendo adotado medidas pertinentes de defesa do er\u00e1rio.</p><p class=\"tCU_-_Transcri\u00e7\u00e3o\">\tg) a identifica\u00e7\u00e3o e qualifica\u00e7\u00e3o dos respons\u00e1veis: </p><p class=\"tCU_-_Transcri\u00e7\u00e3o\">\tRespons\u00e1vel 1: Sr. Luiz Ant\u00f4nio Pulch\u00e9rio Lopes Conde Bastos Rego Matos Souza (CPF XXX.191.686-XX) , prefeito municipal de V\u00e1rzea da Palma/MG nas gest\u00f5es 2005-2008 e 2009-2012;</p><p class=\"tCU_-_Transcri\u00e7\u00e3o\">\tConduta: </p><p class=\"tCU_-_Transcri\u00e7\u00e3o\">\ta) assinar o Termo de Compromisso 1.870/2008, responsabilizando-se pela execu\u00e7\u00e3o do objeto e presta\u00e7\u00e3o de contas do ajuste, sem cumprir o ajustado; </p><p class=\"tCU_-_Transcri\u00e7\u00e3o\">\tb) permitir indevidamente a transfer\u00eancia dos recursos do termo de compromisso para a conta de movimento geral da prefeitura e para a conta de movimento da Secretaria Municipal de Sa\u00fade, possibilitando o desvio de finalidade ou a m\u00e1 gest\u00e3o na sua utiliza\u00e7\u00e3o, vez que n\u00e3o foi comprovada a destina\u00e7\u00e3o dos referidos recursos; </p><p class=\"tCU_-_Transcri\u00e7\u00e3o\">\tc) omitir-se no dever de prestar contas do ajuste, deixando de comprovar o destinat\u00e1rio final dos pagamentos efetuados e, em consequ\u00eancia, a regular utiliza\u00e7\u00e3o dos recursos repassados ao munic\u00edpio;</p><p class=\"tCU_-_Transcri\u00e7\u00e3o\">\tNexo de causalidade entre a conduta e o resultado il\u00edcito: a omiss\u00e3o no dever de prestar contas e a transfer\u00eancia dos recursos para contas de movimento geral da prefeitura possibilitou sua utiliza\u00e7\u00e3o em desconformidade com os termos do ajuste e impediu conhecer o real emprego dos recursos;  </p><p class=\"tCU_-_Transcri\u00e7\u00e3o\">\tCulpabilidade: a gest\u00e3o dos recursos em desconformidade com os normativos, bem como a omiss\u00e3o no dever de prestar contas comprometem a transpar\u00eancia e possibilitam desvios de finalidade no emprego dos recursos. </p><p class=\"tCU_-_Transcri\u00e7\u00e3o\">\t(...) .</p><p class=\"tCU_-_Transcri\u00e7\u00e3o\">7.1\t Do d\u00e9bito: o d\u00e9bito a ser atribu\u00eddo aos respons\u00e1veis corresponde ao valor total de                 R$ 205.767,86 transferido ao munic\u00edpio, em 24/6/2011, visto que foram desviados para finalidade distinta daquela para a qual foram repassados ao munic\u00edpio de V\u00e1rzea da Palma.</p><p class=\"tCU_-_Transcri\u00e7\u00e3o\">10.\tNos termos do art. 12, \u00a7 3\u00ba, da Lei 8.443/1992, ao n\u00e3o responder \u00e0 cita\u00e7\u00e3o expedida por esta Corte de Contas, a respons\u00e1vel torna-se revel, para todos os efeitos, dando-se prosseguimento ao processo. </p><p class=\"tCU_-_Transcri\u00e7\u00e3o\">11.\tA despeito da aplica\u00e7\u00e3o da revelia, devem ser considerados, no entanto, os elementos j\u00e1 constantes dos autos, os quais podem, inclusive, levar a um ju\u00edzo favor\u00e1vel ao respons\u00e1vel revel. </p><p class=\"tCU_-_Transcri\u00e7\u00e3o\">12.\tDeve-se observar que, nos processos do TCU, a revelia n\u00e3o implica a presun\u00e7\u00e3o de que sejam verdadeiras todas as imputa\u00e7\u00f5es levantadas contra os respons\u00e1veis, diferentemente do que ocorre no processo civil, em que o n\u00e3o comparecimento do r\u00e9u nos autos leva \u00e0 presun\u00e7\u00e3o da verdade dos fatos narrados pelo autor. </p><p class=\"tCU_-_Transcri\u00e7\u00e3o\">13.\t Assim, independentemente da revelia, a avalia\u00e7\u00e3o da responsabilidade do agente nos processos desta Corte n\u00e3o prescinde dos elementos existentes nos autos ou para ele carreados, uma vez que s\u00e3o regidos pelo princ\u00edpio da verdade material (<a href=\"https://pesquisa.apps.tcu.gov.br/#/doc/acordao-completo/163/2015/Segunda C\u00e2mara\" target=\"_blank\">Ac\u00f3rd\u00e3o 163/2015-TCU-Segunda C\u00e2mara</a>, Rel.  Andr\u00e9 de Carvalho; 2.685/2015-TCU-2\u00aa C\u00e2mara, Rel. Raimundo Carreiro; 2.801/2015-TCU-1a C\u00e2mara, Rel. Walton Alencar Rodrigues; 4.340/2015-TCU-1\u00aa C\u00e2mara, Rel. Weder De Oliveira e 5.537/2015-TCU-1a C\u00e2mara, Rel. Weder de Oliveira) .</p><p class=\"tCU_-_Transcri\u00e7\u00e3o\">14.\tEntretanto, cabe destacar que nas fases anteriores desta TCE o respons\u00e1vel tamb\u00e9m n\u00e3o se manifestou quanto a apresenta\u00e7\u00e3o da presta\u00e7\u00e3o de contas, mantendo-se omisso (pe\u00e7a 1, p. 356, item 9) .</p><p class=\"tCU_-_Transcri\u00e7\u00e3o\">15.\tAdicionalmente, a irregularidade imputada ao respons\u00e1vel, configurada pela omiss\u00e3o na apresenta\u00e7\u00e3o da presta\u00e7\u00e3o de contas e pela retirada indevida dos recursos federais da conta especifica do Termo de Compromisso 1.870/2008 (pe\u00e7a 1, p. 23-27) , que n\u00e3o permitiu conferir a regularidade na execu\u00e7\u00e3o dos recursos federais descentralizados, da\u00ed decorrendo o dano ao Er\u00e1rio, est\u00e1 claramente demonstrada nos autos, al\u00e9m de que inexistem elementos que possam ser aproveitados na defesa do respons\u00e1vel.</p><p class=\"tCU_-_Transcri\u00e7\u00e3o\">16.\tAssim, transcorrido o prazo regimental fixado e mantendo-se inerte o aludido respons\u00e1vel, imp\u00f5e-se que seja considerado revel, dando-se prosseguimento ao processo, de acordo com o art. 12, \u00a7 3\u00ba, da Lei 8.443/1992.</p><p class=\"tCU_-_Transcri\u00e7\u00e3o\">CONCLUS\u00c3O</p><p class=\"tCU_-_Transcri\u00e7\u00e3o\">17.\tDiante da revelia do respons\u00e1vel, Sr. Luiz Ant\u00f4nio Pulch\u00e9rio Lopes Conde Bastos Rego Matos Souza, e inexistindo nos autos elementos que permitam concluir pela ocorr\u00eancia de boa-f\u00e9 ou de outros excludentes de culpabilidade em sua conduta, prop\u00f5e-se que suas contas sejam julgadas irregulares e que o respons\u00e1vel seja condenado em d\u00e9bito, bem como que lhe seja aplicado a multa prevista no art. 57 da Lei 8.443/1992.</p><p class=\"tCU_-_Transcri\u00e7\u00e3o\">PROPOSTA DE ENCAMINHAMENTO</p><p class=\"tCU_-_Transcri\u00e7\u00e3o\">18.\tDiante do exposto, submetemos os autos, \u00e0 considera\u00e7\u00e3o superior, propondo o seguinte:</p><p class=\"tCU_-_Transcri\u00e7\u00e3o\">18.1\tconsiderar revel o Sr. Luiz Ant\u00f4nio Pulch\u00e9rio Lopes Conde Bastos Rego Matos Souza (CPF XXX.191.686-XX) , de acordo com o \u00a7 3\u00ba, inciso IV, do art. 12, da Lei 8.443, de 16 de julho de 1992;</p><p class=\"tCU_-_Transcri\u00e7\u00e3o\">18.2\tjulgar irregulares as contas do Sr. Luiz Ant\u00f4nio Pulch\u00e9rio Lopes Conde Bastos Rego Matos Souza (CPF XXX.191.686-XX) , com fundamento nos arts. 1\u00ba, inciso I, 16, inciso III, al\u00edneas \u201ca\u201d e \u201cc\u201d, 19, caput, e 23, inciso III, da Lei 8.443/1992 c/c com os arts. 1\u00ba, inciso I, 209, inciso I, 210 e 214, inciso III, do RI/TCU, condenando-o ao pagamento das import\u00e2ncias a seguir especificadas e fixando-lhe o prazo de 15 dias para que comprove perante este Tribunal, em respeito ao art. 214, inciso III, al\u00ednea \u201ca\u201d, do RI/TCU, o recolhimento da d\u00edvida aos cofres do Funda\u00e7\u00e3o Nacional de Sa\u00fade \u2013 Funasa, atualizada monetariamente e acrescida de juros de mora calculados a partir das datas indicadas at\u00e9 a data do efetivo recolhimento e com o abatimento de valores acaso j\u00e1 satisfeitos, nos termos da legisla\u00e7\u00e3o vigente:</p><table><tbody><tr>\t<td><p class=\"body_Text\"><i>VALOR ORIGINAL (R$) </i></p></td>\t<td><p class=\"body_Text\"><i>DATA DA OCORR\u00caNCIA</i></p></td></tr><tr>\t<td><p class=\"body_Text\"><i>205.767,86</i></p></td>\t<td><p class=\"body_Text\"><i>24/6/2011</i></p></td></tr></tbody></table><p class=\"tCU_-_Transcri\u00e7\u00e3o\">                          </p><p class=\"tCU_-_Transcri\u00e7\u00e3o\">18.3\t<b>aplicar</b>, com fundamento no art. 57 da Lei 8.443/1992 c/c o art. 267 do RI/TCU, multa ao Sr. Luiz Ant\u00f4nio Pulch\u00e9rio Lopes Conde Bastos Rego Matos Souza (CPF XXX.191.686-XX) , fixando o prazo de 15 dias, a partir da notifica\u00e7\u00e3o, para que, nos termos do art. 214, inciso III, al\u00ednea \u201ca\u201d, do RI/TCU, comprove perante este Tribunal o recolhimento aos cofres do Tesouro Nacional do valor atualizado monetariamente desde a data do ac\u00f3rd\u00e3o at\u00e9 a data do efetivo recolhimento, se for pago ap\u00f3s o vencimento, na forma da legisla\u00e7\u00e3o em vigor.</p><p class=\"tCU_-_Transcri\u00e7\u00e3o\">18.4<b>\tautorizar</b>, desde logo, a cobran\u00e7a judicial da d\u00edvida nos termos do art. 28, inciso II, da Lei 8.443/1992 c/c o art. 219, inciso II, do RI/TCU, caso n\u00e3o atendida a notifica\u00e7\u00e3o.</p><p class=\"tCU_-_Transcri\u00e7\u00e3o\">18.5 \t<b>autorizar</b>, desde logo, com fundamento no art. 26, da Lei 8.443/1992 c/c o art. 217, do Regimento Interno do TCU, caso seja do interesse do respons\u00e1vel, o parcelamento da d\u00edvida em at\u00e9 36 parcelas, incidindo, sobre cada uma, os encargos legais devidos, sem preju\u00edzo de alert\u00e1-la de que, caso opte por essa forma de pagamento, a falta de comprova\u00e7\u00e3o do recolhimento de qualquer parcela implicar\u00e1 o vencimento antecipado do saldo devedor, nos termos do art. 26, par\u00e1grafo \u00fanico, e 59, da Lei 8.443/1992 c/c o art. 217, \u00a7 2\u00ba, do Regimento Interno do TCU; e,</p><p class=\"tCU_-_Transcri\u00e7\u00e3o\">18.6<b> \tencaminhar</b> c\u00f3pia da delibera\u00e7\u00e3o, bem como do relat\u00f3rio e do voto que a fundamentarem, ao Procurador-Chefe da Procuradoria da Rep\u00fablica no estado de Minas Gerais, nos termos do \u00a7 3\u00ba do art. 16 da Lei 8.443/1992 c/c o \u00a7 7\u00ba do art. 209 do RI/TCU, para ado\u00e7\u00e3o das medidas que entender cab\u00edveis.</p><p class=\"tCU_-_Rel/Voto_-_1\u00ba_\u00a7\"/><p class=\"tCU_-_Rel/Voto_-_1\u00ba_\u00a7\"/><p class=\"footer\"/>", "ADVOGADO": " n\u00e3o h\u00e1", "REPRESENTANTEMP": "Procurador Rodrigo Medeiros de Lima.", "SITUACAO": "OFICIALIZADO", "SUMARIO": "TOMADA DE CONTAS ESPECIAL. TERMO DE COMPROMISSO. FUNASA. EXECU\u00c7\u00c3O DE MELHORIAS HABITACIONAIS PARA CONTROLE DA DOEN\u00c7A CHAGAS. OMISS\u00c3O NO DEVER DE PRESTAR CONTAS. INEXECU\u00c7\u00c3O DO OBJETO. CITA\u00c7\u00c3O DO EX-GESTOR E DO ENTE MUNICIPAL. REVELIA. AUS\u00caNCIA DE COMPROVA\u00c7\u00c3O DE EFETIVO PROVEITO DOS RECURSOS PELO MUNIC\u00cdPIO. EXCLUS\u00c3O DO POLO PASSIVO DA RELA\u00c7\u00c3O JUR\u00cdDICO-PROCESSUAL. RESPONSABILIDADE EXCLUSIVA DO EX-DIRIGENTE MUNICIPAL. D\u00c9BITO. MULTA. CI\u00caNCIA. Somente pode ser arrolada a responsabilidade do ente municipal por eventual desvio de objeto na aplica\u00e7\u00e3o de recursos federais oriundos de transfer\u00eancia volunt\u00e1ria, se comprovado efetivo proveito em favor daquela unidade federativa.", "TIPOPROCESSO": "TOMADA DE CONTAS ESPECIAL (TCE)", "UNIDADETECNICA": " Secretaria de Controle Externo de Tomada de Contas Especial (SecexTCE).", "VOTO": "<p class=\"tCU_-_Rel/Voto_-_1\u00ba_\u00a7\">Cuidam os autos de tomada de contas especial instaurada pela Funda\u00e7\u00e3o Nacional de Sa\u00fade (Funasa) , em desfavor de Luiz Ant\u00f4nio Pulch\u00e9rio Lopes Conde Bastos Rego Matos Souza, prefeito de V\u00e1rzea da Palma/MG durante o per\u00edodo de 2005 a 2012, em raz\u00e3o de omiss\u00e3o no dever de prestar contas do Termo de Compromisso 1.870/2008 (pe\u00e7a 1, p\u00e1gs. 23/27) , celebrado entre a Funasa e o Munic\u00edpio, cujo objeto \u00e9 a execu\u00e7\u00e3o de melhorias habitacionais para preven\u00e7\u00e3o e controle do vetor da doen\u00e7a de chagas.</p><p class=\"tCU_-_Rel/Voto_-_1\u00ba_\u00a7\">De acordo com a cl\u00e1usula terceira do instrumento, foi previsto o valor de R$ 571.577,40 para custeio do objeto do ajuste, dos quais R$ 514.419,65 seriam assumidos pelo concedente e R$ 57.157,75 corresponderiam \u00e0 contrapartida municipal (pe\u00e7a 1, p. 62) . No entanto, a Funasa repassou a quantia de R$ 205.767,86, creditada na conta corrente espec\u00edfica em 24/06/2011 (pe\u00e7a 12, p\u00e1g. 23) . O ajuste vigeu no per\u00edodo de 31/12/2008 a 30/11/2011, j\u00e1 consideradas as prorroga\u00e7\u00f5es por aditivo. </p><p class=\"tCU_-_Rel/Voto_-_1\u00ba_\u00a7\">Verificada a inadimpl\u00eancia do respons\u00e1vel em n\u00e3o comprovar a regular execu\u00e7\u00e3o do objeto do termo de compromisso e n\u00e3o apresentada a respectiva a presta\u00e7\u00e3o de contas, debalde as tentativas da Funasa para reaver o valor em alcance, foi instaurada tomada de contas especial, da qual foi certificada a irregularidade das contas e imputado d\u00e9bito integral a Luiz Ant\u00f4nio Pulch\u00e9rio Lopes Conde Bastos Rego Matos Souza, bem como tomou ci\u00eancia autoridade m\u00e1xima competente.</p><p class=\"tCU_-_Rel/Voto_-_1\u00ba_\u00a7\">Perante esta Corte de Contas, Luiz Ant\u00f4nio Pulch\u00e9rio Lopes Conde Bastos Rego Matos Souza e o Munic\u00edpio V\u00e1rzea da Palma/MG foram regularmente instados a apresentar defesa ou a recolher o d\u00e9bito \u00e0 Funda\u00e7\u00e3o Nacional de Sa\u00fade (pe\u00e7as 17, 20, 23, 24 e 25) . Os respons\u00e1veis quedaram-se inertes, arcando com o \u00f4nus da revelia, nos termos do artigo 12, \u00a7 3\u00ba, da Lei 8.443/1992.</p><p class=\"tCU_-_Rel/Voto_-_1\u00ba_\u00a7\">Ap\u00f3s realizar dilig\u00eancia junto ao Banco do Brasil e \u00e0 Prefeitura de V\u00e1rzea da Palma/MG (pe\u00e7as 12/13) , a Secretaria de Controle Externo no Estado de Minas Gerais verificou que os recursos do termo de compromisso permaneceram aplicados na conta espec\u00edfica do ajuste (Ag\u00eancia 2.765-0, conta 18.386-5) at\u00e9 o dia 5/9/2012.</p><p class=\"tCU_-_Rel/Voto_-_1\u00ba_\u00a7\">A partir dessa data, foram transferidos R$ 220.000,00 para a conta 57.323-X, ag\u00eancia 2.765-0 do Banco do Brasil (conta de movimento geral da prefeitura) e R$ 140,00 para a conta 7.650-3, da mesma ag\u00eancia (conta de movimento da Secretaria Municipal de Sa\u00fade) , restando o saldo de R$ 2,83 (corrigido at\u00e9 17/6/2013) .</p><p class=\"tCU_-_Rel/Voto_-_1\u00ba_\u00a7\">De acordo as informa\u00e7\u00f5es coligidas aos autos e as conclus\u00f5es do Relat\u00f3rio de Comiss\u00e3o Municipal de 16/8/2013 (pe\u00e7a 12, p\u00e1gs. 12/16) , a unidade t\u00e9cnica verificou que n\u00e3o foram realizadas as a\u00e7\u00f5es de melhorias domiciliares com vistas a prevenir a prolifera\u00e7\u00e3o do vetor da doen\u00e7a de chagas. Identificou tamb\u00e9m desvio de finalidade ante a realiza\u00e7\u00e3o de pagamentos diversos de interesse da administra\u00e7\u00e3o municipal, embora n\u00e3o se possa identificar essas despesas. Registra restitui\u00e7\u00e3o \u00e0 Funasa quantia de R$ 3,01, em 14/08/2014.</p><p class=\"tCU_-_Rel/Voto_-_1\u00ba_\u00a7\">Observa que, ao t\u00e9rmino dos trabalhos da comiss\u00e3o institu\u00edda pelo atual prefeito de V\u00e1rzea da Palma/MG, foi protocolada junto ao Minist\u00e9rio P\u00fablico Estadual den\u00fancia contra o ex-gestores para que fossem apuradas responsabilidade na esfera penal, sem preju\u00edzo das san\u00e7\u00f5es na esfera c\u00edvel e administrativa (pe\u00e7a 12, p\u00e1gs. 3/10) .</p><p class=\"tCU_-_Rel/Voto_-_1\u00ba_\u00a7\">N\u00e3o obstante a revelia do ente subnacional, a unidade instrutiva prop\u00f5e afastar a responsabilidade do Munic\u00edpio de V\u00e1rzea do Palma/MG, uma vez que n\u00e3o h\u00e1 como comprovar que os recursos federais tenham sido empregados em finalidade distinta daquela acordada no termo de compromisso e que tenham efetivamente beneficiado a comunidade. Nesse sentido, alinha os <a href=\"https://pesquisa.apps.tcu.gov.br/#/doc/acordao-completo/1637/2015/Primeira C\u00e2mara\" target=\"_blank\">Ac\u00f3rd\u00e3o 1637/2015-TCU-Primeira C\u00e2mara</a>, 7.783/2015-1\u00aa C\u00e2mara e 6.256/2014-2\u00aa C\u00e2mara.</p><p class=\"tCU_-_Rel/Voto_-_1\u00ba_\u00a7\">Com fundamento nos arts. 1\u00ba, inciso I, 12, \u00a7 3\u00ba, 16, inciso III, al\u00edneas \u201ca\u201d e \u201cc\u201d, 19, <i>caput</i>, e 23, inciso III, e 57 da Lei 8.443/1992, conclui por declarar a revelia e julgar irregulares as contas de Luiz Ant\u00f4nio Pulch\u00e9rio Lopes Conde Bastos Rego Matos Souza, condenando-o ao ressarcimento da integralidade dos valores transferidos pela Funasa e ao pagamento de san\u00e7\u00e3o pecuni\u00e1ria individual.</p><p class=\"tCU_-_Rel/Voto_-_1\u00ba_\u00a7\">Desde logo, sugere a autoriza\u00e7\u00e3o para cobran\u00e7a judicial da d\u00edvida caso n\u00e3o sejam atendidas as notifica\u00e7\u00f5es de d\u00e9bito, conforme artigo 28, inciso II, da Lei 8.443/1992.</p><p class=\"tCU_-_Rel/Voto_-_1\u00ba_\u00a7\">Em arremate, alvitra encaminhamento de c\u00f3pia da delibera\u00e7\u00e3o, bem como do relat\u00f3rio e do voto que a fundamentam ao Minist\u00e9rio P\u00fablico Federal para ajuizamento das a\u00e7\u00f5es penais e civis que entender cab\u00edveis, conforme art. 16, \u00a7 3\u00ba, da Lei 8.443/1992 c/c o art. 209, \u00a7 7\u00ba do RI/TCU.</p><p class=\"tCU_-_Rel/Voto_-_1\u00ba_\u00a7\">O Minist\u00e9rio P\u00fablico junto ao TCU manifestou-se de acordo com a proposta da unidade t\u00e9cnica.</p><p class=\"tCU_-_Rel/Voto_-_1\u00ba_\u00a7\">Feito esse hist\u00f3rico, passo a decidir.</p><p class=\"tCU_-_Rel/Voto_-_1\u00ba_\u00a7\">Aquies\u00e7o aos pareceres uniformes da unidade t\u00e9cnica e do Minist\u00e9rio P\u00fablico de Contas, cujos fundamentos incorporo ao meu voto.</p><p class=\"tCU_-_Rel/Voto_-_1\u00ba_\u00a7\">Com espeque no artigo 12, \u00a7 3\u00ba, da Lei 8.443/1992, declaro a revelia de Luiz Ant\u00f4nio Pulch\u00e9rio Lopes Conde e do Munic\u00edpio de V\u00e1rzea da Palma/MG, os quais, apesar de regularmente convocados, n\u00e3o compareceram aos autos para apresentar defesa.</p><p class=\"tCU_-_Rel/Voto_-_1\u00ba_\u00a7\">O ex-prefeito Luiz Ant\u00f4nio Pulch\u00e9rio Lopes Conde Bastos Rego Matos Souza assumiu a inteira responsabilidade pela omiss\u00e3o no dever de prestar contas dos recursos do Termo de Compromisso 1.870/2008, dando causa \u00e0 inexecu\u00e7\u00e3o do objeto do ajuste ao n\u00e3o realizar melhorias habitacionais para preven\u00e7\u00e3o e controle do vetor da doen\u00e7a de chagas.</p><p class=\"tCU_-_Rel/Voto_-_1\u00ba_\u00a7\">Tamb\u00e9m contribuiu para a indevida transfer\u00eancia dos recursos da Uni\u00e3o da conta banc\u00e1ria vinculada ao ajuste para a conta de movimento geral da prefeitura, bem como para conta de movimenta\u00e7\u00e3o de valores da Secretaria Municipal de Sa\u00fade, sem que se saiba a destina\u00e7\u00e3o desses valores, seja na execu\u00e7\u00e3o do objeto do termo de compromisso, seja na realiza\u00e7\u00e3o despesas de interesse do ente municipal. </p><p class=\"tCU_-_Rel/Voto_-_1\u00ba_\u00a7\">O rompimento do nexo causal entre receita vinculada ao acordo e a aus\u00eancia de comprova\u00e7\u00e3o de aplica\u00e7\u00e3o da despesa no objeto do plano de trabalho, no caso operada com a mera transfer\u00eancia de verba federal da conta espec\u00edfica do termo de compromisso para outras contas de ente subnacional, n\u00e3o geram presun\u00e7\u00e3o de que o munic\u00edpio tenha sido indevidamente beneficiado. </p><p class=\"tCU_-_Rel/Voto_-_1\u00ba_\u00a7\">O Tribunal tem firme jurisprud\u00eancia de que somente pode ser arrolada a responsabilidade do ente municipal por eventual desvio de objeto na aplica\u00e7\u00e3o de recursos federais oriundos de transfer\u00eancia volunt\u00e1ria, se comprovado efetivo proveito em favor daquela unidade federativa. Nessa vereda, cito os <a href=\"https://pesquisa.apps.tcu.gov.br/#/doc/acordao-completo/3347/2019/Primeira C\u00e2mara\" target=\"_blank\">Ac\u00f3rd\u00e3o 3347/2019-TCU-Primeira C\u00e2mara</a>, 2.181/2018-1\u00aa C\u00e2mara, 7.585/2015-1\u00aa C\u00e2mara, 1.885/2015-Plen\u00e1rio. </p><p class=\"tCU_-_Rel/Voto_-_1\u00ba_\u00a7\">Por essas raz\u00f5es, excluo o Munic\u00edpio de V\u00e1rzea da Palma/MG do polo passivo da presente rela\u00e7\u00e3o jur\u00eddico-processual. </p><p class=\"tCU_-_Rel/Voto_-_1\u00ba_\u00a7\">Resta, assim, configurada grave viola\u00e7\u00e3o da norma legal de natureza financeira, de responsabilidade exclusiva de Luiz Ant\u00f4nio Pulch\u00e9rio Lopes Conde Bastos Rego Matos Souza. O ex-gestor municipal violou as disposi\u00e7\u00f5es contidas no art. 37, caput c/c o art. 70, par\u00e1grafo \u00fanico, da Constitui\u00e7\u00e3o da Rep\u00fablica Federativa do Brasil, art. 93 do Decreto-lei 200/67, art. 66 do Decreto 93.872/1986, art. 28 da IN STN 1/1997 ou art. 56 da Portaria Interministerial 127/2008 ou art. 72 da Portaria Interministerial 507/2011 e cl\u00e1usula terceira e quarta do Termo de Compromisso 1.870/2008.</p><p class=\"tCU_-_Rel/Voto_-_1\u00ba_\u00a7\">Ante o exposto e com fundamento nos arts. 1\u00ba, inciso I, 16, inciso III, al\u00edneas \u201ca\u201d e \u201cc\u201d, 19, caput, e 23, inciso III, da Lei 8.443/1992 c/c com os arts. 1\u00ba, inciso I, 202, \u00a7 6\u00ba, 209, inciso I, 210 e 214, inciso III, do RI/TCU, julgo irregulares as contas de Luiz Ant\u00f4nio Pulch\u00e9rio Lopes Conde, condenando-o a ressarcir \u00e0 Funda\u00e7\u00e3o Nacional de Sa\u00fade a integralidade dos valores repassados por meio do Termo de Compromisso 1.870/2008, deduzida a import\u00e2ncia j\u00e1 recolhida \u00e0 entidade concedente, nos termos da legisla\u00e7\u00e3o em vigor:</p><table><tbody><tr>\t<td><p class=\"tCU_-_Ac_-_item_9_-_\u00a7\u00a7\">VALOR ORIGINAL (R$) </p></td>\t<td><p class=\"tCU_-_Ac_-_item_9_-_\u00a7\u00a7\">DATA DA OCORR\u00caNCIA</p></td>\t<td><p class=\"tCU_-_Ac_-_item_9_-_\u00a7\u00a7\">D\u00e9bito/Cr\u00e9dito</p></td></tr><tr>\t<td><p class=\"tCU_-_Ac_-_item_9_-_\u00a7\u00a7\">205.767,86</p></td>\t<td><p class=\"tCU_-_Ac_-_item_9_-_\u00a7\u00a7\">24/6/2011</p></td>\t<td><p class=\"tCU_-_Ac_-_item_9_-_\u00a7\u00a7\">D\u00e9bito</p></td></tr><tr>\t<td><p class=\"tCU_-_Ac_-_item_9_-_\u00a7\u00a7\">3,01</p></td>\t<td><p class=\"tCU_-_Ac_-_item_9_-_\u00a7\u00a7\">14/08/2014</p></td>\t<td><p class=\"tCU_-_Ac_-_item_9_-_\u00a7\u00a7\">Cr\u00e9dito</p></td></tr></tbody></table><p class=\"tCU_-_Rel/Voto_-_1\u00ba_\u00a7\">                 Valor do d\u00e9bito, atualizado em 22/04/2019: R$ 321.464,42</p><p class=\"tCU_-_Rel/Voto_-_1\u00ba_\u00a7\">Com suped\u00e2neo no artigo 57 da Lei 8.443/1992, aplico a Luiz Ant\u00f4nio Pulch\u00e9rio Lopes Conde multa no valor de R$ 257.000,00 (duzentos e cinquenta e sete mil reais) a ser recolhida ao Tesouro Nacional, na forma da legisla\u00e7\u00e3o em vig\u00eancia.</p><p class=\"tCU_-_Rel/Voto_-_1\u00ba_\u00a7\">Autorizo, desde logo, a cobran\u00e7a judicial das d\u00edvidas caso n\u00e3o seja atendida a notifica\u00e7\u00e3o pelo respons\u00e1vel, nos termos do artigo 28, inciso II, da Lei Org\u00e2nica do TCU.</p><p class=\"tCU_-_Rel/Voto_-_1\u00ba_\u00a7\">Por fim, encaminho c\u00f3pia da delibera\u00e7\u00e3o, bem como do relat\u00f3rio e do voto que a fundamentam, ao Procurador-Chefe da Procuradoria da Rep\u00fablica no estado de Minas Gerais, nos termos do \u00a7 3\u00ba do art. 16 da Lei 8.443/1992 c/c o \u00a7 7\u00ba do art. 209 do RI/TCU, para ado\u00e7\u00e3o das medidas que entender cab\u00edveis.</p><p class=\"tCU_-_Rel/Voto_-_1\u00ba_\u00a7\">Feitas essas considera\u00e7\u00f5es, voto por que o Tribunal acolha a minuta de ac\u00f3rd\u00e3o que ora submeto \u00e0 delibera\u00e7\u00e3o do colegiado.</p><p class=\"body_Text\">TCU, Sala das Sess\u00f5es Ministro Luciano Brand\u00e3o Alves de Souza, em 28 de maio de 2019.</p><p class=\"body_Text\"/><p class=\"body_Text\"/><p class=\"body_Text\">WALTON ALENCAR RODRIGUES </p><p class=\"body_Text\">Relator</p><p class=\"footer\"/>", "DTATUALIZACAO": "20210620", "URLARQUIVO": "https://contas.tcu.gov.br/sagas/SvlVisualizarRelVotoAcRtf?codFiltro=SAGAS-SESSAO-ENCERRADA&seOcultaPagina=S&item0=662930", "URLARQUIVOPDF": "https://contas.tcu.gov.br/sagas/SvlVisualizarRelVotoAc?codFiltro=SAGAS-SESSAO-ENCERRADA&seOcultaPagina=S&item0=662930", "EXTENSAOARQUIVO": "doc", "CODPROCESSO": "53216327"}