{"KEY": "ACORDAO-COMPLETO-2356526", "TIPO": "AC\u00d3RD\u00c3O", "TITULO": "AC\u00d3RD\u00c3O 5123/2019 ATA 22/2019 - PRIMEIRA C\u00c2MARA", "FAVORITO": false, "NUMACORDAO": "5123", "ANOACORDAO": "2019", "NUMATA": "22/2019", "ACORDAO": "<p class=\"tCU_-_Ac_-_item_9_-_\u00a7\u00a7\">VISTOS, relatados e discutidos estes autos de recurso de reconsidera\u00e7\u00e3o interposto por Jo\u00e3o Soares Lyra Neto, ex-prefeito de Caruaru/PE, em face do <a href=\"https://pesquisa.apps.tcu.gov.br/#/doc/acordao-completo/4968/2017/Primeira C\u00e2mara\" target=\"_blank\">Ac\u00f3rd\u00e3o 4968/2017-TCU-Primeira C\u00e2mara</a>, por meio do qual esta Corte julgou suas contas irregulares, e condenou-o ao pagamento de d\u00e9bito e multa;</p><p class=\"tCU_-_Ac_-_item_9_-_\u00a7\u00a7\">ACORDAM os Ministros do Tribunal de Contas da Uni\u00e3o, reunidos em sess\u00e3o da 1\u00aa C\u00e2mara, ante as raz\u00f5es expostas pelo Relator, em:</p><p class=\"tCU_-_Ac_-_item_9_-_\u00a7\u00a7\">9.1. conhecer do recurso de reconsidera\u00e7\u00e3o, com fundamento nos arts. 32, inciso I e 33, da Lei 8.443/92 c/c o art. 285, <i>caput</i>, do RI/TCU, para, no m\u00e9rito, negar-lhe provimento;</p><p class=\"tCU_-_Ac_-_item_9_-_\u00a7\u00a7\">9.2. dar ci\u00eancia desta delibera\u00e7\u00e3o ao recorrente e aos demais interessados.</p><p class=\"tCU_-_Ac_-_item_9_-_\u00a7\u00a7\"/>", "ASSUNTO": "Recurso de reconsidera\u00e7\u00e3o contra decis\u00e3o de que julgou irregulares as contas do recorrente e o condenou ao pagamento de d\u00e9bito e multa em raz\u00e3o na inexecu\u00e7\u00e3o parcial de conv\u00eanio firmado com a Funda\u00e7\u00e3o Nacional de Sa\u00fade no \u00e2mbito do \u0093Programa de Controle de Doen\u00e7as End\u00eamicas em Caruaru.", "COLEGIADO": "Primeira C\u00e2mara", "DATASESSAO": "02/07/2019", "ENTIDADE": " Munic\u00edpio de Caruaru/PE.", "INTERESSADOS": "3. Recorrentes: Jo\u00e3o Soares Lyra Neto (XXX.956.924-XX).", "PROC": "<a href=\"https://pesquisa.apps.tcu.gov.br/#/push/processo?numero=02482720097\" target=\"_blank\">024.827/2009-7</a>", "QUORUM": " <br>13.1. Ministros presentes: Walton Alencar Rodrigues (Presidente), Benjamin Zymler e Vital do R\u00eago (Relator).<br>13.2. Ministro-Substituto convocado: Marcos Bemquerer Costa.<br>13.3. Ministros-Substitutos presentes: Augusto Sherman Cavalcanti e Weder de Oliveira.", "RECURSOS": [{"key": "ACORDAO-COMPLETO-2367548", "titulo": "Ac\u00f3rd\u00e3o 9798/2019 - Primeira C\u00e2mara", "tipo": "Ac\u00f3rd\u00e3o", "ano": "2019", "numero": "9798", "colegiado": "Primeira C\u00e2mara"}], "ACORDAOSRELACIONADOS": [{"key": "ACORDAO-COMPLETO-2367548", "titulo": "Ac\u00f3rd\u00e3o 9798/2019 - Primeira C\u00e2mara", "tipo": "Ac\u00f3rd\u00e3o", "ano": "2019", "numero": "9798", "colegiado": "Primeira C\u00e2mara"}], "RELATOR": "VITAL DO R\u00caGO", "RELATORDELIBERACAORECORRIDA": " Ministro Benjamin Zymler.", "RELATORIO": "<p class=\"tCU_-_Ep\u00edgrafe\">\tAdoto como relat\u00f3rio, com os ajustes de forma pertinentes, a instru\u00e7\u00e3o de m\u00e9rito carreada aos autos pela Secretaria de Recursos (pe\u00e7a 76) , a qual contou com a concord\u00e2ncia integral do seu dirigente e do representante do Minist\u00e9rio P\u00fablico junto ao TCU (pe\u00e7as 77 e 78) .</p><p class=\"tCU_-_Ep\u00edgrafe\">1. Trata-se de recurso de reconsidera\u00e7\u00e3o (pe\u00e7a 63) interposto por Jo\u00e3o Soares Lyra Neto contra o <a href=\"https://pesquisa.apps.tcu.gov.br/#/doc/acordao-completo/4968/2017/Primeira C\u00e2mara\" target=\"_blank\">Ac\u00f3rd\u00e3o 4968/2017-TCU-Primeira C\u00e2mara</a> (Pe\u00e7a 24) . </p><p class=\"tCU_-_Ep\u00edgrafe\">1.1. A delibera\u00e7\u00e3o recorrida apresenta o seguinte teor: </p><p class=\"tCU_________T2\">9.1. rejeitar as alega\u00e7\u00f5es de defesa do Sr. Jo\u00e3o Soares Lyra Neto;</p><p class=\"tCU_________T2\">9.2. com fundamento nos arts. 1\u00ba, inciso I, 16, inciso III, al\u00ednea \"c\", da Lei 8.443, de 1992, c/c os arts. 19 e 23, inciso III, da mesma lei, e nos arts. 1\u00ba, inciso I, 202, \u00a7 6\u00ba, 209, incisos I e II, e 214, inciso III, do Regimento Interno/TCU, julgar irregulares as contas do Sr. Jo\u00e3o Soares Lyra Neto, condenando-o ao pagamento das import\u00e2ncias abaixo discriminadas, fixando-lhe o prazo de 15 (quinze) dias, a contar da notifica\u00e7\u00e3o, para comprovar, perante este Tribunal, o recolhimento das d\u00edvidas aos cofres da Funda\u00e7\u00e3o Nacional de Sa\u00fade - Funasa, atualizadas monetariamente e acrescidas dos juros de mora a partir das datas indicadas, descontando-se os cr\u00e9ditos j\u00e1 efetuados:</p><table><tbody><tr>\t<td><p class=\"tCU_-_Ep\u00edgrafe\">Data</p></td>\t<td><p class=\"tCU_-_Ep\u00edgrafe\">Valor</p></td>\t<td><p class=\"tCU_-_Ep\u00edgrafe\">Natureza</p></td></tr><tr>\t<td><p class=\"tCU_-_Ep\u00edgrafe\">10/02/1998</p></td>\t<td><p class=\"tCU_-_Ep\u00edgrafe\">81.220,13</p></td>\t<td><p class=\"tCU_-_Ep\u00edgrafe\">D\u00e9bito</p></td></tr><tr>\t<td><p class=\"tCU_-_Ep\u00edgrafe\">10/02/1998</p></td>\t<td><p class=\"tCU_-_Ep\u00edgrafe\">80.749,00</p></td>\t<td><p class=\"tCU_-_Ep\u00edgrafe\">Cr\u00e9dito</p></td></tr><tr>\t<td><p class=\"tCU_-_Ep\u00edgrafe\">05/03/1998</p></td>\t<td><p class=\"tCU_-_Ep\u00edgrafe\">20.711,14</p></td>\t<td><p class=\"tCU_-_Ep\u00edgrafe\">D\u00e9bito</p></td></tr><tr>\t<td><p class=\"tCU_-_Ep\u00edgrafe\">05/02/1999</p></td>\t<td><p class=\"tCU_-_Ep\u00edgrafe\">20.711,14</p></td>\t<td><p class=\"tCU_-_Ep\u00edgrafe\">D\u00e9bito</p></td></tr><tr>\t<td><p class=\"tCU_-_Ep\u00edgrafe\">02/03/1999</p></td>\t<td><p class=\"tCU_-_Ep\u00edgrafe\">81.220,14</p></td>\t<td><p class=\"tCU_-_Ep\u00edgrafe\">D\u00e9bito</p></td></tr><tr>\t<td><p class=\"tCU_-_Ep\u00edgrafe\">10/03/1999</p></td>\t<td><p class=\"tCU_-_Ep\u00edgrafe\">121.018,00</p></td>\t<td><p class=\"tCU_-_Ep\u00edgrafe\">D\u00e9bito</p></td></tr><tr>\t<td><p class=\"tCU_-_Ep\u00edgrafe\">09/10/2000</p></td>\t<td><p class=\"tCU_-_Ep\u00edgrafe\">1.335,72</p></td>\t<td><p class=\"tCU_-_Ep\u00edgrafe\">Cr\u00e9dito</p></td></tr></tbody></table><p class=\"tCU_________T2\">9.3. aplicar ao Sr. Jo\u00e3o Soares Lyra Neto a multa referida no art. 57 da Lei n\u00ba 8.443/92, no valor de R$ 75.000,00 (setenta e cinco mil reais) , fixando-lhe o prazo de 15 (quinze) dias, a contar da notifica\u00e7\u00e3o, para que comprove perante o Tribunal (art. 23, inciso III, al\u00ednea \"a\" da Lei 8.443, de 1992 c/c o art. 214, inciso III, al\u00ednea \"a\" do RI/TCU) o recolhimento da d\u00edvida aos cofres do Tesouro Nacional, atualizada monetariamente, a contar da data deste ac\u00f3rd\u00e3o at\u00e9 a data do efetivo recolhimento, caso n\u00e3o seja paga no prazo estabelecido, na forma da legisla\u00e7\u00e3o em vigor;</p><p class=\"tCU_________T2\">9.4. autorizar, desde logo, com amparo no art. 28, inciso II da Lei 8.443, de 1992, a cobran\u00e7a judicial das d\u00edvidas, caso n\u00e3o atendidas as notifica\u00e7\u00f5es;</p><p class=\"tCU_________T2\">9.5. autorizar, desde j\u00e1, nos termos do art. 26 da Lei 8.443, de 1992, o parcelamento da d\u00edvida em at\u00e9 36 (trinta e seis) parcelas mensais e sucessivas, atualizadas monetariamente at\u00e9 a data do pagamento, esclarecendo ao respons\u00e1vel que a falta de pagamento de qualquer parcela importar\u00e1 no vencimento antecipado do saldo devedor (art. 217, \u00a7 2\u00ba, do RI/TCU) , sem preju\u00edzo das demais medidas legais;</p><p class=\"tCU_________T2\">9.6. encaminhar c\u00f3pia do presente ac\u00f3rd\u00e3o, bem como do relat\u00f3rio e do voto que o fundamentam, ao respons\u00e1vel, \u00e0 Funda\u00e7\u00e3o Nacional de Sa\u00fade e ao Munic\u00edpio de Caruaru/PE; </p><p class=\"tCU_________T2\">9.7. encaminhar c\u00f3pia deste ac\u00f3rd\u00e3o, bem como do relat\u00f3rio e do voto que o fundamentam, \u00e0 Procuradoria da Rep\u00fablica no Estado de Pernambuco, para ajuizamento das a\u00e7\u00f5es cab\u00edveis, nos termos do art. 209, \u00a7 7\u00ba, do Regimento Interno do TCU.</p><p class=\"tCU_-_Ep\u00edgrafe\"><b>HIST\u00d3RICO</b></p><p class=\"tCU_-_Ep\u00edgrafe\">2. Trata-se de tomada de contas especial instaurada pela Funda\u00e7\u00e3o Nacional de Sa\u00fade - Funasa em raz\u00e3o da inexecu\u00e7\u00e3o parcial do Conv\u00eanio 1723/1998, celebrado com o Munic\u00edpio de Caruaru/PE, objetivando a execu\u00e7\u00e3o de a\u00e7\u00f5es no \u00e2mbito do \"Programa de Controle de Doen\u00e7as End\u00eamicas em Caruaru, com a amplia\u00e7\u00e3o e reforma de pr\u00e9dio para a implanta\u00e7\u00e3o do Centro de Controle de Zoonoses\".</p><p class=\"tCU_-_Ep\u00edgrafe\">2.1. Para a consecu\u00e7\u00e3o do objeto da aven\u00e7a foi previsto o aporte de R$ 357.368,60, sendo R$ 324.800,55 destinados \u00e0 conta da concedente e o restante a cargo do Munic\u00edpio.</p><p class=\"tCU_-_Ep\u00edgrafe\">2.2. As vistorias e an\u00e1lises realizadas pelo concedente identificaram que o conv\u00eanio teve execu\u00e7\u00e3o parcial de 22,6% e registrou que as obras do pr\u00e9dio para a implanta\u00e7\u00e3o do Centro de Controle de Zoonoses n\u00e3o tinham condi\u00e7\u00f5es de ser aceitas<i>,</i> uma vez que se encontravam inacabadas, deterioradas pelas a\u00e7\u00f5es de v\u00e2ndalos, sem ter alcan\u00e7ado os benef\u00edcios sociais esperados (Relat\u00f3rio de Acompanhamento T\u00e9cnico, de 17/11/2000; Pareceres t\u00e9cnicos 122/2001, de 14/8/2001, 1/2002, de 11/1/2002, 79/2003, de 3/9/2003, 60/2006, de 24/8/2006; e Parecer Financeiro 48/2007, de 19/3/2007, constantes das pe\u00e7as 3 a 9) .</p><p class=\"tCU_-_Ep\u00edgrafe\">2.3. Ap\u00f3s desenvolvimento do processo, esta Corte de Contas, em conformidade com os exames da Funasa (entidade concedente) , concluiu que o conv\u00eanio teve execu\u00e7\u00e3o parcial e n\u00e3o alcan\u00e7ou os objetivos do pacto celebrado. </p><p class=\"tCU_-_Ep\u00edgrafe\">2.4. Dessa forma, decidiu-se, por meio do <a href=\"https://pesquisa.apps.tcu.gov.br/#/doc/acordao-completo/4968/2017/Primeira C\u00e2mara\" target=\"_blank\">Ac\u00f3rd\u00e3o 4968/2017-TCU-Primeira C\u00e2mara</a>, julgar irregulares as contas do respons\u00e1vel, condenando-o em d\u00e9bito e aplicando-lhe a multa no valor de R$ 75.000,00 do art. 57 da Lei 8.443/1992. </p><p class=\"tCU_-_Ep\u00edgrafe\">2.5. Ap\u00f3s o julgamento foram interpostos dois embargos de declara\u00e7\u00e3o, ambos conhecidos e rejeitados.</p><p class=\"tCU_-_Ep\u00edgrafe\">2.6. Neste momento, o recorrente insurge-se contra a delibera\u00e7\u00e3o previamente descrita.</p><p class=\"tCU_-_Ep\u00edgrafe\"><b>EXAME DE ADMISSIBILIDADE</b></p><p class=\"tCU_-_Ep\u00edgrafe\">3. Reitera-se o exame de admissibilidade contido nas pe\u00e7as 64-65, suspendendo-se os efeitos dos itens 9.2, 9.3 e 9.4 do <a href=\"https://pesquisa.apps.tcu.gov.br/#/doc/acordao-completo/4968/2017/Primeira C\u00e2mara\" target=\"_blank\">Ac\u00f3rd\u00e3o 4968/2017-TCU-Primeira C\u00e2mara</a>, ratificado pelo Ministro Relator Vital do R\u00eago Filho (despacho de pe\u00e7a 67) . </p><p class=\"tCU_-_Ep\u00edgrafe\"><b>EXAME DE M\u00c9RITO</b></p><p class=\"tCU_-_Ep\u00edgrafe\"><b>4. Delimita\u00e7\u00e3o</b></p><p class=\"tCU_-_Ep\u00edgrafe\">4.1. Constitui objeto do presente recurso definir se:</p><p class=\"tCU_-_Ep\u00edgrafe\">a) o parecer do engenheiro civil contratado pelo recorrente, bem como os argumentos enumerados s\u00e3o suficientes para afastar sua responsabilidade;</p><p class=\"tCU_-_Ep\u00edgrafe\">b) houve ilegalidade na multa aplicada e, portanto, injusta sua condena\u00e7\u00e3o; </p><p class=\"tCU_-_Ep\u00edgrafe\">c) houve prescri\u00e7\u00e3o do d\u00e9bito ou da multa.</p><p class=\"tCU_-_Ep\u00edgrafe\"><b>5. Da auditoria contratada pelo ex-Prefeito de Caruaru. </b></p><p class=\"tCU_-_Ep\u00edgrafe\">5.1. Defende-se no recurso que n\u00e3o foi apreciada e considerada no julgamento do ac\u00f3rd\u00e3o recorrido \"a auditoria contratada pela parte Recorrente e realizada por Engenheiro devidamente identificado\" (pe\u00e7a 37) , na qual teria se constado \"que parte da obra foi praticamente conclu\u00edda e hoje est\u00e1 em funcionamento\".</p><p class=\"tCU_-_Ep\u00edgrafe\">5.2. Dessa forma, ap\u00f3s transcrever os argumentos do laudo emitido pelo engenheiro por ele contratado, argumenta que:</p><p class=\"tCU_-_Ep\u00edgrafe\">a) o relat\u00f3rio esclarece que significativa parcela da obra foi executada e disponibilizada \u00e0 coletividade, conforme fotos anexadas aos autos (pe\u00e7a 37, p. 13-20) ;</p><p class=\"tCU_-_Ep\u00edgrafe\">b) a pr\u00f3pria Funasa reconheceu a execu\u00e7\u00e3o de 60% do conv\u00eanio, logo, haveria diverg\u00eancia entre valor da condena\u00e7\u00e3o e as obras efetivamente constru\u00eddas e disponibilizadas;</p><p class=\"tCU_-_Ep\u00edgrafe\">c) houve a compra de materiais de constru\u00e7\u00e3o e a execu\u00e7\u00e3o f\u00edsica da obra, mas o ac\u00f3rd\u00e3o n\u00e3o computou estas parcelas como gasto regular do conv\u00eanio;</p><p class=\"tCU_-_Ep\u00edgrafe\">d) n\u00e3o haveria possibilidade de o Munic\u00edpio Caruaru/PE firmar novos conv\u00eanios, requisitando novos recursos para dar continuidade de obras em andamento como requereu o ac\u00f3rd\u00e3o condenat\u00f3rio, uma vez que o mesmo objeto constava do pacto anterior em andamento, ademais, em janeiro de 2001 n\u00e3o era mais o gestor; </p><p class=\"tCU_-_Ep\u00edgrafe\">e) as obras sofreram paralisa\u00e7\u00e3o em decorr\u00eancia das chuvas que assolaram o munic\u00edpio e que provocou o atraso no cronograma de execu\u00e7\u00e3o, provocando a defasagem dos recursos necess\u00e1rios \u00e0 execu\u00e7\u00e3o do objeto;  </p><p class=\"tCU_-_Ep\u00edgrafe\">f) houve contradi\u00e7\u00e3o no julgado quanto \u00e0 necessidade de celebra\u00e7\u00e3o de aditivos, pois a aven\u00e7a deveria ser realizada pelo gestor sucessor, que n\u00e3o o fez e optou por efetuar a constru\u00e7\u00e3o de uma obra nova ao inv\u00e9s de concluir os servi\u00e7os j\u00e1 executados;</p><p class=\"tCU_-_Ep\u00edgrafe\">g) diversos julgados j\u00e1 reconheceram que \"meras irregularidades formais\" n\u00e3o s\u00e3o suficientes para a imposi\u00e7\u00e3o de d\u00e9bito ao jurisdicionado;</p><p class=\"tCU_-_Ep\u00edgrafe\">h) houve omiss\u00e3o no julgado acerca do abandono das obras pelo gestor sucessor, uma vez que at\u00e9 o final do exerc\u00edcio de 2000 quase 80% das obras estavam prontas e somente n\u00e3o foram conclu\u00eddas em raz\u00e3o do encerramento do seu mandato;</p><p class=\"tCU_-_Ep\u00edgrafe\">i) o plano de trabalho estava defasado e houve atraso no repasse dos recursos.</p><p class=\"tCU_-_Ep\u00edgrafe\">5.3. Por fim, em raz\u00e3o de o recorrente transcrever quase a integralidade da exposi\u00e7\u00e3o contida no parecer emitido por engenheiro contratado por ele (pe\u00e7a 37) , sintetiza-se o teor do documento como raz\u00f5es do recorrente.</p><p class=\"tCU_-_Ep\u00edgrafe\">5.4. Ap\u00f3s exame da manifesta\u00e7\u00e3o contida na pe\u00e7a 37, verifica-se que o subscritor, ap\u00f3s historiar os fatos inerentes ao pacto e \u00e0 fase interna da tomada de contas especial, tenta explicar as irregularidades constatadas no ac\u00f3rd\u00e3o. </p><p class=\"tCU_-_Ep\u00edgrafe\">5.5. Alega que entre o per\u00edodo no qual foi feito o plano de trabalho para a recupera\u00e7\u00e3o da edifica\u00e7\u00e3o e a libera\u00e7\u00e3o de recursos financeiros acentuaram-se os desgastes das edifica\u00e7\u00f5es e foram identificadas novas necessidades de recupera\u00e7\u00f5es com acr\u00e9scimo de quantitativos e do prazo de execu\u00e7\u00e3o das obras; de modo que o valor repassado n\u00e3o foi suficiente para concluir a obra.</p><p class=\"tCU_-_Ep\u00edgrafe\">5.6. Aduz que \"se tivessem as pequenas obras de acabamento sido executadas, e sido entregues as instala\u00e7\u00f5es executadas mesmo ap\u00f3s 06 (seis) anos ap\u00f3s o termino da gest\u00e3o do ex-Prefeito, a Presta\u00e7\u00e3o de Contas teria sido aceita\" pela Funasa, conforme se extrai dos pareceres do concedente (Parecer T\u00e9cnico 563/01e Parecer T\u00e9cnico 31/2007) ;</p><p class=\"tCU_-_Ep\u00edgrafe\">5.7. Argumenta tamb\u00e9m que, <i>verbis:</i>: </p><p class=\"tCU_________T2\">\"1. O significativo atraso de mais de 250 (duzentos e cinquenta) dias no repasse, fazendo com que o termo final do Convenio passasse para setembro do ano eleitoral de 2000. </p><p class=\"tCU_________T2\">2. Em face do desgaste das instala\u00e7\u00f5es existentes no per\u00edodo entre os primeiros levantamentos para a elabora\u00e7\u00e3o do Plano de Trabalho que instruiu o processo do Conv\u00eanio e o in\u00edcio das obras, al\u00e9m da identifica\u00e7\u00e3o de novas necessidades que s\u00f3 puderam ser identificadas com o in\u00edcio das obras, por se tratar de obra de reforma, houve necessidade de aditamento tanto do valor da obra como do prazo de sua execu\u00e7\u00e3o, aditamento este que n\u00e3o foi poss\u00edvel naquele momento, em raz\u00e3o da normatiza\u00e7\u00e3o da LRF.</p><p class=\"tCU_________T2\">3. (...) a aloca\u00e7\u00e3o de novos recursos se tornou imposs\u00edvel naquele final de exerc\u00edcio de 2000, devido \u00e0s limita\u00e7\u00f5es do artigo 9\u00b0 da Lei de Responsabilidade Fiscal, o que agravado pelo fato de a expira\u00e7\u00e3o da vig\u00eancia ter ocorrido naquele mesmo ano de 2000 e pela falta de experi\u00eancia para a solu\u00e7\u00e3o de impasses da natureza. </p><p class=\"tCU_________T2\">4. A dificuldade na contrata\u00e7\u00e3o de novas despesas que seriam repassadas para o exerc\u00edcio seguinte a cargo da nova gest\u00e3o.</p><p class=\"tCU_________T2\">5. Ressalte-se que as finan\u00e7as da municipalidade foram repassadas para o novo sucessor totalmente saneadas e em condi\u00e7\u00f5es para que o sucessor conclu\u00edsse de imediato a referida obra.\"</p><p class=\"tCU_-_Ep\u00edgrafe\">5.8. Ainda de acordo com o parecerista, as fotografias apresentadas comprovavam que haveria a necessidade de aloca\u00e7\u00e3o de pequena monta de recursos financeiros para que o objeto do conv\u00eanio pudesse ser entregue \u00e0 popula\u00e7\u00e3o (pe\u00e7a 37, p. 13-20) . </p><p class=\"tCU_-_Ep\u00edgrafe\">5.9. Por fim, aponta que os fatores que causaram a imediata entrega da unidade \u00e0 popula\u00e7\u00e3o consistiram na impossibilidade de se adotar novas despesas com a aquisi\u00e7\u00e3o de mobili\u00e1rio, equipamentos e acess\u00f3rios para o pleno funcionamento, bem como a dificuldade para contratar pessoal no fim da sua gest\u00e3o. E conclui, registrando que parte da obra que ficou quase pronta foi posta \u00e0 disposi\u00e7\u00e3o da popula\u00e7\u00e3o.</p><p class=\"tCU_-_Ep\u00edgrafe\"><b>An\u00e1lise:</b></p><p class=\"tCU_-_Ep\u00edgrafe\">5.10. Inicialmente \u00e9 importante mencionar que as raz\u00f5es recursais s\u00e3o estruturadas utilizando a manifesta\u00e7\u00e3o juntada \u00e0 pe\u00e7a 37 como prova da regular aplica\u00e7\u00e3o dos recursos. Em que pese o recorrente alegar que se tratou de uma auditoria por ele contratada, o mencionado documento, de fato, trata-se de um parecer elaborado por engenheiro civil inscrito no CREA-PE sob o n\u00famero 6.018. Verifica-se, portanto, tratar t\u00e3o somente de declara\u00e7\u00e3o de terceiro. </p><p class=\"tCU_-_Ep\u00edgrafe\">5.11. Segundo a jurisprud\u00eancia do TCU (<i>v.g</i> <a href=\"https://pesquisa.apps.tcu.gov.br/#/doc/acordao-completo/5407/2016/Segunda C\u00e2mara\" target=\"_blank\">Ac\u00f3rd\u00e3o 5407/2016-TCU-Segunda C\u00e2mara</a> e <a href=\"https://pesquisa.apps.tcu.gov.br/#/doc/acordao-completo/542/2015/Plen\u00e1rio\" target=\"_blank\">Ac\u00f3rd\u00e3o 542/2015-TCU-Plen\u00e1rio</a>) , as declara\u00e7\u00f5es de terceiros possuem baixa for\u00e7a probat\u00f3ria. Provam t\u00e3o-somente a exist\u00eancia da declara\u00e7\u00e3o, mas n\u00e3o o fato declarado. Assim, este Tribunal mant\u00e9m entendimento pac\u00edfico no sentido de que em sede de an\u00e1lise de contas de conv\u00eanios, as declara\u00e7\u00f5es prestadas por terceiros, por si s\u00f3, n\u00e3o s\u00e3o meios de prova capazes de atestar a efetiva execu\u00e7\u00e3o do objeto custeado com recursos p\u00fablicos federais.</p><p class=\"tCU_-_Ep\u00edgrafe\">5.12. A declara\u00e7\u00e3o, especificamente em rela\u00e7\u00e3o \u00e0 execu\u00e7\u00e3o do objeto, n\u00e3o \u00e9 apta, portanto, a ser admitida como meio de prova a refutar as conclus\u00f5es obtidas pela Funasa no Relat\u00f3rio de Acompanhamento T\u00e9cnico, de 17/11/2000 e Pareceres t\u00e9cnicos 122/2001, de 14/8/2001, 1/2002, de 11/1/2002, 79/2003, de 3/9/2003, 60/2006, de 24/8/2006, bem como do Parecer Financeiro 48/2007, de 19/3/2007, todos citados no relat\u00f3rio que conduziu o ac\u00f3rd\u00e3o recorrido.</p><p class=\"tCU_-_Ep\u00edgrafe\">5.13. Ainda sobre o parecer de pe\u00e7a 37, h\u00e1 refer\u00eancias as fotografias juntadas (pe\u00e7a 37, p. 13-20) . Sobre as fotografias tamb\u00e9m h\u00e1 diversos precedentes no sentido de que desacompanhadas de provas mais robustas s\u00e3o insuficientes para comprovar a regularidade na aplica\u00e7\u00e3o dos recursos p\u00fablicos transferidos por meio de conv\u00eanio, tais elementos, como os que ora s\u00e3o colacionados ao recurso, n\u00e3o cont\u00eam informa\u00e7\u00f5es como data, imagens da localiza\u00e7\u00e3o do objeto e outras capazes de estabelecer nexo de causalidade entre a obra executada e os recursos federais oportunamente repassados. </p><p class=\"tCU_-_Ep\u00edgrafe\">5.14. Embora possam, eventualmente, comprovar a realiza\u00e7\u00e3o do objeto, n\u00e3o demonstram a vincula\u00e7\u00e3o entre o objeto e a origem dos recursos aplicados (<i>v.g</i> <a href=\"https://pesquisa.apps.tcu.gov.br/#/doc/acordao-completo/2436/2015/Plen\u00e1rio\" target=\"_blank\">Ac\u00f3rd\u00e3o 2436/2015-TCU-Plen\u00e1rio</a> e <a href=\"https://pesquisa.apps.tcu.gov.br/#/doc/acordao-completo/1824/2015/Primeira C\u00e2mara\" target=\"_blank\">Ac\u00f3rd\u00e3o 1824/2015-TCU-Primeira C\u00e2mara</a>) . </p><p class=\"tCU_-_Ep\u00edgrafe\">5.15. No caso sob exame, a quest\u00e3o das datas adquire relev\u00e2ncia. Observa-se que o documento de pe\u00e7a 37, embora n\u00e3o datado pelo subscritor, foi elaborado no ano de 2017, distante do ano de 1999, exerc\u00edcio em que se deveria ter aplicado os recursos do conv\u00eanio na obra sob discuss\u00e3o. As fotos n\u00e3o possuem datas, logo nada comprovam acerca do objeto no momento em que a Funasa detectou as irregularidades. </p><p class=\"tCU_-_Ep\u00edgrafe\">5.16. Nesse sentido, as supostas evid\u00eancias n\u00e3o demonstram a execu\u00e7\u00e3o do objeto e n\u00e3o devem ser aceitas como aptas a desconstituir o decidido no ac\u00f3rd\u00e3o condenat\u00f3rio. </p><p class=\"tCU_-_Ep\u00edgrafe\">5.17. Com rela\u00e7\u00e3o aos demais argumentos do recorrente e do parecerista, verifica-se que assentam suas alega\u00e7\u00f5es em tr\u00eas quest\u00f5es centrais: (a) a insufici\u00eancia dos recursos do conv\u00eanio para concluir a obra, (b) a responsabilidade do seu sucessor de obter os recursos necess\u00e1rios para o t\u00e9rmino do empreendimento, (c) a execu\u00e7\u00e3o de parcela relevante do objeto e a inadequada imputa\u00e7\u00e3o do montante do d\u00e9bito.</p><p class=\"tCU_-_Ep\u00edgrafe\">5.18. No tocante aos dois primeiros argumentos, entende-se, em conformidade com o ac\u00f3rd\u00e3o recorrido, que os apelos n\u00e3o merecem prosperar. </p><p class=\"tCU_-_Ep\u00edgrafe\">5.19. Acerca das defici\u00eancias do plano de trabalho e do atraso na transfer\u00eancia dos recursos, vale frisar que as medidas deveriam ter sido adotadas pelo pr\u00f3prio ex-Prefeito para a resolu\u00e7\u00e3o dos percal\u00e7os. </p><p class=\"tCU_-_Ep\u00edgrafe\">5.20. A desatualiza\u00e7\u00e3o do planejamento inicial (defasagem do plano de trabalho) n\u00e3o pode ser atribu\u00edda a outro agente diverso do ex-Prefeito. Nos termos do art. 2\u00ba, \u00a7 1\u00ba, da Instru\u00e7\u00e3o Normativa-STN 01/1997, competia ao convenente apresentar plano de trabalho, contendo especifica\u00e7\u00e3o completa do bem a ser produzido ou adquirido e, no caso de obras, instala\u00e7\u00f5es ou servi\u00e7os, o projeto b\u00e1sico, o qual, por sua vez, deveria contemplar o custo total para a conclus\u00e3o do empreendimento.</p><p class=\"tCU_-_Ep\u00edgrafe\">5.21. Por quest\u00e3o de l\u00f3gica jur\u00eddica, se a obra inacabada e inserv\u00edvel \u00e0 popula\u00e7\u00e3o teve como causa a desatualiza\u00e7\u00e3o do plano de trabalho, o que n\u00e3o se est\u00e1 admitir, mas t\u00e3o somente a ponderar, \u00e9 poss\u00edvel deduzir que a conduta do ex-Gestor, aquele que prop\u00f4s a celebra\u00e7\u00e3o do pacto, se mostra em desconformidade ao regulamentado. No presente caso, foi o recorrente que executou a tarefa, logo foi ele quem deu causa a irregularidade. Assim, em nada o socorre o argumento acerca da desatualiza\u00e7\u00e3o do plano de trabalho. </p><p class=\"tCU_-_Ep\u00edgrafe\">5.22. No tocante ao retardo no repasse dos recursos financeiros, entende-se ser obriga\u00e7\u00e3o do convenente atualizar a situa\u00e7\u00e3o e buscar a solu\u00e7\u00e3o perante a entidade repassadora. \u00c9 o que disp\u00f5e o art. 15 da Instru\u00e7\u00e3o Normativa-STN 01/1997.</p><p class=\"tCU_-_Ep\u00edgrafe\">5.23. Nesse sentido o argumento de existir objeto em execu\u00e7\u00e3o n\u00e3o afasta do gestor a obriga\u00e7\u00e3o de acertar os termos pactuados e formaliz\u00e1-los junto ao concedente, sob pena de assumir o risco, como o que ocorreu no presente caso, de executar objeto inserv\u00edvel aos fins a que se destinava e atrair a responsabilidade de ressarcir o er\u00e1rio.</p><p class=\"tCU_-_Ep\u00edgrafe\">5.24. Na mesma esteira, \u00e9 necess\u00e1rio esclarecer que se avalizado pelo concedente e na exist\u00eancia de circunst\u00e2ncia que refugiam ao dom\u00ednio do gestor, o objeto poderia sofrer altera\u00e7\u00f5es e adequa\u00e7\u00f5es n\u00e3o importando, necessariamente, na disponibiliza\u00e7\u00e3o de novos recursos. Conforme exposto pelo Ministro-Relator, medida extrema como a den\u00fancia do conv\u00eanio poderia ter sido adotada e afastar a sua responsabilidade (art. 7\u00ba, inciso X, da Instru\u00e7\u00e3o Normativa-STN 01/1997) . O que n\u00e3o se admite \u00e9 a inexecu\u00e7\u00e3o parcial e a situa\u00e7\u00e3o de completo abandono das obras como os fatos constatados nas vistorias <i>in loco</i> da entidade concedente.  </p><p class=\"tCU_-_Ep\u00edgrafe\">5.25. Tamb\u00e9m, a nosso sentir, n\u00e3o prospera o argumento de ser da responsabilidade do seu sucessor o abandono e deteriora\u00e7\u00e3o das obras, veja o que disp\u00f4s o voto do ac\u00f3rd\u00e3o condutor, <i>verbis:</i> </p><p class=\"tCU_________T2\">24. Quanto ao assunto, tamb\u00e9m \u00e9 assente a culpa do ex-Prefeito, uma vez que a situa\u00e7\u00e3o de abandono e deteriora\u00e7\u00e3o das obras se manifestou ainda na sua administra\u00e7\u00e3o, conforme apurado em vistoria da Funasa. Segundo o Relat\u00f3rio de Acompanhamento T\u00e9cnico da Divis\u00e3o de Engenharia de Sa\u00fade P\u00fablica da Funasa, de 4/12/2000 (pe\u00e7a 3, p. 82) :</p><p class=\"tCU_-_Ep\u00edgrafe\"> <i>\"O conv\u00eanio est\u00e1 paralisado e a obra objeto do mesmo, encontra-se inconclusa. S\u00f3 dois blocos est\u00e3o constru\u00eddos com pequenos detalhes de acabamento a fazer o, Canil/Gat\u00edl e o Almoxarifado geral. O bloco de Administra\u00e7\u00e3o, Est\u00e1bulo, muros, sistema de \u00e1gua e esgotamento sanit\u00e1rio, n\u00e3o foram constru\u00eddos. Todo o complexo encontra-se aberto pass\u00edvel de depreda\u00e7\u00e3o e roubo.\"</i></p><p class=\"tCU_-_Ep\u00edgrafe\">5.26. Em rela\u00e7\u00e3o ao montante do d\u00e9bito, \u00e9 preciso esclarecer que o ac\u00f3rd\u00e3o condenou o recorrente ante a inutilidade e aus\u00eancia de benef\u00edcio social decorrente da estrutura parcialmente constru\u00edda. </p><p class=\"tCU_-_Ep\u00edgrafe\">5.27. Esta Corte tem oscilado entre a imputa\u00e7\u00e3o do d\u00e9bito total nos casos nos quais ocorre a imprestabilidade da fra\u00e7\u00e3o executada do objeto e a completa frustra\u00e7\u00e3o dos objetivos do conv\u00eanio (<i>v.g</i><b> </b><a href=\"https://pesquisa.apps.tcu.gov.br/#/doc/acordao-completo/2581/2014/Plen\u00e1rio\" target=\"_blank\">Ac\u00f3rd\u00e3o 2581/2014-TCU-Plen\u00e1rio</a>; 1.521/2007, 1.964/2007, 903/2008, 1.017/2008, 4.587/2009, 5.175/2013, 10121/2017, todos da 2\u00aa C\u00e2mara e 6.723/2014, 1.595/2007, ambos da 1\u00aa C\u00e2mara) e a imputa\u00e7\u00e3o parcial do d\u00e9bito, nos casos em que se demonstra que os recursos aplicados no objeto, ainda que incompleto, aproveitaria \u00e0 popula\u00e7\u00e3o (<i>v.g</i> Ac\u00f3rd\u00e3os 112/2007, 862/2007, 2.368/2007, 3543/2007, todos da 2\u00aa C\u00e2mara) .</p><p class=\"tCU_-_Ep\u00edgrafe\">5.28. Dessa forma, entende-se a quest\u00e3o de direito remete \u00e0 quest\u00e3o de fato, e dever\u00e1 ser definida em cada caso concreto. Se a parcela executada aproveitar ao p\u00fablico benefici\u00e1rio ainda que parcialmente, o conv\u00eanio ser\u00e1 tido por parcialmente executado e o d\u00e9bito proporcional a parcela n\u00e3o executada. Contudo, se a parcela executada for imprest\u00e1vel ou for suficiente para que o pacto alcance os objetivos para o qual foi celebrado, a imputa\u00e7\u00e3o da totalidade dos recursos repassados se imp\u00f5e. </p><p class=\"tCU_-_Ep\u00edgrafe\">5.29. Tal proposi\u00e7\u00e3o se justifica, pois o objeto de um conv\u00eanio, ou de qualquer outro meio de transfer\u00eancia de recursos, n\u00e3o pode ser analisado, sob a \u00f3tica da presta\u00e7\u00e3o de contas, de forma totalmente desvinculada dos fins a que se prop\u00f5e. A efetiva gera\u00e7\u00e3o do benef\u00edcio esperado por determinada interven\u00e7\u00e3o \u00e9, em regra, condi\u00e7\u00e3o necess\u00e1ria para ateste da boa e regular aplica\u00e7\u00e3o dos recursos p\u00fablicos. (<b><i>v.g</i></b> <a href=\"https://pesquisa.apps.tcu.gov.br/#/doc/acordao-completo/2581/2014/Plen\u00e1rio\" target=\"_blank\">Ac\u00f3rd\u00e3o 2581/2014-TCU-Plen\u00e1rio</a> e 6.723/2014-TCU-1\u00aa C\u00e2mara) .  </p><p class=\"tCU_-_Ep\u00edgrafe\">5.30. <i>In casu,</i> a situa\u00e7\u00e3o de obra inacabada verificada nas vistorias da Funasa, ratificadas por esta Corte de Contas, permite concluir, em linha com o decidido no ac\u00f3rd\u00e3o recorrido, a imprestabilidade da fra\u00e7\u00e3o executada. A obra somente cumpriria com o seu desiderato se conclu\u00edda e entregue em perfeito funcionamento para a comunidade.   </p><p class=\"tCU_-_Ep\u00edgrafe\">5.31. A situa\u00e7\u00e3o <i>sub examine</i> se assemelha a uma ponte inacabada, sempre poder\u00e1 se argumentar que parte da estrutura foi constru\u00edda e poder\u00e1 ser aproveitada, contudo, at\u00e9 a sua conclus\u00e3o n\u00e3o presta ao objetivo, que seria propiciar a transposi\u00e7\u00e3o de um lado a outro. N\u00e3o se pode inferir que em algum momento as obras do objeto e a opera\u00e7\u00e3o da unidade sejam retomadas e aproveitados os recursos repassados.  </p><p class=\"tCU_-_Ep\u00edgrafe\">5.32. Logo, a parcela executada se mostrou imprest\u00e1vel ao alcance dos objetivos do pacto. Assim, deve-se destacar que a condena\u00e7\u00e3o decorreu da execu\u00e7\u00e3o parcial do objeto sem qualquer proveito para a comunidade e, portanto, devido a imputa\u00e7\u00e3o pela totalidade dos valores repassados.</p><p class=\"tCU_-_Ep\u00edgrafe\"><b>6. Da ilegalidade da multa aplicada </b></p><p class=\"tCU_-_Ep\u00edgrafe\">6.1. Defende-se a ilegalidade na multa aplicada, uma vez que n\u00e3o houve a utiliza\u00e7\u00e3o irregular dos recursos, sendo injusta a condena\u00e7\u00e3o.</p><p class=\"tCU_-_Ep\u00edgrafe\"><b>An\u00e1lise:</b></p><p class=\"tCU_-_Ep\u00edgrafe\">6.2. Para a jurisprud\u00eancia consolidada desta Corte, no \u00e2mbito dos processos de controle externo, a responsabilidade dos gestores de recursos p\u00fablicos \u00e9 de natureza subjetiva e surge o dever de reparar no momento em que causa preju\u00edzo ao er\u00e1rio. </p><p class=\"tCU_-_Ep\u00edgrafe\">6.3. Espera-se do gestor diligente que demonstre a boa e regular aplica\u00e7\u00e3o dos recursos. Age com culpa aquele que n\u00e3o prova a correta aplica\u00e7\u00e3o dos recursos. Logo, ao deixar de demonstrar a correta execu\u00e7\u00e3o do objeto e o alcance dos objetivos do pacto convenial, o gestor incorre em il\u00edcito, descumpre obriga\u00e7\u00e3o de fazer imposta pela lei, o que conduz, necessariamente, a dano que deve ser ressarcido. </p><p class=\"tCU_-_Ep\u00edgrafe\">6.4. Todo aquele que causa preju\u00edzo a outrem, dolosa ou culposamente, tem o dever de indenizar, dever esse que, na \u00e1rea p\u00fablica, \u00e9 operacionalizado pela Tomada de Contas Especial, instrumental de concretiza\u00e7\u00e3o do devido ressarcimento.</p><p class=\"tCU_-_Ep\u00edgrafe\">6.5. Nessa toada, o artigo 57 da Lei 8.443/92 autoriza esta Corte a aplicar multa ao respons\u00e1vel nos casos em que se tenha resultado d\u00e9bito, como o que ora se verifica, portanto, \u00e0 luz do dispositivo mencionado n\u00e3o se verifica ilegalidade na aplica\u00e7\u00e3o da san\u00e7\u00e3o. </p><p class=\"tCU_-_Ep\u00edgrafe\"><b>7. Da prescri\u00e7\u00e3o do d\u00e9bito </b></p><p class=\"tCU_-_Ep\u00edgrafe\">7.1. O recorrente aduz em suas raz\u00f5es recursais a ocorr\u00eancia da prescri\u00e7\u00e3o do d\u00e9bito. </p><p class=\"tCU_-_Ep\u00edgrafe\">7.2. Argumenta, em s\u00edntese, que:</p><p class=\"tCU_-_Ep\u00edgrafe\"> a) deve-se reconhecer \"a efic\u00e1cia da Lei Federal, (...) lei que rege os processos administrativos, a Lei n\u00ba 8.112/90 que prev\u00ea, em seu art. 110, o prazo de 5 anos para a prescri\u00e7\u00e3o punitiva dos atos\", que no presente caso se se encerrou em 2004;</p><p class=\"tCU_-_Ep\u00edgrafe\"> b) \"o art. 205 do C\u00f3digo Civil fixa prazo de dez anos para a prescri\u00e7\u00e3o para pretens\u00e3o punitiva\", o que alcan\u00e7aria os fatos discutidos nestes autos;</p><p class=\"tCU_-_Ep\u00edgrafe\">c) em sede de repercuss\u00e3o geral (RE 669.069/MG) , j\u00e1 decidiu o STF que n\u00e3o s\u00e3o todos os danos produzidos ao patrim\u00f4nio p\u00fablico que seriam imprescrit\u00edveis, dessa forma, no caso concreto haveria prescri\u00e7\u00e3o, pois n\u00e3o houve improbidade.</p><p class=\"tCU_-_Ep\u00edgrafe\"><b>An\u00e1lise:</b></p><p class=\"tCU_-_Ep\u00edgrafe\">7.3. A prescri\u00e7\u00e3o do d\u00e9bito arguida pelo recorrente deve ser rejeitada. Objetiva-se na Tomada de Contas Especial - TCE a apura\u00e7\u00e3o da responsabilidade civil/administrativa dos que deram causa a dano ao Er\u00e1rio. N\u00e3o se aplica, portanto, o RE 669.069 citado pelo recorrente. Dessa forma, nos termos do art. 37, \u00a75\u00ba, da Constitui\u00e7\u00e3o Federal, as a\u00e7\u00f5es de ressarcimento ao patrim\u00f4nio p\u00fablico s\u00e3o imprescrit\u00edveis. Logo, n\u00e3o houve prescri\u00e7\u00e3o da pretens\u00e3o ao ressarcimento. Este \u00e9 o entendimento do Supremo Tribunal Federal (MS 26210/DF, in DJ de 10/10/2008) e deste Tribunal, nos termos da S\u00famula/TCU 282, <b>verbis:</b></p><p class=\"tCU_________T2\">As a\u00e7\u00f5es de ressarcimento movidas pelo Estado contra os agentes causadores de danos ao er\u00e1rio s\u00e3o imprescrit\u00edveis.  </p><p class=\"tCU_-_Ep\u00edgrafe\">7.4. O recorrente, ainda, faz refer\u00eancia ao julgamento do RE 669069, sob o rito da repercuss\u00e3o geral. Mas ali o Supremo Tribunal Federal (STF) reafirmou a interpreta\u00e7\u00e3o do art. 37, \u00a7 5\u00ba, da Lei Maior, segundo a qual s\u00e3o imprescrit\u00edveis as a\u00e7\u00f5es de ressarcimento de danos decorrentes de il\u00edcitos tipificados como de improbidade administrativa e como il\u00edcitos penais. Ressalvou-se, na ocasi\u00e3o, apenas os danos decorrentes de il\u00edcitos civis (no caso concreto, um acidente automobil\u00edstico) . Por elucidativo, vale a leitura do seguinte trecho do voto que guiou a decis\u00e3o paradigm\u00e1tica (STF, RE 669069) : </p><p class=\"tCU_________T2\">3. Em suma, n\u00e3o h\u00e1 d\u00favidas de que o fragmento final do \u00a7 5\u00ba do art. 37 da Constitui\u00e7\u00e3o veicula, sob a forma da imprescritibilidade, uma ordem de bloqueio destinada a conter eventuais iniciativas legislativas displicentes com o patrim\u00f4nio p\u00fablico. Esse sentido deve ser preservado. Todavia, n\u00e3o \u00e9 adequado embutir na norma de imprescritibilidade um alcance ilimitado, ou limitado apenas pelo (a) conte\u00fado material da pretens\u00e3o a ser exercida - o ressarcimento - ou (b) pela causa remota que deu origem ao desfalque no er\u00e1rio - um ato il\u00edcito em sentido amplo. O que se mostra mais consent\u00e2neo com o sistema de direito, inclusive o constitucional, que consagra a prescritibilidade como princ\u00edpio, \u00e9 atribuir um sentido estrito aos il\u00edcitos de que trata o \u00a7 5\u00ba do art. 37 da Constitui\u00e7\u00e3o Federal, afirmando como tese de repercuss\u00e3o geral a de que a imprescritibilidade a que se refere o mencionado dispositivo diz respeito apenas a a\u00e7\u00f5es de ressarcimento de danos decorrentes de il\u00edcitos tipificados como de improbidade administrativa e como il\u00edcitos penais. [...] (STF. RE 669069, Rel. Min. Teori Zavascki, Tribunal Pleno, Repercuss\u00e3o Geral - M\u00e9rito DJe 27/4/2016) . </p><p class=\"tCU_-_Ep\u00edgrafe\">7.5. No voto que guiou o julgamento dos Embargos de Declara\u00e7\u00e3o opostos no mesmo RE 669069, a abrang\u00eancia do julgamento ficou bem delimitada: </p><p class=\"tCU_________T2\">[...]. 2. O primeiro ponto a ser enfrentado diz respeito \u00e0 abrang\u00eancia da tese fixada, bem como \u00e0 exata defini\u00e7\u00e3o dos atos que poderiam ser considerados il\u00edcitos civis, para fins de reprodu\u00e7\u00e3o do entendimento firmado em sede de repercuss\u00e3o geral. No julgamento, proferi voto no sentido de negar provimento ao recurso extraordin\u00e1rio, afirmando a tese de que \"a imprescritibilidade a que se refere o art. 37, \u00a7 5\u00ba, da CF diz respeito apenas a a\u00e7\u00f5es de ressarcimento de danos ao er\u00e1rio decorrentes de atos praticados por qualquer agente, servidor ou n\u00e3o, tipificados como il\u00edcitos de improbidade administrativa ou como il\u00edcitos penais\". Contudo, fiquei vencido quanto \u00e0 tese firmada, uma vez que o posicionamento majorit\u00e1rio desta Corte, encabe\u00e7ado pelo Min. Roberto Barroso, foi no sentido de que a orienta\u00e7\u00e3o a ser fixada, para fins de repercuss\u00e3o geral, deveria ser mais restrita e adstrita ao caso concreto, que consistia em a\u00e7\u00e3o de ressarcimento ajuizada pela Uni\u00e3o em raz\u00e3o de danos sofridos em decorr\u00eancia de acidente de tr\u00e2nsito. Assentou-se, assim, a tese de que \"\u00e9 prescrit\u00edvel a a\u00e7\u00e3o de repara\u00e7\u00e3o de danos \u00e0 Fazenda P\u00fablica decorrente de il\u00edcito civil\". 3. Nos debates travados na oportunidade do julgamento ficou clara a op\u00e7\u00e3o do Tribunal de considerar como il\u00edcito civil os de natureza semelhante \u00e0 do caso concreto em exame, a saber: il\u00edcitos decorrentes de acidente de tr\u00e2nsito. O conceito, sob esse aspecto, deve ser buscado pelo m\u00e9todo de exclus\u00e3o: n\u00e3o se consideram il\u00edcitos civis, de um modo geral, os que decorrem de infra\u00e7\u00f5es ao direito p\u00fablico, como os de natureza penal, os decorrentes de atos de improbidade e assim por diante. Ficou expresso nesses debates, reproduzidos no ac\u00f3rd\u00e3o embargado, que a prescritibilidade ou n\u00e3o em rela\u00e7\u00e3o a esses outros il\u00edcitos seria examinada em julgamento pr\u00f3prio. Por isso mesmo, recentemente, o Supremo Tribunal Federal reconheceu a repercuss\u00e3o geral de dois temas relacionados \u00e0 prescritibilidade da pretens\u00e3o de ressarcimento ao er\u00e1rio: (a) Tema 897 - \"Prescritibilidade da pretens\u00e3o de ressarcimento ao er\u00e1rio em face de agentes p\u00fablicos por ato de improbidade administrativa\"; e (b) Tema 899 - \"Prescritibilidade da pretens\u00e3o de ressarcimento ao er\u00e1rio fundada em decis\u00e3o de Tribunal de Contas\". Desse modo, se d\u00favidas ainda houvesse, \u00e9 evidente que as pretens\u00f5es de ressarcimento decorrentes de atos tipificados como il\u00edcitos de improbidade administrativa, assim como aquelas fundadas em decis\u00f5es das Cortes de Contas, n\u00e3o foram abrangidas pela tese fixada no julgado embargado. [...]. (RE 669069 ED, Rel. Min. Teori Zavascki, Tribunal Pleno, DJe 29/6/2016) .</p><p class=\"tCU_-_Ep\u00edgrafe\">7.6. Em rela\u00e7\u00e3o ao argumento de haver repercuss\u00e3o geral reconhecida, mas pendente de julgamento pelo STF, que apreciar\u00e1 especificamente a incid\u00eancia ou n\u00e3o de prescri\u00e7\u00e3o \u00e0 pretens\u00e3o de ressarcimento fundada em decis\u00e3o de tribunal de contas (RE 636.886 - Tema 899) , a susta\u00e7\u00e3o determinada n\u00e3o retira a for\u00e7a normativa que se extrai da literalidade do art. 37, \u00a7 5\u00ba, da Constitui\u00e7\u00e3o. A presun\u00e7\u00e3o de constitucionalidade acompanha normas em geral desde o nascedouro, sejam emendas constitucionais, leis em geral e, com muito mais for\u00e7a, \u00e9 \u00ednsita ao pr\u00f3prio texto constitucional original. De forma que, enquanto n\u00e3o sobrevier interpreta\u00e7\u00e3o eventualmente restritiva por parte da Suprema Corte, n\u00e3o cabe outra leitura do texto constitucional, cujo teor \u00e9 sublinhado no \u00e2mbito do processo administrativo de controle externo pela S\u00famula-TCU 282.</p><p class=\"tCU_-_Ep\u00edgrafe\">7.7. Portanto, na hip\u00f3tese de o colegiado julgador entender pela manuten\u00e7\u00e3o de alguma parcela do d\u00e9bito, a d\u00edvida n\u00e3o estaria fulminada por prescri\u00e7\u00e3o, ressalvada eventual manifesta\u00e7\u00e3o em sentido contr\u00e1rio do STF (tema 899 da repercuss\u00e3o geral) que venha a lume antes da respectiva quita\u00e7\u00e3o levada a termo espontaneamente ou por meio de execu\u00e7\u00e3o for\u00e7ada.</p><p class=\"tCU_-_Ep\u00edgrafe\">7.8. Ante o exposto, entende-se que a quest\u00e3o em rela\u00e7\u00e3o ao d\u00e9bito n\u00e3o merece acolhida.</p><p class=\"tCU_-_Ep\u00edgrafe\">7.9. No tocante \u00e0 prescri\u00e7\u00e3o da multa, ap\u00f3s longa discuss\u00e3o nesta Corte, restou decidido e firmado o incidente de uniformiza\u00e7\u00e3o de jurisprud\u00eancia (<a href=\"https://pesquisa.apps.tcu.gov.br/#/doc/acordao-completo/1441/2016/Plen\u00e1rio\" target=\"_blank\">Ac\u00f3rd\u00e3o 1441/2016-TCU-Plen\u00e1rio</a>) no sentido abaixo exposto.   </p><p class=\"tCU_-_Ep\u00edgrafe\">7.10. Entende-se contraproducente e desprovido de racionalidade processual desenvolver argumentos e alega\u00e7\u00f5es a justificar tese jur\u00eddica diversa, por n\u00e3o haver ind\u00edcios de evolu\u00e7\u00e3o hermen\u00eautica, ainda que seja o entendimento desse auditor informante. </p><p class=\"tCU_-_Ep\u00edgrafe\">7.11. Dessa forma, a an\u00e1lise e o encaminhamento ser\u00e1 feito de acordo com o definido no <a href=\"https://pesquisa.apps.tcu.gov.br/#/doc/acordao-completo/1441/2016/Plen\u00e1rio\" target=\"_blank\">Ac\u00f3rd\u00e3o 1441/2016-TCU-Plen\u00e1rio</a>.</p><p class=\"tCU_-_Ep\u00edgrafe\">7.12. O <i>decisum</i> deixou assentado que:</p><p class=\"tCU_-_Ep\u00edgrafe\">a) A pretens\u00e3o punitiva do TCU subordina-se ao prazo geral de prescri\u00e7\u00e3o indicado no art. 205 da Lei 10.406/2002 (C\u00f3digo Civil) , dez anos;</p><p class=\"tCU_-_Ep\u00edgrafe\">b) o termo <b><i>a quo</i></b> para o prazo prescricional \u00e9 contado a partir da data de ocorr\u00eancia da irregularidade sancionada, nos termos do art. 189 da Lei 10.406/2002 (C\u00f3digo Civil) ;</p><p class=\"tCU_-_Ep\u00edgrafe\">c) o ato que ordenar a cita\u00e7\u00e3o, a audi\u00eancia ou oitiva da parte interrompe a prescri\u00e7\u00e3o da pretens\u00e3o punitiva do TCU, nos termos do art. 202, inciso I, da Lei 10.406/2002 (C\u00f3digo Civil) , recome\u00e7ando a contagem da data do ato que motivou a interrup\u00e7\u00e3o, nos termos do art. 202, par\u00e1grafo \u00fanico, parte inicial, do C\u00f3digo Civil;</p><p class=\"tCU_-_Ep\u00edgrafe\">d) a prescri\u00e7\u00e3o da pretens\u00e3o punitiva do TCU ser\u00e1 suspensa toda vez que a parte apresentar elementos adicionais de defesa ou quando forem necess\u00e1rias dilig\u00eancias em raz\u00e3o de algum fato novo trazido pela parte, n\u00e3o suficientemente documentado nas manifesta\u00e7\u00f5es processuais. A paralisa\u00e7\u00e3o da contagem do prazo prescricional ocorrer\u00e1 no per\u00edodo compreendido entre a juntada dos elementos adicionais de defesa ou da pe\u00e7a contendo o fato novo e a an\u00e1lise dos referidos elementos ou da resposta \u00e0 dilig\u00eancia, nos termos do art. 160, \u00a7 2\u00ba, do Regimento Interno do TCU.</p><p class=\"tCU_-_Ep\u00edgrafe\">7.13. Segundo o regime prescricional previsto no C\u00f3digo Civil, observa-se que os fatos ocorridos na vig\u00eancia do CC/1916, mas que no in\u00edcio da vig\u00eancia do novo C\u00f3digo (11/1/2003) ainda n\u00e3o ultrapassaram mais de 10 anos (mais da metade do prazo anterior) , aplica-se o prazo decenal do novo C\u00f3digo, segundo a regra de seu art. 2.028. </p><p class=\"tCU_-_Ep\u00edgrafe\">7.14. A condena\u00e7\u00e3o do recorrente decorreu da inexecu\u00e7\u00e3o do objeto e da imprestabilidade da fra\u00e7\u00e3o executada, assim, entende-se que o termo <i>a quo</i> para a contagem do prazo prescricional iniciaria com o fim da vig\u00eancia do pacto. Contudo, verifica-se, conforme exposto acima, que o in\u00edcio da contagem deve se deslocar para 11/1/2003 (in\u00edcio da vig\u00eancia do CC/2002) .</p><p class=\"tCU_-_Ep\u00edgrafe\">7.15. O prazo foi interrompido em 1/6/2010 (pe\u00e7a 12, p. 50/57) , cita\u00e7\u00e3o do respons\u00e1vel, logo, do in\u00edcio da contagem do prazo at\u00e9 a cita\u00e7\u00e3o decorreram menos de dez anos, portanto interrompido prazo prescricional. Ato cont\u00ednuo, a condena\u00e7\u00e3o ocorreu no dia 27/6/2017, menos de dez anos entre a interrup\u00e7\u00e3o do prazo e a condena\u00e7\u00e3o. Portanto, n\u00e3o est\u00e1 prescrita a pretens\u00e3o punitiva, nos termos do entendimento desta Corte de Contas.</p><p class=\"tCU_-_Ep\u00edgrafe\"><b>CONCLUS\u00c3O</b></p><p class=\"tCU_-_Ep\u00edgrafe\">8. Das an\u00e1lises anteriores, conclui-se que:</p><p class=\"tCU_-_Ep\u00edgrafe\">a) os elementos colacionados aos autos, a exemplo das declara\u00e7\u00f5es de terceiros e fotografias, bem como os argumentos manejados no parecer e nas raz\u00f5es recursais n\u00e3o foram suficientes para demonstrar a execu\u00e7\u00e3o do objeto e (ou) a sua utilidade \u00e0 popula\u00e7\u00e3o, e portanto, inaptos a afastar a responsabilidade do ex-gestor;</p><p class=\"tCU_-_Ep\u00edgrafe\">b) n\u00e3o h\u00e1 ilegalidade na multa aplicada ao ex-Prefeito;</p><p class=\"tCU_-_Ep\u00edgrafe\">c) n\u00e3o h\u00e1 prescri\u00e7\u00e3o nem do d\u00e9bito, nem da multa.</p><p class=\"tCU_-_Ep\u00edgrafe\">8.1. Com base nessas conclus\u00f5es, prop\u00f5e-se <b>negar</b> <b>provimento ao recurso.</b></p><p class=\"tCU_-_Ep\u00edgrafe\"><b>PROPOSTA DE ENCAMINHAMENTO</b></p><p class=\"tCU_-_Ep\u00edgrafe\">9. Ante o exposto, com fundamento nos arts. 32, I e 33, da Lei 8.443/92 c/c o art. 285, caput, do RI-TCU, submetem-se os autos \u00e0 considera\u00e7\u00e3o superior, propondo-se:</p><p class=\"tCU_-_Ep\u00edgrafe\">a) conhecer do recurso e, no m\u00e9rito, negar-lhe provimento; </p><p class=\"tCU_-_Ep\u00edgrafe\">b) dar ci\u00eancia do ac\u00f3rd\u00e3o que for prolatado \u00e0 recorrente e aos demais interessados, ressaltando-se que o relat\u00f3rio e o voto que o acompanharem podem ser consultados no endere\u00e7o www.tcu.gov.br/acordaos, no dia seguinte ao de sua oficializa\u00e7\u00e3o.</p><p class=\"tCU_-_Ep\u00edgrafe\">\t\u00c9 o relat\u00f3rio.</p><p class=\"footer\"/>", "ADVOGADO": " Pedro Henrique de Oliveira Bezerra (OAB/PE 23.140) e outros. ", "REPRESENTANTEMP": "Procuradora-Geral Cristina Machado da Costa e Silva.", "SITUACAO": "OFICIALIZADO", "SUMARIO": "RECURSO DE RECONSIDERA\u00c7\u00c3O EM TOMADA DE CONTAS ESPECIAL. CONV\u00caNIO. INEXECU\u00c7\u00c3O PARCIAL DO OBJETO. IRREGULARIDADE DAS CONTAS. D\u00c9BITO. MULTA. RAZ\u00d5ES RECURSAIS INSUFICIENTES PARA ALTERAR O M\u00c9RITO DO JULGADO. NEGATIVA DE PROVIMENTO DO RECURSO.", "TIPOPROCESSO": "TOMADA DE CONTAS ESPECIAL (TCE)", "UNIDADETECNICA": " Secretaria de Recursos (Serur).", "VOTO": "<p class=\"tCU_-_Ep\u00edgrafe\">Por preencher os requisitos de admissibilidade previstos nos arts. 32, inciso I, e 33 da Lei 8.443/1992, deve ser conhecido o presente recurso de reconsidera\u00e7\u00e3o interposto por Jo\u00e3o Soares Lyra Neto, prefeito de Caruaru/PE na gest\u00e3o de 1997 a 2000, em face do <a href=\"https://pesquisa.apps.tcu.gov.br/#/doc/acordao-completo/4968/2017/Primeira C\u00e2mara\" target=\"_blank\">Ac\u00f3rd\u00e3o 4968/2017-TCU-Primeira C\u00e2mara</a>, da relatoria do <b>Ministro Benjamin Zymler</b>. </p><p class=\"tCU_-_Ep\u00edgrafe\">Por meio dessa decis\u00e3o, o Tribunal julgou irregulares as contas do ex-prefeito, condenou-o ao pagamento de d\u00e9bito e multa no valor de R$ 75.000,00, em raz\u00e3o da inexecu\u00e7\u00e3o parcial do Conv\u00eanio 1723/1998, celebrado entre a municipalidade e a Funda\u00e7\u00e3o Nacional de Sa\u00fade (Funasa) , com o objetivo de executar a\u00e7\u00f5es no \u00e2mbito do \"Programa de Controle de Doen\u00e7as End\u00eamicas em Caruaru\", mediante a amplia\u00e7\u00e3o e reforma de pr\u00e9dio para a implanta\u00e7\u00e3o do Centro de Controle de Zoonoses.</p><p class=\"tCU_-_Ep\u00edgrafe\">Para a consecu\u00e7\u00e3o do objeto foram previstos o aporte de R$ 357.368,60, sendo R$ 324.800,55 a cargo do concedente e o restante de responsabilidade do munic\u00edpio.</p><p class=\"tCU_-_Ep\u00edgrafe\">Vistorias e an\u00e1lises realizadas pelo concedente identificaram que o conv\u00eanio teve execu\u00e7\u00e3o parcial de 22,6%, al\u00e9m de terem registrado que as obras do pr\u00e9dio para a implanta\u00e7\u00e3o do Centro de Controle de Zoonose n\u00e3o tinham condi\u00e7\u00f5es de serem aceitas, em raz\u00e3o de se encontrarem inacabadas, deterioradas pelas a\u00e7\u00f5es de v\u00e2ndalos, sem terem atingido os benef\u00edcios sociais esperados.</p><p class=\"tCU_-_Ep\u00edgrafe\">Ap\u00f3s exame das alega\u00e7\u00f5es de defesa, os Ministros do Tribunal reunidos em sess\u00e3o da Primeira C\u00e2mara acompanharam o relator <i>a quo</i> no sentido de julgar irregulares as contas do ex-prefeito, ocasi\u00e3o em que foi prolatado o <a href=\"https://pesquisa.apps.tcu.gov.br/#/doc/acordao-completo/4968/2017/Primeira C\u00e2mara\" target=\"_blank\">Ac\u00f3rd\u00e3o 4968/2017-TCU-Primeira C\u00e2mara</a>, contra o qual se insurge, neste momento, o recorrente.</p><p class=\"tCU_-_Ep\u00edgrafe\">Nesta etapa, constitui objeto deste recurso verificar: (i) se o parecer de engenheiro civil contratado pelo recorrente, bem como os argumentos enumerados, s\u00e3o suficientes para afastar sua responsabilidade; (ii) se houve ilegalidade na multa aplicada e, portanto, injusta sua condena\u00e7\u00e3o; e (iii) se houve a prescri\u00e7\u00e3o do d\u00e9bito ou da multa.</p><p class=\"tCU_-_Ep\u00edgrafe\">Ap\u00f3s examinar todos os pontos apresentados, a Secretaria de Recursos conclui que os elementos colacionados aos autos, a exemplo das declara\u00e7\u00f5es de terceiros e fotografias, bem como os argumentos manejados no parecer e nas raz\u00f5es recursais n\u00e3o foram suficientes para demonstrar a execu\u00e7\u00e3o do objeto e/ou sua utilidade \u00e0 popula\u00e7\u00e3o, e, portanto, inaptos a afastar a responsabilidade do ex-gestor. Tamb\u00e9m consigna pela aus\u00eancia de ilegalidade na aplica\u00e7\u00e3o da multa, bem como pela inocorr\u00eancia de prescri\u00e7\u00e3o, tanto do d\u00e9bito quanto da multa aplicada.</p><p class=\"tCU_-_Ep\u00edgrafe\">Ante o exposto, passo ao exame do presente recurso de reconsidera\u00e7\u00e3o.</p><p class=\"tCU_-_Ep\u00edgrafe\">De in\u00edcio, ressalto que grande parte do recurso \u00e9 mera transcri\u00e7\u00e3o do suposto laudo de engenharia juntado \u00e0 pe\u00e7a 37, que tenta demonstrar a regular aplica\u00e7\u00e3o dos recursos. Como bem frisado pela unidade t\u00e9cnica, apesar de o recorrente alegar que se tratou de uma auditoria por ele contratada, o mencionado documento, de fato, trata-se de um parecer elaborado por engenheiro civil, que, a t\u00edtulo de registro, tamb\u00e9m \u00e9 advogado, inscrito na OAB/PE sob o n\u00famero 20.140 (visto existir apenas um Antonio Domingos da Silva Maia identificado no sistema CPF) .</p><p class=\"tCU_-_Ep\u00edgrafe\">No caso concreto, o referido laudo t\u00e9cnico pode ser aceito apenas como declara\u00e7\u00e3o de terceiro. De acordo com a jurisprud\u00eancia desta Corte, as declara\u00e7\u00f5es de terceiros possuem baixa for\u00e7a probat\u00f3ria, pois provam t\u00e3o somente a exist\u00eancia da declara\u00e7\u00e3o em si, n\u00e3o o fato declarado. Desta forma, o Tribunal mant\u00e9m entendimento pac\u00edfico no sentido de que, em sede de an\u00e1lise de presta\u00e7\u00e3o de contas de conv\u00eanios, as declara\u00e7\u00f5es prestadas por terceiros, por si s\u00f3, n\u00e3o s\u00e3o meios de prova capazes de atestar a efetiva execu\u00e7\u00e3o do objeto custeado com recursos p\u00fablicos federais.</p><p class=\"tCU_-_Ep\u00edgrafe\">Dessa forma, as declara\u00e7\u00f5es constantes no referido laudo de que significativa parcela da obra foi executada e disponibilizada \u00e0 coletividade, conforme fotos anexadas aos autos, n\u00e3o \u00e9 apta a ser admitida como meio de prova a refutar as conclus\u00f5es obtidas pela Funasa no Relat\u00f3rio de Acompanhamento T\u00e9cnico, de 17/11/2000, e Pareceres T\u00e9cnicos 122/2001, 1/2002 e 79/2003 e 60/2006. </p><p class=\"tCU_-_Ep\u00edgrafe\">Ademais, acerca das fotos juntadas no referido parecer (pe\u00e7a 37) , h\u00e1 diversos precedentes do Tribunal no sentido de que as fotos, quando desacompanhadas de provas mais robustas, s\u00e3o insuficientes para comprovar a regularidade na aplica\u00e7\u00e3o dos recursos p\u00fablicos transferidos por meio do conv\u00eanio. As fotos n\u00e3o cont\u00eam informa\u00e7\u00f5es como data, imagens da localiza\u00e7\u00e3o do objeto e outras capazes de estabelecer o nexo de causalidade entre os recursos recebidos e a obra executada.</p><p class=\"tCU_-_Ep\u00edgrafe\">Ante o exposto, as evid\u00eancias trazidas pelo recorrente n\u00e3o demonstram a execu\u00e7\u00e3o do objeto e n\u00e3o devem ser aceitas como aptas a desconstituir o decidido no ac\u00f3rd\u00e3o condenat\u00f3rio.</p><p class=\"tCU_-_Ep\u00edgrafe\">Com um olhar mais aprofundado no laudo t\u00e9cnico de 2017 (pe\u00e7a 37) , elaborado portanto mais de dezessete anos ap\u00f3s o fim da vig\u00eancia do conv\u00eanio, verifica-se que a pe\u00e7a t\u00e9cnica se reveste mais da forma de alega\u00e7\u00f5es de defesa do que de um laudo de engenharia propriamente dito. Em seu in\u00edcio, o engenheiro tra\u00e7a todo um hist\u00f3rico desde a fase anterior \u00e0 assinatura do conv\u00eanio, at\u00e9 a fase final do mandato do ex-prefeito, findado no fim do ano de 2000, ocasi\u00e3o tamb\u00e9m em que terminou a vig\u00eancia do conv\u00eanio. Em seguida, procura refutar pontos dos relat\u00f3rios e pareceres emitidos pelo concedente.</p><p class=\"tCU_-_Ep\u00edgrafe\">Os principais pontos de defesa trazidos neste laudo referem-se a argumentos acerca da insufici\u00eancia dos recursos do conv\u00eanio para concluir a obra, da defasagem do plano inicial de trabalho e da responsabilidade dos prefeitos que lhe sucederam de obter os recursos necess\u00e1rios para o t\u00e9rmino do empreendimento.</p><p class=\"tCU_-_Ep\u00edgrafe\">Todos esses pontos foram enfrentados na decis\u00e3o recorrida, como bem frisou o relator <i>a quo</i>, Ministro Benjamin Zymler, no seu voto que acompanhou o <a href=\"https://pesquisa.apps.tcu.gov.br/#/doc/acordao-completo/6354/2018/Plen\u00e1rio\" target=\"_blank\">Ac\u00f3rd\u00e3o 6354/2018-TCU-Plen\u00e1rio</a>, em que foram apreciados os segundos embargos declarat\u00f3rios apresentados pelo respons\u00e1vel contra o ac\u00f3rd\u00e3o que o condenou em d\u00e9bito. A seguir transcrevo a parte do referido voto em que houve o exame desses pontos trazidos no laudo.</p><p>18. Com rela\u00e7\u00e3o \u00e0 execu\u00e7\u00e3o parcial do objeto, ainda que o plano de trabalho estivesse defasado, que os recursos tivessem sido repassados com atraso e que o pre\u00e7o do empreendimento tenha se tornado mais oneroso, caberia ao gestor ter proposto a celebra\u00e7\u00e3o de termo aditivo ao conv\u00eanio, com o objetivo de dotar a aven\u00e7a dos recursos necess\u00e1rios para finalizar as obras, nos termos do art. 15 da Instru\u00e7\u00e3o Normativa-STN n\u00ba 01/1997. </p><p>19. Na impossibilidade de conclus\u00e3o do objeto e de obten\u00e7\u00e3o de novos recursos, por fato supostamente alheio \u00e0 sua vontade, deveria o respons\u00e1vel ter denunciado o conv\u00eanio, proposto \u00e0 sua rescis\u00e3o e, assim, n\u00e3o despendido os recursos dispon\u00edveis em uma obra que n\u00e3o teria nenhuma serventia.</p><p>20. Segundo o art. 7\u00ba, inciso X, da Instru\u00e7\u00e3o Normativa-STN n\u00ba 01/1997, constitui cl\u00e1usula obrigat\u00f3ria em conv\u00eanios a que prev\u00ea <i>\"a faculdade aos part\u00edcipes para denunci\u00e1-lo ou rescindi-lo, a qualquer tempo, imputando-se-lhes as responsabilidades das obriga\u00e7\u00f5es decorrentes do prazo em que tenham vigido e creditando-se-lhes, igualmente os benef\u00edcios adquiridos no mesmo per\u00edodo.\"</i>.</p><p>21. Quanto \u00e0 suposta defasagem do plano de trabalho inicial do conv\u00eanio, entendo que tal falha, se de fato ocorreu, deve ser imputada primariamente ao pr\u00f3prio convenente. Conforme o art. 2\u00ba, \u00a7 1\u00ba, da Instru\u00e7\u00e3o Normativa-STN n\u00ba 01/1997, competia ao convenente apresentar plano de trabalho ao concedente, contendo especifica\u00e7\u00e3o completa do bem a ser produzido ou adquirido e, no caso de obras, instala\u00e7\u00f5es ou servi\u00e7os, o projeto b\u00e1sico, o qual, por sua vez, deveria contemplar o custo total para a conclus\u00e3o do empreendimento.</p><p>22. Sendo assim, se a obra inacabada decorreu da defasagem do plano de trabalho, o que se afirma por hip\u00f3tese, tal medida foi causada por a\u00e7\u00e3o do pr\u00f3prio ex-Prefeito, que prop\u00f4s ajuste inepto para atingir os objetivos aven\u00e7ados. </p><p>23. Ressalto, ainda, por for\u00e7a de considera\u00e7\u00f5es trazidas pela unidade t\u00e9cnica, que as obras inacabadas resultaram em incurs\u00f5es de v\u00e2ndalos, que promoveram saques e depreda\u00e7\u00e3o generalizada nas edifica\u00e7\u00f5es inconclusas, as quais nunca cumpriram a finalidade do acordo. </p><p>24. Quanto ao assunto, tamb\u00e9m \u00e9 assente a culpa do ex-Prefeito, uma vez que a situa\u00e7\u00e3o de abandono e deteriora\u00e7\u00e3o das obras se manifestou ainda na sua administra\u00e7\u00e3o, conforme apurado em vistoria da Funasa. Segundo o Relat\u00f3rio de Acompanhamento T\u00e9cnico da Divis\u00e3o de Engenharia de Sa\u00fade P\u00fablica da Funasa, de 4/12/2000 (pe\u00e7a 3, p. 82) :</p><p> (...) </p><p>25. Quanto \u00e0 utilidade e o benef\u00edcio social da estrutura parcialmente constru\u00edda, o pr\u00f3prio ex-Prefeito reconheceu, no Relat\u00f3rio de Cumprimento do Objeto, que <i>\"n\u00e3o foram alcan\u00e7ados benef\u00edcios com a comunidade, devido \u00e0 n\u00e3o conclus\u00e3o total da obra para o seu funcionamento.\"</i> (pe\u00e7a 1, p. 76) .</p><p>26. Nesse ponto, concordo com a Secex/PE que a jurisprud\u00eancia do TCU \u00e9 pac\u00edfica no sentido de <i>\"que a execu\u00e7\u00e3o parcial do objeto conveniado somente se presta a reduzir o valor do d\u00e9bito imputado ao respons\u00e1vel quando comprovada a possibilidade de aproveitamento das parcelas conclu\u00eddas. No caso em tela, como j\u00e1 afirmado, as obras nunca entraram em funcionamento. Antes mesmo do fim do mandato do gestor respons\u00e1vel pela execu\u00e7\u00e3o do conv\u00eanio, constatou-se a n\u00e3o execu\u00e7\u00e3o total, a paralisa\u00e7\u00e3o das obras e o descuido com o patrim\u00f4nio.\"</i></p><p>27. Quanto \u00e0 responsabiliza\u00e7\u00e3o do prefeito sucessor, as irregularidades verificadas na execu\u00e7\u00e3o da aven\u00e7a - realiza\u00e7\u00e3o parcial e abandono da obra - foram constatadas ainda no ano de 2000, \u00faltimo ano do mandato do Sr. Jo\u00e3o Soares Lyra Neto. Ademais, toda a realiza\u00e7\u00e3o de despesas do acordo se deu na gest\u00e3o do Sr. Jo\u00e3o Soares Lyra Neto, inclusive a obriga\u00e7\u00e3o de apresenta\u00e7\u00e3o da presta\u00e7\u00e3o de contas. </p><p>28. Sendo assim, embora o prefeito sucessor pudesse ter agido no sentido de buscar novos recursos para a conclus\u00e3o do ajuste, entendo que a causa direta e imediata do dano foi a conduta omissiva do Sr. Jo\u00e3o Soares Lyra Neto, ao deixar de adotar, no momento oportuno, as medidas necess\u00e1rias para a altera\u00e7\u00e3o da aven\u00e7a e sua efetiva conclus\u00e3o. Com isso, entendo que ele deve ser condenado em d\u00e9bito pela perda dos recursos manejados durante a sua gest\u00e3o, na forma proposta pela unidade t\u00e9cnica.</p><p class=\"tCU_-_Ep\u00edgrafe\">Portanto, verifica-se que as alega\u00e7\u00f5es agora apresentadas de que haveria contradi\u00e7\u00e3o da decis\u00e3o recorrida quanto \u00e0 necessidade de celebra\u00e7\u00e3o de aditivos, que no seu entender deveriam ter sido realizadas pelos gestores que lhe sucederam, n\u00e3o prospera. Como se observa do \u00a7 28 do voto do ac\u00f3rd\u00e3o combatido, restou claro que caberia ao recorrente ter agido para buscar novos recursos para a conclus\u00e3o do ajuste, o que n\u00e3o o fez, de acordo com a decis\u00e3o recorrida, por omiss\u00e3o. De igual modo, a escusa de que n\u00e3o poderia ter celebrado novo conv\u00eanio, requisitando novos recursos, por se tratar do mesmo objeto n\u00e3o prospera. Poderia o convenente ter proposto uma revis\u00e3o do plano de trabalho com as quantidades supostamente necess\u00e1rias para a conclus\u00e3o do empreendimento e ter submetido tal revis\u00e3o ao concedente, e em caso de negativa deste, incluir mais recursos da municipalidade. Por\u00e9m, n\u00e3o o fez.</p><p class=\"tCU_-_Ep\u00edgrafe\">Tamb\u00e9m n\u00e3o prospera o argumento de que teria ocorrido omiss\u00e3o acerca do abandono da obra pelo gestor sucessor. A partir do par\u00e1grafo 24 da decis\u00e3o recorrida, acima transcrito, verifica-se que, ainda na gest\u00e3o do recorrente, foi verificado o abandono da obra.</p><p class=\"tCU_-_Ep\u00edgrafe\">Com rela\u00e7\u00e3o ao montante do d\u00e9bito, insta esclarecer que o recorrente foi condenado em raz\u00e3o da inutilidade e aus\u00eancia de benef\u00edcio social decorrente da estrutura parcialmente constru\u00edda. Todavia os materiais adquiridos como ve\u00edculos e equipamentos da meta 2 foram abatidos do d\u00e9bito, diante de sua utilidade independente da conclus\u00e3o da obra. </p><p class=\"tCU_-_Ep\u00edgrafe\">Outro ponto trazido pelo recorrente que n\u00e3o merece prosperar refere-se a tentativa de transferir a culpa pela n\u00e3o conclus\u00e3o das obras para o atraso na transfer\u00eancia dos recursos. No pr\u00f3prio laudo t\u00e9cnico (pe\u00e7a 37, p. 8) consta a informa\u00e7\u00e3o de que o recorrente optou por realizar a licita\u00e7\u00e3o apenas ap\u00f3s receber todas as cinco parcelas da verba federal transferida pelo concedente. Na presta\u00e7\u00e3o de contas, consta solicita\u00e7\u00e3o da prefeitura para que fosse prorrogada a vig\u00eancia do conv\u00eanio em raz\u00e3o de atrasos decorrentes do processo licitat\u00f3rio (pe\u00e7a 1, p. 62) , subscrito pelo pr\u00f3prio prefeito. Logo, n\u00e3o cabe atribuir ao concedente culpa pelo suposto aumento de custo ou deteriora\u00e7\u00e3o da obra, conforme alegado pelo recorrente.</p><p class=\"tCU_-_Ep\u00edgrafe\">Quando aos demais argumentos presentes no aludido laudo t\u00e9cnico, al\u00e9m das alega\u00e7\u00f5es de ilegalidade da multa aplicada e da prescri\u00e7\u00e3o do d\u00e9bito e da multa, considero que foram enfrentados de forma percuciente pela unidade recursal, de modo que incorporo na \u00edntegra os seus argumentos como minhas raz\u00f5es de decidir, sem necessidade de acrescer outros pontos.</p><p class=\"tCU_-_Ep\u00edgrafe\">Por \u00faltimo, ap\u00f3s este processo ser inclu\u00eddo na pauta desta sess\u00e3o, o representante do respons\u00e1vel requereu o adiamento do julgamento, com a justificativa do ex\u00edguo lapso de tempo entre a publica\u00e7\u00e3o e a data da referida sess\u00e3o. Todavia, observo que esta sistem\u00e1tica est\u00e1 em plena conson\u00e2ncia com o disposto no art. 141 do Regimento Interno desta Corte, o qual fixa os prazos a serem observados para a inclus\u00e3o e divulga\u00e7\u00e3o dos processos na pauta das sess\u00f5es. Dessa forma, inferido o presente pleito.</p><p class=\"tCU_-_Ep\u00edgrafe\">\tAnte o exposto, VOTO para que seja conhecido o presente recurso de reconsidera\u00e7\u00e3o e, no m\u00e9rito, seja-lhe negado provimento, mantendo inalterada a decis\u00e3o recorrida.</p><p class=\"body_Text\">TCU, Sala das Sess\u00f5es Ministro Luciano Brand\u00e3o Alves de Souza, em 2 de julho de 2019.</p><p class=\"body_Text\"/><p class=\"body_Text\"/><p class=\"body_Text\"/><p class=\"body_Text\"/><p class=\"body_Text\">Ministro VITAL DO R\u00caGO </p><p class=\"body_Text\">Relator</p><p class=\"footer\"/>", "DTATUALIZACAO": "20220925", "URLARQUIVO": "https://contas.tcu.gov.br/sagas/SvlVisualizarRelVotoAcRtf?codFiltro=SAGAS-SESSAO-ENCERRADA&seOcultaPagina=S&item0=665668", "URLARQUIVOPDF": "https://contas.tcu.gov.br/sagas/SvlVisualizarRelVotoAc?codFiltro=SAGAS-SESSAO-ENCERRADA&seOcultaPagina=S&item0=665668", "EXTENSAOARQUIVO": "doc"}