{"KEY": "ACORDAO-COMPLETO-2466524", "TIPO": "AC\u00d3RD\u00c3O", "TITULO": "AC\u00d3RD\u00c3O 7921/2021 ATA 15/2021 - PRIMEIRA C\u00c2MARA", "FAVORITO": false, "NUMACORDAO": "7921", "ANOACORDAO": "2021", "NUMATA": "15/2021", "ACORDAO": "<p class=\"list_Paragraph\">VISTOS, relatados e discutidos estes autos de tomada de contas especial instaurada pela Funda\u00e7\u00e3o Nacional de Sa\u00fade em raz\u00e3o da impugna\u00e7\u00e3o total dos recursos repassados por meio do Termo de Compromisso PAC 283/2007-Siafi 635261, tendo por objeto a execu\u00e7\u00e3o de Sistemas de Esgotamento Sanit\u00e1rio no Munic\u00edpio de Granja/CE.</p><p>ACORDAM os Ministros do Tribunal de Contas da Uni\u00e3o, reunidos em sess\u00e3o desta 1\u00aa C\u00e2mara, ante as raz\u00f5es expostas pelo relator, e com fundamento nos arts. 1\u00ba, inciso I, 12, \u00a7 3\u00ba, 16, inciso III, al\u00edneas \"a\" e \"c\", e \u00a7\u00a72\u00ba e 3\u00ba, 19, 23, inciso III, 26, 28, inciso II, e 57 da Lei 8.443/1992 c/c os arts. 1\u00ba, inciso I, 209, incisos II e III, 210, 214, inciso III, al\u00ednea \"a\", 215 a 217 e 267 do Regimento Interno, em: </p><p>9.1. excluir Esmerino Oliveira Arruda Coelho da rela\u00e7\u00e3o processual;</p><p>9.2. declarar rev\u00e9is H\u00e9lio Fontenele Magalh\u00e3es, Jos\u00e9 da Silva e Construtora Frei Dami\u00e3o Ltda.;</p><p>9.3. julgar irregulares as contas de H\u00e9lio Fontenele Magalh\u00e3es, Jos\u00e9 da Silva e da Construtora Frei Dami\u00e3o Ltda., e conden\u00e1-los, solidariamente, ao pagamento das quantias a seguir especificadas, com a fixa\u00e7\u00e3o do prazo de quinze dias, a contar da notifica\u00e7\u00e3o, para comprovarem, perante o Tribunal (art. 214, inciso III, al\u00ednea \"a\", do Regimento Interno) , o recolhimento da d\u00edvida aos cofres da Funda\u00e7\u00e3o Nacional de Sa\u00fade, atualizada monetariamente e acrescida dos juros de mora, calculados a partir das datas discriminadas, at\u00e9 a data do recolhimento, na forma prevista na legisla\u00e7\u00e3o em vigor.</p><p>9.3.1 H\u00e9lio Fontenele Magalh\u00e3es individualmente:</p><table><tbody><tr>\t<td><p class=\"body_Text\">Valor original (R$) </p></td>\t<td><p class=\"body_Text\">Data de ocorr\u00eancia</p></td>\t<td><p class=\"body_Text\">D\u00e9bito/Cr\u00e9dito</p></td></tr><tr>\t<td><p class=\"body_Text\">1.060.000,00</p></td>\t<td><p class=\"body_Text\">21/9/2009</p></td>\t<td><p class=\"body_Text\">D</p></td></tr><tr>\t<td><p class=\"body_Text\">530.000,00</p></td>\t<td><p class=\"body_Text\">8/9/2010</p></td>\t<td><p class=\"body_Text\">D</p></td></tr><tr>\t<td><p class=\"body_Text\">1.060.000,00</p></td>\t<td><p class=\"body_Text\">1/7/2011</p></td>\t<td><p class=\"body_Text\">D</p></td></tr><tr>\t<td><p class=\"body_Text\">316.665,74</p></td>\t<td><p class=\"body_Text\">11/08/2011</p></td>\t<td><p class=\"body_Text\">C</p></td></tr><tr>\t<td><p class=\"body_Text\">148.200,08</p></td>\t<td><p class=\"body_Text\">06/09/2011</p></td>\t<td><p class=\"body_Text\">C</p></td></tr><tr>\t<td><p class=\"body_Text\">161.818,91</p></td>\t<td><p class=\"body_Text\">03/10/2011</p></td>\t<td><p class=\"body_Text\">C</p></td></tr><tr>\t<td><p class=\"body_Text\">259.579,43</p></td>\t<td><p class=\"body_Text\">27/10/2011</p></td>\t<td><p class=\"body_Text\">C</p></td></tr><tr>\t<td><p class=\"body_Text\">175.849,57</p></td>\t<td><p class=\"body_Text\">22/11/2011</p></td>\t<td><p class=\"body_Text\">C</p></td></tr><tr>\t<td><p class=\"body_Text\">85.336,27</p></td>\t<td><p class=\"body_Text\">09/03/2012</p></td>\t<td><p class=\"body_Text\">C</p></td></tr></tbody></table><p>9.3.2. H\u00e9lio Fontenele Magalh\u00e3es, solidariamente com a Construtora Frei Dami\u00e3o Ltda. e com Jos\u00e9 da Silva:</p><table><tbody><tr>\t<td><p class=\"body_Text\">Valor original (R$) </p></td>\t<td><p class=\"body_Text\">Data de ocorr\u00eancia</p></td>\t<td><p class=\"body_Text\">D\u00e9bito/Cr\u00e9dito</p></td></tr><tr>\t<td><p class=\"body_Text\">316.665,74</p></td>\t<td><p class=\"body_Text\">11/08/2011</p></td>\t<td><p class=\"body_Text\">D</p></td></tr><tr>\t<td><p class=\"body_Text\">148.200,08</p></td>\t<td><p class=\"body_Text\">06/09/2011</p></td>\t<td><p class=\"body_Text\">D</p></td></tr><tr>\t<td><p class=\"body_Text\">161.818,91</p></td>\t<td><p class=\"body_Text\">03/10/2011</p></td>\t<td><p class=\"body_Text\">D</p></td></tr><tr>\t<td><p class=\"body_Text\">259.579,43</p></td>\t<td><p class=\"body_Text\">27/10/2011</p></td>\t<td><p class=\"body_Text\">D</p></td></tr><tr>\t<td><p class=\"body_Text\">175.849,57</p></td>\t<td><p class=\"body_Text\">22/11/2011</p></td>\t<td><p class=\"body_Text\">D</p></td></tr><tr>\t<td><p class=\"body_Text\">85.336,27</p></td>\t<td><p class=\"body_Text\">09/03/2012</p></td>\t<td><p class=\"body_Text\">D</p></td></tr></tbody></table><p>9.4. aplicar individualmente a H\u00e9lio Fontenele Magalh\u00e3es, Jos\u00e9 da Silva e \u00e0 Construtora Frei Dami\u00e3o Ltda., multas nos valores de R$ 450.000,00 (quatrocentos e cinquenta mil reais) , R$ 180.000,00 (cento e oitenta mil reais) e R$ 180.000,00 (cento e oitenta mil reais) , respectivamente, fixando-lhes o prazo de quinze dias, a contar da notifica\u00e7\u00e3o, para que comprovem, perante o Tribunal, o recolhimento da d\u00edvida aos cofres do Tesouro Nacional, atualizada monetariamente desde a data presente ac\u00f3rd\u00e3o at\u00e9 a do efetivo recolhimento, se pagas ap\u00f3s o vencimento, na forma da legisla\u00e7\u00e3o em vigor;</p><p>9.5. autorizar, desde logo, a cobran\u00e7a judicial das d\u00edvidas, caso n\u00e3o atendidas as notifica\u00e7\u00f5es;</p><p>9.6. autorizar, caso requerido e se o processo n\u00e3o tiver sido remetido para cobran\u00e7a judicial, o parcelamento das d\u00edvidas em at\u00e9 36 (trinta e seis) parcelas mensais e consecutivas;</p><p>9.7. fixar o vencimento da primeira parcela em quinze dias, a contar do recebimento da notifica\u00e7\u00e3o, e os das demais a cada 30 dias, devendo incidir sobre cada valor mensal os correspondentes acr\u00e9scimos legais, na forma prevista na legisla\u00e7\u00e3o em vigor;</p><p>9.8. alertar os respons\u00e1veis que, em caso de parcelamento da d\u00edvida, a falta de pagamento de qualquer parcela importar\u00e1 no vencimento antecipado do saldo devedor;</p><p>9.9. remeter c\u00f3pia da presente delibera\u00e7\u00e3o \u00e0 Funasa e aos respons\u00e1veis, para ci\u00eancia;</p><p>9.10. informar \u00e0 Procuradoria da Rep\u00fablica no Estado do Cear\u00e1, \u00e0 Funasa e aos respons\u00e1veis que a presente delibera\u00e7\u00e3o, acompanhada do Relat\u00f3rio e do Voto que a fundamentam, est\u00e1 dispon\u00edvel para a consulta no endere\u00e7o www.tcu.gov.br/acordaos.</p>", "ASSUNTO": "Tomada de Contas Especial instaurada pela Funda\u00e7\u00e3o Nacional de Sa\u00fade em raz\u00e3o da impugna\u00e7\u00e3o total das despesas realizadas com os recursos do Termo de Compromisso n\u00b0 283/2007, celebrado com a Prefeitura Municipal de Granja/CE, tendo por objeto a constru\u00e7\u00e3o de sistema de esgotamento sanit\u00e1rio.", "COLEGIADO": "Primeira C\u00e2mara", "DATASESSAO": "11/05/2021", "ENTIDADE": " Munic\u00edpio de Granja/CE", "INTERESSADOS": "3. Respons\u00e1veis: Construtora Frei Dami\u00e3o Ltda - ME (08.681.846/0001-46); Esmerino Oliveira Arruda Coelho (XXX.227.217-XX); H\u00e9lio Fontenele Magalh\u00e3es (XXX.158.223-XX); Jose da Silva (XXX.172.623-XX)", "PROC": "<a href=\"https://pesquisa.apps.tcu.gov.br/#/push/processo?numero=03341020194\" target=\"_blank\">033.410/2019-4</a>", "QUORUM": " <br>13.1. Ministros presentes: Walton Alencar Rodrigues (Presidente), Benjamin Zymler e Jorge Oliveira (Relator).<br>13.2. Ministros-Substitutos presentes: Augusto Sherman Cavalcanti e Weder de Oliveira.", "RELATOR": "JORGE OLIVEIRA", "RELATORIO": "<p>Adoto como relat\u00f3rio a instru\u00e7\u00e3o da Secretaria de Controle Externo de Tomada de Contas Especial - Secex/TCE (pe\u00e7a 41) , que contou com o endosso dos dirigentes daquela unidade (pe\u00e7as 42 e 43) e a concord\u00e2ncia do Minist\u00e9rio P\u00fablico junto ao TCU (pe\u00e7a 44) :</p><p>\"<b><i>INTRODU\u00c7\u00c3O</i></b></p><p class=\"list_Paragraph\"><i>\tCuidam os autos de Tomada de Contas Especial instaurada pela Funda\u00e7\u00e3o Nacional de Sa\u00fade - Funasa, em desfavor do Sr. H\u00e9lio Fontenele Magalh\u00e3es (CPF: XXX.158.223-XX) , Prefeito Municipal de Granja/CE de 4/4 a 14/11/2012 e do Sr. Esmerino Oliveira Arruda Coelho (CPF XXX.227.217-XX - falecido) , Prefeito Municipal de Granja/CE de 1/1/2009 a 3/4/2012, em raz\u00e3o da impugna\u00e7\u00e3o total dos recursos repassados por meio do TC PAC 283/2007 - Siafi 635261 (pe\u00e7a 8, p. 12-13) , celebrado com a Funasa, tendo por objeto a execu\u00e7\u00e3o de Sistemas de Esgotamento Sanit\u00e1rio. </i></p><h4><i>HIST\u00d3RICO </i></h4><p class=\"list_Paragraph\"><i>\tPara a execu\u00e7\u00e3o do objeto foi previsto um total de R$ 5.583.939,78, sendo R$ 5.300.000,00 a cargo da concedente e R$ 283.939,78 de contrapartida municipal, conforme cl\u00e1usula segunda do TC PAC 283/2007 (pe\u00e7a 8, p. 12) e cl\u00e1usula primeira do Termo de Aprova\u00e7\u00e3o Formal do Termo de Compromisso (pe\u00e7a 8, p. 14) . </i></p><p class=\"list_Paragraph\"><i>O conv\u00eanio teve por objeto a execu\u00e7\u00e3o de dois sistemas de esgotamento sanit\u00e1rio, nas localidades de Timonha e Adrian\u00f3polis, compostos de rede coletora, esta\u00e7\u00e3o elevat\u00f3ria, esta\u00e7\u00e3o de tratamento de esgoto, emiss\u00e1rio e liga\u00e7\u00f5es domiciliares, conforme Plano de Trabalho (pe\u00e7a 8, p. 4-6) .</i></p><p class=\"list_Paragraph\"><i>Os recursos foram transferidos pela Funasa conforme quadro a seguir:</i></p><table><tbody><tr>\t<td><p class=\"list_Paragraph\"><b><i>Ordem Banc\u00e1ria</i></b></p></td>\t<td><p class=\"list_Paragraph\"><b><i>Data do cr\u00e9dito (pe\u00e7a 11) </i></b></p></td>\t<td><p class=\"list_Paragraph\"><b><i>Valor (R$) </i></b></p></td></tr><tr>\t<td><p class=\"list_Paragraph\"><i>2009OB808909</i></p></td>\t<td><p class=\"list_Paragraph\"><i>21/9/2009</i></p></td>\t<td><p class=\"list_Paragraph\"><i>1.060.000,00</i></p></td></tr><tr>\t<td><p class=\"list_Paragraph\"><i>2010OB808794</i></p></td>\t<td><p class=\"list_Paragraph\"><i>8/9/2010</i></p></td>\t<td><p class=\"list_Paragraph\"><i>530.000,00</i></p></td></tr><tr>\t<td><p class=\"list_Paragraph\"><i>2011OB804396</i></p></td>\t<td><p class=\"list_Paragraph\"><i>1/7/2011</i></p></td>\t<td><p class=\"list_Paragraph\"><i>1.060.000,00</i></p></td></tr><tr>\t<td><p class=\"list_Paragraph\"><b><i>TOTAL</i></b></p></td>\t<td><p class=\"list_Paragraph\"><b><i>2.650.000,00</i></b></p></td></tr></tbody></table><p class=\"list_Paragraph\"><i>A vig\u00eancia do conv\u00eanio foi de 31/12/2007 a 18/6/2012, conforme 4\u00ba Termo Aditivo (pe\u00e7a 8, p. 65) , com prazo para apresenta\u00e7\u00e3o da presta\u00e7\u00e3o de contas at\u00e9 17/8/2012.</i></p><p class=\"list_Paragraph\"><i>A Funasa realizou duas visitas t\u00e9cnicas ao munic\u00edpio em junho de 2011 e abril de 2014, conforme Relat\u00f3rio de Visita T\u00e9cnica (pe\u00e7a 8, p. 57-58) e Parecer T\u00e9cnico (pe\u00e7a 6) , tendo apontado, neste \u00faltimo, execu\u00e7\u00e3o f\u00edsica de 28,35%, que as obras estavam paralisadas desde o segundo semestre de 2012 e se encontravam em estado de abandono, com destrui\u00e7\u00e3o de algumas unidades constru\u00eddas.</i></p><p class=\"list_Paragraph\"><i>No mesmo parecer t\u00e9cnico consta a informa\u00e7\u00e3o que o munic\u00edpio havia encaminhado \u00e0 Funasa relat\u00f3rio de andamento, por meio do Of\u00edcio 350/2012, de 1/11/2012, informando que as obras haviam alcan\u00e7ado 51,15% de execu\u00e7\u00e3o, o que n\u00e3o restou comprovado na visita t\u00e9cnica realizada.</i></p><p class=\"list_Paragraph\"><i>Por meio do Parecer Financeiro 164/2014 (pe\u00e7a 8, p. 89-92) a Funasa opinou pela reprova\u00e7\u00e3o integral dos recursos repassados, no valor de R$ 2.650.000,00, registrando o seguinte:</i></p><p class=\"list_Paragraph\"><i>a) a presta\u00e7\u00e3o de contas parcial das 1\u00aa e 2\u00aa parcelas foi encaminhada em 8/11/2010 e aprovada por meio do Parecer Financeiro 163/2011 (inexistente nos autos) ;</i></p><p class=\"list_Paragraph\"><i>b) n\u00e3o foi apresentada a presta\u00e7\u00e3o de contas referente \u00e0 3\u00aa parcela do conv\u00eanio;</i></p><p class=\"list_Paragraph\"><i>c) execu\u00e7\u00e3o f\u00edsica do objeto em 28,35%;</i></p><p class=\"list_Paragraph\"><i>d) que foi impetrada contra os respons\u00e1veis A\u00e7\u00e3o Civil de Improbidade Administrativa; </i></p><p class=\"list_Paragraph\"><i>e) aus\u00eancia de documento de posse dos terrenos; e</i></p><p class=\"list_Paragraph\"><i>f) n\u00e3o devolu\u00e7\u00e3o do saldo e utiliza\u00e7\u00e3o indevida dos rendimentos financeiros, que n\u00e3o foram considerados no d\u00e9bito em raz\u00e3o da impugna\u00e7\u00e3o total.</i></p><p class=\"list_Paragraph\"><i>Os respons\u00e1veis foram notificados da reprova\u00e7\u00e3o da presta\u00e7\u00e3o de contas por meio dos Of\u00edcios 823/2014, 824/2014, 1434/2015 e 56/2016 (pe\u00e7a 8, p. 99-100, 103-104, 122-124 e 126) .  </i></p><p class=\"list_Paragraph\"><i>No \u00faltimo Parecer Financeiro 119/2016 (pe\u00e7a 8, p. 130-133) , a Funasa manteve a reprova\u00e7\u00e3o total dos recursos repassados, acrescentando \u00e0s considera\u00e7\u00f5es feitas no Parecer Financeiro 164/2014, o seguinte:</i></p><p class=\"list_Paragraph\"><i>a) as despesas ocorreram entre julho e novembro de 2011, per\u00edodo em que o Sr. H\u00e9lio Fontenele Magalh\u00e3es assinava como prefeito municipal, havendo ainda uma sa\u00edda de R$ 85.336,27 em mar\u00e7o/2012 n\u00e3o justificada;</i></p><p class=\"list_Paragraph\"><i>b) que o Sr. H\u00e9lio Fontenele Magalh\u00e3es, mesmo n\u00e3o exercendo o cargo de prefeito entre julho e novembro de 2011, assinou todas as notas de empenho e de pagamento do conv\u00eanio, bem como o pedido de prorroga\u00e7\u00e3o do conv\u00eanio em 12/6/2012, sendo, portanto, respons\u00e1vel pela aplica\u00e7\u00e3o dos recursos e pela apresenta\u00e7\u00e3o da presta\u00e7\u00e3o de contas referente \u00e0 3\u00aa parcela.</i></p><p class=\"list_Paragraph\"><i>Os respons\u00e1veis foram notificados da reprova\u00e7\u00e3o da presta\u00e7\u00e3o de contas e do teor do Parecer Financeiro 119/2016 (pe\u00e7a 8, p. 144-147 e 164-166) .</i></p><p class=\"list_Paragraph\"><i>O Relat\u00f3rio de Tomada de Contas Especial (pe\u00e7a 8, p. 170-174) indicou a ocorr\u00eancia de preju\u00edzo ao er\u00e1rio no valor de R$ 2.650.000,00, em raz\u00e3o da impugna\u00e7\u00e3o total dos recursos repassados, tendo responsabilizado solidariamente pelo dano o Sr. H\u00e9lio Fontenele Magalh\u00e3es (CPF: XXX.158.223-XX) , Prefeito Municipal de Granja/CE de 4/4 a 14/11/2012 e o Sr. Esmerino Oliveira Arruda Coelho (CPF XXX.227.217-XX - falecido) , Prefeito Municipal de Granja/CE de 1/1/2009 a 3/4/2012.</i></p><p class=\"list_Paragraph\"><i>O Relat\u00f3rio de Auditoria 624/2019 da Controladoria Geral da Uni\u00e3o - CGU, bem como os respectivos Certificado de Auditoria, Parecer do Dirigente de Controle Interno e Pronunciamento Ministerial (pe\u00e7a 2, p. 5-13) conclu\u00edram pelas mesmas irregularidades e responsabilidades apontadas no Relat\u00f3rio de Tomada de Contas Especial da Funasa.</i></p><p class=\"list_Paragraph\"><i>Na instru\u00e7\u00e3o inicial de pe\u00e7a 14, ao se examinar os elementos constantes dos autos, opinou-se pelo afastamento da responsabilidade do Sr. Esmerino Oliveira Arruda Coelho, uma vez que n\u00e3o havia praticado qualquer ato de gest\u00e3o relacionado ao conv\u00eanio, o que contou com a anu\u00eancia da relatora (pe\u00e7a 17) . Dessa forma, deve ser exclu\u00eddo da rela\u00e7\u00e3o processual desta TCE.</i></p><p class=\"list_Paragraph\"><i>Na mesma instru\u00e7\u00e3o, prop\u00f4s-se a responsabiliza\u00e7\u00e3o da Construtora Frei Dami\u00e3o Ltda. (CNPJ 08.681.846/0001-46) e de seu s\u00f3cio administrador, n\u00e3o responsabilizados pela Funasa, ante a constata\u00e7\u00e3o de recebimento por servi\u00e7os n\u00e3o executados. </i></p><p class=\"list_Paragraph\"><i>Com rela\u00e7\u00e3o \u00e0 responsabiliza\u00e7\u00e3o do s\u00f3cio administrador, Sr. Jos\u00e9 da Silva, conforme registrado no item 32 da instru\u00e7\u00e3o de pe\u00e7a 14, verificou-se que a Construtora Frei Dami\u00e3o Ltda. se encontrava na situa\u00e7\u00e3o cadastral 'baixada', desde 17/11/2016 (pe\u00e7a 13) . Assim, prop\u00f4s-se sua cita\u00e7\u00e3o, em solidariedade com a empresa e o ex-gestor, a exemplo do entendimento manifestado pelo Ministro Andr\u00e9 de Carvalho no despacho de pe\u00e7a 70 do TC <a href=\"https://pesquisa.apps.tcu.gov.br/#/doc/processo/843420166\" target=\"_blank\">Processo 008.434/2016-6</a>, que determinou a cita\u00e7\u00e3o dos s\u00f3cios diretores em raz\u00e3o do encerramento das atividades da empresa da qual eram s\u00f3cios.</i></p><p class=\"list_Paragraph\"><i>Assim, entendeu-se necess\u00e1ria a cita\u00e7\u00e3o e audi\u00eancia dos respons\u00e1veis nos seguintes termos:</i></p><p><i>a)\t realizar a </i><b><i>CITA\u00c7\u00c3O</i></b><i> solid\u00e1ria do Sr. H\u00e9lio Fontenele Magalh\u00e3es (CPF: XXX.158.223-XX) , Prefeito Municipal de Granja/CE de 4/4 a 14/11/2012, com a Construtora Frei Dami\u00e3o Ltda. (CNPJ 08.681.846/0001-46) e com o seu ent\u00e3o s\u00f3cio administrador, Sr. Jos\u00e9 da Silva (CPF: XXX.172.623-XX) , com fundamento nos arts. 10, \u00a7 1\u00ba, e 12, incisos I e II, da Lei 8.443/1992 c/c o art. 202, incisos I e II, do RI/TCU, para que, no prazo de quinze dias, apresentem alega\u00e7\u00f5es de defesa e/ou recolham aos cofres do Tesouro Nacional as quantias abaixo indicadas, atualizadas monetariamente a partir das respectivas datas at\u00e9 o efetivo recolhimento, abatendo-se na oportunidade a quantia eventualmente ressarcida, na forma da legisla\u00e7\u00e3o em vigor, em decorr\u00eancia da irregularidade abaixo descrita:</i></p><p><i>a.1) Sr. H\u00e9lio Fontenele Magalh\u00e3es </i><b><i>individualmente</i></b><i>:</i></p><p class=\"list_Paragraph\"><b><i>\tIrregularidade</i></b><i>: n\u00e3o comprova\u00e7\u00e3o da boa e regular aplica\u00e7\u00e3o dos recursos federais repassados atrav\u00e9s do TC PAC 283/2007, em face da omiss\u00e3o no dever de prestar contas da 3\u00aa parcela do conv\u00eanio.</i></p><p class=\"list_Paragraph\"><b><i>\tDispositivos violados</i></b><i>: par\u00e1grafo \u00fanico do art. 70 da Constitui\u00e7\u00e3o Federal; art. 93 do Decreto-Lei 200/67; arts. 28, da IN/STN 1/2007; al\u00edneas 'a', 'b' e 'c', da cl\u00e1usula terceira do TC PAC 283/2007.</i></p><p class=\"list_Paragraph\"><b><i>\tQuantifica\u00e7\u00e3o do d\u00e9bito</i></b><i>:</i></p><table><tbody><tr>\t<td><p class=\"body_Text\"><i>VALOR ORIGINAL (R$) </i></p></td>\t<td><p class=\"body_Text\"><i>DATA DA OCORR\u00caNCIA</i></p></td>\t<td><p class=\"body_Text\"><i>D\u00c9BITO/CR\u00c9DITO</i></p></td></tr><tr>\t<td><p class=\"body_Text\"><i>1.060.000,00</i></p></td>\t<td><p class=\"body_Text\"><i>21/9/2009</i></p></td>\t<td><p class=\"body_Text\"><i>D</i></p></td></tr><tr>\t<td><p class=\"body_Text\"><i>530.000,00</i></p></td>\t<td><p class=\"body_Text\"><i>8/9/2010</i></p></td>\t<td><p class=\"body_Text\"><i>D</i></p></td></tr><tr>\t<td><p class=\"body_Text\"><i>1.060.000,00</i></p></td>\t<td><p class=\"body_Text\"><i>1/7/2011</i></p></td>\t<td><p class=\"body_Text\"><i>D</i></p></td></tr><tr>\t<td><p class=\"body_Text\"><i>316.665,74</i></p></td>\t<td><p class=\"body_Text\"><i>11/08/2011</i></p></td>\t<td><p class=\"body_Text\"><i>C</i></p></td></tr><tr>\t<td><p class=\"body_Text\"><i>148.200,08</i></p></td>\t<td><p class=\"body_Text\"><i>06/09/2011</i></p></td>\t<td><p class=\"body_Text\"><i>C</i></p></td></tr><tr>\t<td><p class=\"body_Text\"><i>161.818,91</i></p></td>\t<td><p class=\"body_Text\"><i>03/10/2011</i></p></td>\t<td><p class=\"body_Text\"><i>C</i></p></td></tr><tr>\t<td><p class=\"body_Text\"><i>259.579,43</i></p></td>\t<td><p class=\"body_Text\"><i>27/10/2011</i></p></td>\t<td><p class=\"body_Text\"><i>C</i></p></td></tr><tr>\t<td><p class=\"body_Text\"><i>175.849,57</i></p></td>\t<td><p class=\"body_Text\"><i>22/11/2011</i></p></td>\t<td><p class=\"body_Text\"><i>C</i></p></td></tr><tr>\t<td><p class=\"body_Text\"><i>85.336,27</i></p></td>\t<td><p class=\"body_Text\"><i>09/03/2012</i></p></td>\t<td><p class=\"body_Text\"><i>C</i></p></td></tr></tbody></table><p class=\"list_Paragraph\"><b><i>\tCofre para recolhimento</i></b><i>: Tesouro Nacional</i></p><p class=\"list_Paragraph\"><b><i>\tConduta</i></b><i>: omitir-se do dever de prestar contas da 3\u00aa parcela dos recursos federais repassados atrav\u00e9s do TC PAC 283/2007.</i></p><p class=\"list_Paragraph\"><b><i>\tNexo de causalidade</i></b><i>: a omiss\u00e3o do dever de prestar contas da 3\u00aa parcela dos recursos federais repassados atrav\u00e9s do TC PAC 283/2007, propiciou a impossibilidade de se comprovar o nexo entre os valores repassados e as despesas realizadas, bem como a interrup\u00e7\u00e3o dos repasses e, consequentemente, a paralisa\u00e7\u00e3o da obra, seu abandono e sua imprestabilidade, resultando em dano ao er\u00e1rio correspondente ao valor total repassado.</i></p><p class=\"list_Paragraph\"><i>\t</i><b><i>Culpabilidade</i></b><i>: n\u00e3o h\u00e1 excludentes de ilicitude, de culpabilidade ou de punibilidade. \u00c9 razo\u00e1vel supor que o respons\u00e1vel tinha consci\u00eancia da ilicitude de sua conduta, sendo-lhe exig\u00edvel conduta diversa daquela que foi adotada, qual seja, desincumbir-se do seu dever por meio da apresenta\u00e7\u00e3o da presta\u00e7\u00e3o de contas da 3\u00aa parcela do conv\u00eanio, comprovando assim a boa e regular aplica\u00e7\u00e3o dos recursos.</i></p><p><i>a.2) Sr. H\u00e9lio Fontenele Magalh\u00e3es </i><b><i>solidariamente</i></b><i> com a Construtora Frei Dami\u00e3o Ltda. e com o Sr. Jos\u00e9 da Silva (CPF: XXX.172.623-XX) :</i></p><p class=\"list_Paragraph\"><b><i>\tIrregularidade</i></b><i>: execu\u00e7\u00e3o parcial do objeto do TC PAC 283/2007 em 28,35% com realiza\u00e7\u00e3o de pagamentos a maior, equivalentes a 50% do total.</i></p><p class=\"list_Paragraph\"><b><i>\tDispositivos violados - Sr. H\u00e9lio Fontenele Magalh\u00e3es</i></b><i>: par\u00e1grafo \u00fanico do art. 70 da Constitui\u00e7\u00e3o Federal; art. 93 do Decreto-Lei 200/67; art. 22 da IN/STN 1/2007; al\u00edneas 'a', 'b' e 'c', da cl\u00e1usula terceira do TC PAC 283/2007.</i></p><p class=\"list_Paragraph\"><b><i>\tDispositivos violados - Construtora Frei Dami\u00e3o Ltda. e Sr. Jos\u00e9 da Silva</i></b><i>: arts. 62 e 63 da Lei 4.320/1964.</i></p><p class=\"list_Paragraph\"><b><i>\tQuantifica\u00e7\u00e3o do d\u00e9bito</i></b><i>:</i></p><table><tbody><tr>\t<td><p class=\"body_Text\"><i>VALOR ORIGINAL (R$) </i></p></td>\t<td><p class=\"body_Text\"><i>DATA DA OCORR\u00caNCIA</i></p></td></tr><tr>\t<td><p class=\"body_Text\"><i>316.665,74</i></p></td>\t<td><p class=\"body_Text\"><i>11/08/2011</i></p></td></tr><tr>\t<td><p class=\"body_Text\"><i>148.200,08</i></p></td>\t<td><p class=\"body_Text\"><i>06/09/2011</i></p></td></tr><tr>\t<td><p class=\"body_Text\"><i>161.818,91</i></p></td>\t<td><p class=\"body_Text\"><i>03/10/2011</i></p></td></tr><tr>\t<td><p class=\"body_Text\"><i>259.579,43</i></p></td>\t<td><p class=\"body_Text\"><i>27/10/2011</i></p></td></tr><tr>\t<td><p class=\"body_Text\"><i>175.849,57</i></p></td>\t<td><p class=\"body_Text\"><i>22/11/2011</i></p></td></tr><tr>\t<td><p class=\"body_Text\"><i>85.336,27</i></p></td>\t<td><p class=\"body_Text\"><i>09/03/2012</i></p></td></tr></tbody></table><p class=\"list_Paragraph\"><b><i>\tCofre para recolhimento</i></b><i>: Tesouro Nacional</i></p><p class=\"list_Paragraph\"><b><i>\tConduta - Sr. H\u00e9lio Fontenele Magalh\u00e3es</i></b><i>: executar parcialmente o objeto pactuado em 28,35%, e realizar pagamentos a maior, equivalentes a 50% do total.</i></p><p class=\"list_Paragraph\"><b><i>\tConduta - Construtora Frei Dami\u00e3o Ltda. e Sr. Jos\u00e9 da Silva</i></b><i>: executar parcialmente o objeto contratado em 28,35% e receber o equivalente a 50% do total das obras.</i></p><p class=\"list_Paragraph\"><b><i>\tNexo de causalidade - Sr. H\u00e9lio Fontenele Magalh\u00e3es</i></b><i>: a execu\u00e7\u00e3o parcial do objeto do TC PAC 283/2007 em 28,35% com realiza\u00e7\u00e3o de pagamentos a maior, equivalentes a 50% do total, propiciou o n\u00e3o atingimento dos objetivos pactuados no conv\u00eanio e, consequentemente, dano ao er\u00e1rio equivalente \u00e0 diferen\u00e7a entre o valor executado e o pago.</i></p><p class=\"list_Paragraph\"><b><i>\tNexo de causalidade - Construtora Frei Dami\u00e3o Ltda. e Sr. Jos\u00e9 da Silva</i></b><i>: a execu\u00e7\u00e3o parcial do objeto contratado em 28,35%, com recebimento de pagamentos equivalentes a 50% do total das obras, resultou em dano ao er\u00e1rio equivalente \u00e0 diferen\u00e7a entre o valor recebido e o executado.</i></p><p class=\"list_Paragraph\"><i>\t</i><b><i>Culpabilidade - Sr. H\u00e9lio Fontenele Magalh\u00e3es</i></b><i>: n\u00e3o h\u00e1 excludentes de ilicitude, de culpabilidade ou de punibilidade. \u00c9 razo\u00e1vel supor que o respons\u00e1vel tinha consci\u00eancia da ilicitude de sua conduta, sendo-lhe exig\u00edvel conduta diversa daquela que foi adotada, qual seja, executar integralmente o objeto conveniado e abster-se de realizar pagamentos por servi\u00e7os n\u00e3o realizados, comprovando assim a boa e regular aplica\u00e7\u00e3o dos recursos.</i></p><p class=\"list_Paragraph\"><b><i>\tCulpabilidade - Construtora Frei Dami\u00e3o Ltda. e Sr. Jos\u00e9 da Silva</i></b><i>: n\u00e3o h\u00e1 excludentes de ilicitude, de culpabilidade ou de punibilidade. \u00c9 razo\u00e1vel supor que o Sr. Jos\u00e9 da Silva e a empresa, por ele representada, tinham consci\u00eancia da ilicitude de suas condutas, sendo-lhes exig\u00edveis condutas diversas daquelas que foram adotadas, qual seja, executar integralmente o objeto contratado e abster-se de receberem por servi\u00e7os n\u00e3o executados.</i></p><p class=\"list_Paragraph\"><i>b) \trealizar a </i><b><i>AUDI\u00caNCIA</i></b><i> do Sr. H\u00e9lio Fontenele Magalh\u00e3es (CPF: XXX.158.223-XX) , Prefeito Municipal de Granja/CE de 4/4 a 14/11/2012, com fundamento no art. 12, inciso III, da Lei 8.443/1992, para, no prazo de quinze dias, a contar do recebimento da presente comunica\u00e7\u00e3o, apresentar raz\u00f5es de justificativa quanto \u00e0 irregularidade detalhada a seguir:</i></p><p class=\"list_Paragraph\"><i>\t</i><b><i>Irregularidade</i></b><i>: n\u00e3o cumprimento do prazo originalmente estipulado para presta\u00e7\u00e3o de contas final do TC PAC 283/2007, firmado com a Funda\u00e7\u00e3o Nacional de Sa\u00fade e que tinha por objeto e execu\u00e7\u00e3o de sistemas de esgotamento sanit\u00e1rio, o qual se encerrou em 10/5/2012.</i></p><p class=\"list_Paragraph\"><i>\t</i><b><i>Conduta</i></b><i>: descumprir o prazo originalmente estipulado para a apresenta\u00e7\u00e3o da presta\u00e7\u00e3o de contas final do TC PAC 283/2007, o qual se encerrou em 10/5/2012.</i></p><p class=\"list_Paragraph\"><i>\t</i><b><i>Nexo de causalidade</i></b><i>: o descumprimento do prazo originalmente estipulado para presta\u00e7\u00e3o de contas final do TC PAC 283/2007 impediu o estabelecimento do nexo causal entre as poss\u00edveis despesas efetuadas e os recursos recebidos no \u00e2mbito do TC PAC 283/2007.</i></p><p class=\"list_Paragraph\"><i>\t</i><b><i>Culpabilidade</i></b><i>: n\u00e3o h\u00e1 excludentes de ilicitude, de culpabilidade e de punibilidade; \u00e9 razo\u00e1vel supor que o respons\u00e1vel tinha consci\u00eancia da ilicitude de sua conduta, sendo-lhe exig\u00edvel conduta diversa daquela que foi adotada, qual seja, desincumbir-se do seu dever por meio da apresenta\u00e7\u00e3o da presta\u00e7\u00e3o de contas da 3\u00aa parcela no prazo e forma devidos.</i></p><p class=\"list_Paragraph\"><i>Em cumprimento ao despacho da relatora, Ministra Ana Arraes (pe\u00e7a 17) , foram promovidas as cita\u00e7\u00f5es e audi\u00eancia dos respons\u00e1veis conforme quadro a seguir:</i></p><table><tbody><tr>\t<td><p><b><i>Respons\u00e1vel</i></b></p></td>\t<td><p class=\"list_Paragraph\"><b><i>Cita\u00e7\u00e3o</i></b></p></td>\t<td><p class=\"list_Paragraph\"><b><i>Recebimento</i></b></p></td>\t<td><p class=\"list_Paragraph\"><b><i>Origem do endere\u00e7o</i></b></p></td></tr><tr>\t<td><p class=\"list_Paragraph\"><i>H\u00e9lio Fontenele Magalh\u00e3es</i></p></td>\t<td><p class=\"list_Paragraph\"><i>Of\u00edcio 32.797/2020 (pe\u00e7a 24) </i></p></td>\t<td><p class=\"list_Paragraph\"><i>27/12/2020 (pe\u00e7a 27) </i></p></td>\t<td><p class=\"list_Paragraph\"><i>Base de dados do TCU (pe\u00e7a 18) </i></p></td></tr><tr>\t<td><p class=\"list_Paragraph\"/><p class=\"list_Paragraph\"/><p class=\"list_Paragraph\"/><p class=\"list_Paragraph\"/><p class=\"list_Paragraph\"/><p class=\"list_Paragraph\"><i>Construtora Frei Dami\u00e3o Ltda.</i></p></td>\t<td><p class=\"list_Paragraph\"><i>Of\u00edcio 24.671/2020 (pe\u00e7a 22) </i></p></td>\t<td><p class=\"list_Paragraph\"><i>'Ausente 3X' (pe\u00e7a 25) </i></p></td>\t<td><p class=\"list_Paragraph\"><i>Receita Federal (pe\u00e7a 19) </i></p></td></tr><tr>\t<td><p class=\"list_Paragraph\"/></td>\t<td><p class=\"list_Paragraph\"><i>Of\u00edcio 46.594/2020 (pe\u00e7a 31) </i></p></td>\t<td><p class=\"list_Paragraph\"><i>6/10/2020 (pe\u00e7a 36) </i></p></td>\t<td><p class=\"list_Paragraph\"><i>TSE (pe\u00e7a 28) - endere\u00e7o do representante legal</i></p></td></tr><tr>\t<td><p class=\"list_Paragraph\"/></td>\t<td><p class=\"list_Paragraph\"><i>Of\u00edcio 46.595/2020 (pe\u00e7a 32) </i></p></td>\t<td><p class=\"list_Paragraph\"><i>6/10/2020 (pe\u00e7a 35) </i></p></td>\t<td><p class=\"list_Paragraph\"><i>Receita Federal (pe\u00e7a 19) </i></p></td></tr><tr>\t<td><p class=\"list_Paragraph\"/></td>\t<td><p class=\"list_Paragraph\"><i>Edital 1428/2020 (pe\u00e7a 30) </i></p></td>\t<td><p class=\"list_Paragraph\"><i>23/9/2020 (pe\u00e7a 34) </i></p></td>\t<td><p class=\"list_Paragraph\"><i>Aus\u00eancia de outros endere\u00e7os dispon\u00edveis (pe\u00e7a 114) </i></p></td></tr><tr>\t<td><p class=\"list_Paragraph\"><i>Jos\u00e9 da Silva</i></p></td>\t<td><p class=\"list_Paragraph\"><i>Of\u00edcio 32.796/2020 (pe\u00e7a 23) </i></p></td>\t<td><p class=\"list_Paragraph\"><i>'Endere\u00e7o insuficiente' (pe\u00e7a 26) </i></p></td>\t<td><p class=\"list_Paragraph\"><i>Receita Federal (pe\u00e7a 20) </i></p></td></tr><tr>\t<td><p class=\"list_Paragraph\"/></td>\t<td><p class=\"list_Paragraph\"><i>Of\u00edcio 51.750/2020 (pe\u00e7a 33) </i></p></td>\t<td><p class=\"list_Paragraph\"><i>6/10/2020 (pe\u00e7a 37) </i></p></td>\t<td><p class=\"list_Paragraph\"><i>TSE (pe\u00e7a 28) </i></p></td></tr></tbody></table><p class=\"list_Paragraph\"><i>Transcorrido o prazo regimental fixado, os respons\u00e1veis permaneceram silentes. Operam-se, portanto, os efeitos da revelia, dando-se prosseguimento ao processo, nos termos do art. 12, \u00a73\u00ba, da Lei 8.443/1992.</i></p><p><b><i>EXAME T\u00c9CNICO</i></b></p><p class=\"list_Paragraph\"><i>Preliminarmente, cumpre tecer breves considera\u00e7\u00f5es sobre a forma como s\u00e3o realizadas as comunica\u00e7\u00f5es processuais no TCU. A esse respeito, destacam-se o art. 179, do Regimento Interno do TCU (Resolu\u00e7\u00e3o 155, de 4/12/2002) e os arts. 3\u00ba e 4\u00ba, inciso III, \u00a7 1\u00ba, da Resolu\u00e7\u00e3o TCU 170, de 30 de junho de 2004, </i><b><i>in verbis</i></b><i>:</i></p><p><b><i>Resolu\u00e7\u00e3o 155/2002 (Regimento Interno) :</i></b></p><p><i>Art. 179. A cita\u00e7\u00e3o, a audi\u00eancia ou a notifica\u00e7\u00e3o, bem como a comunica\u00e7\u00e3o de dilig\u00eancia, far se-\u00e3o:</i></p><p><i>I - mediante ci\u00eancia da parte, efetivada por servidor designado, por meio eletr\u00f4nico, fac-s\u00edmile, telegrama ou qualquer outra forma, desde que fique confirmada inequivocamente a entrega da comunica\u00e7\u00e3o ao destinat\u00e1rio;</i></p><p><i>II - mediante carta registrada, com aviso de recebimento que comprove a entrega no endere\u00e7o do destinat\u00e1rio;</i></p><p><i>III - por edital publicado no Di\u00e1rio Oficial da Uni\u00e3o, quando o seu destinat\u00e1rio n\u00e3o for localizado</i></p><p><i> (...) </i></p><p><b><i>Resolu\u00e7\u00e3o TCU 170/2004:</i></b></p><p><i>Art. 3\u00ba As comunica\u00e7\u00f5es ser\u00e3o encaminhadas aos seus destinat\u00e1rios por meio de:</i></p><p><i>I - correio eletr\u00f4nico, fac-s\u00edmile ou telegrama;</i></p><p><i>II - servidor designado;</i></p><p><i>III - carta registrada, com aviso de recebimento;</i></p><p><i>IV - edital publicado no Di\u00e1rio Oficial da Uni\u00e3o, quando o seu destinat\u00e1rio n\u00e3o for localizado, nas hip\u00f3teses em que seja necess\u00e1rio o exerc\u00edcio de defesa.</i></p><p><i> (...) </i></p><p><i>Art. 4\u00ba. Consideram-se entregues as comunica\u00e7\u00f5es:</i></p><p><i>I - efetivadas conforme disposto nos incisos I e II do artigo anterior, mediante confirma\u00e7\u00e3o da ci\u00eancia do destinat\u00e1rio;</i></p><p><i>II - realizadas na forma prevista no inciso III do artigo anterior, com o retorno do aviso de recebimento, entregue comprovadamente no endere\u00e7o do destinat\u00e1rio;</i></p><p><i>III - na data de publica\u00e7\u00e3o do edital no Di\u00e1rio Oficial da Uni\u00e3o, quando realizadas na forma prevista no inciso IV do artigo anterior.</i></p><p><i>\u00a7 1\u00ba O endere\u00e7o do destinat\u00e1rio dever\u00e1 ser previamente confirmado mediante consulta aos sistemas dispon\u00edveis ao Tribunal ou a outros meios de informa\u00e7\u00e3o, a qual dever\u00e1 ser juntada ao respectivo processo.</i></p><p class=\"list_Paragraph\"><i>Portanto, a validade da cita\u00e7\u00e3o via postal n\u00e3o depende de que o aviso de recebimento seja assinado pelo pr\u00f3prio destinat\u00e1rio da comunica\u00e7\u00e3o, o que dispensa, no caso em tela, a entrega do AR em 'm\u00e3os pr\u00f3prias'. A exig\u00eancia da norma \u00e9 no sentido de o Tribunal verificar se a correspond\u00eancia foi entregue no endere\u00e7o correto, residindo aqui a necessidade de certeza inequ\u00edvoca. </i></p><p class=\"list_Paragraph\"><i>N\u00e3o \u00e9 outra a orienta\u00e7\u00e3o da jurisprud\u00eancia do TCU, conforme se verifica nos julgados a seguir transcritos:</i></p><p><i>S\u00e3o v\u00e1lidas as comunica\u00e7\u00f5es processuais entregues, mediante carta registrada, no endere\u00e7o correto do respons\u00e1vel, n\u00e3o havendo necessidade de que o recebimento seja feito por ele pr\u00f3prio (<a href=\"https://pesquisa.apps.tcu.gov.br/#/doc/acordao-completo/3648/2013/Segunda C\u00e2mara\" target=\"_blank\">Ac\u00f3rd\u00e3o 3648/2013-TCU-Segunda C\u00e2mara</a>, Relator Ministro Jos\u00e9 Jorge) ;</i></p><p><i>\u00c9 prescind\u00edvel a entrega pessoal das comunica\u00e7\u00f5es pelo TCU, raz\u00e3o pela qual n\u00e3o h\u00e1 necessidade de que o aviso de recebimento seja assinado pelo pr\u00f3prio destinat\u00e1rio. Entregando se a correspond\u00eancia no endere\u00e7o correto do destinat\u00e1rio, presume-se o recebimento da cita\u00e7\u00e3o. (<a href=\"https://pesquisa.apps.tcu.gov.br/#/doc/acordao-completo/1019/2008/Plen\u00e1rio\" target=\"_blank\">Ac\u00f3rd\u00e3o 1019/2008-TCU-Plen\u00e1rio</a>, Relator Ministro Benjamin Zymler) ;</i></p><p><i>As comunica\u00e7\u00f5es do TCU, inclusive as cita\u00e7\u00f5es, dever\u00e3o ser realizadas mediante Aviso de Recebimento - AR, via Empresa Brasileira de Correios e Tel\u00e9grafos, bastando para sua validade que se demonstre que a correspond\u00eancia foi entregue no endere\u00e7o correto. (<a href=\"https://pesquisa.apps.tcu.gov.br/#/doc/acordao-completo/1526/2007/Plen\u00e1rio\" target=\"_blank\">Ac\u00f3rd\u00e3o 1526/2007-TCU-Plen\u00e1rio</a>, Relator Ministro Aroldo Cedraz) .</i></p><p class=\"list_Paragraph\"><i>A validade do crit\u00e9rio de comunica\u00e7\u00e3o processual do TCU foi referendada pelo Supremo Tribunal Federal, nos termos do julgamento do MS-AgR 25.816/DF, por meio do qual se afirmou a desnecessidade da ci\u00eancia pessoal do interessado, entendendo-se suficiente a comprova\u00e7\u00e3o da entrega do 'AR' no endere\u00e7o do destinat\u00e1rio:</i></p><p><i>EMENTA: AGRAVO REGIMENTAL. MANDADO DE SEGURAN\u00c7A. DESNECESSIDADE DE INTIMA\u00c7\u00c3O PESSOAL DAS DECIS\u00d5ES DO TRIBUNAL DE CONTAS DA UNI\u00c3O. ART. 179 DO REGIMENTO INTERNO DO TCU. INTIMA\u00c7\u00c3O DO ATO IMPUGNADO POR CARTA REGISTRADA, INICIADO O PRAZO DO ART. 18 DA LEI n\u00ba 1.533/51 DA DATA CONSTANTE DO AVISO DE RECEBIMENTO. DECAD\u00caNCIA RECONHECIDA. AGRAVO IMPROVIDO.</i></p><p><i>O envio de carta registrada com aviso de recebimento est\u00e1 expressamente enumerado entre os meios de comunica\u00e7\u00e3o de que disp\u00f5e o Tribunal de Contas da Uni\u00e3o para proceder \u00e0s suas intima\u00e7\u00f5es.</i></p><p><i>O inciso II do art. 179 do Regimento Interno do TCU \u00e9 claro ao exigir apenas a comprova\u00e7\u00e3o da entrega no endere\u00e7o do destinat\u00e1rio, bastando o aviso de recebimento simples.</i></p><p class=\"list_Paragraph\"><i>No caso em apre\u00e7o todas as cita\u00e7\u00f5es s\u00e3o v\u00e1lidas. A Construtora Frei Dami\u00e3o Ltda. foi citada no seu endere\u00e7o constante da base de dados da Receita Federal, no de seu representante legal (TSE) e, adicionalmente, por edital, conforme quadro do item 18. O Sr. Jos\u00e9 da Silva foi citado no endere\u00e7o constante da base de dados do TSE, ante o insucesso de sua cita\u00e7\u00e3o naquele constante da base de dados da Receita Federal. J\u00e1 o Sr. H\u00e9lio Fontenele Magalh\u00e3es recebeu de pr\u00f3prio punho a cita\u00e7\u00e3o em seu endere\u00e7o constante da base de dados do TCU, ante o insucesso de sua cita\u00e7\u00e3o no endere\u00e7o constante da base de dados da Receita Federal. Houve recebimento efetivo de todas as notifica\u00e7\u00f5es, conforme quadro do item 176.</i></p><p class=\"list_Paragraph\"><i>Quanto ao m\u00e9rito, nos processos do TCU, a revelia n\u00e3o conduz \u00e0 presun\u00e7\u00e3o de que seriam verdadeiras todas as imputa\u00e7\u00f5es levantadas contra os respons\u00e1veis, diferentemente do que ocorre no processo civil, em que a revelia do r\u00e9u opera a presun\u00e7\u00e3o da verdade dos fatos narrados pelo autor. Dessa forma, a avalia\u00e7\u00e3o da responsabilidade dos agentes n\u00e3o pode prescindir da prova existente no processo ou para ele carreada. </i></p><p class=\"list_Paragraph\"><i>Ao n\u00e3o apresentar sua defesa, os respons\u00e1veis deixaram de produzir prova quanto \u00e0 regularidade da aplica\u00e7\u00e3o dos recursos do conv\u00eanio, em afronta \u00e0s normas que imp\u00f5em aos jurisdicionados a obriga\u00e7\u00e3o legal de, sempre que demandados pelos \u00f3rg\u00e3os de controle, apresentarem os documentos que demonstrem a correta utiliza\u00e7\u00e3o das verbas p\u00fablicas, a exemplo do contido no art. 93 do Decreto-Lei 200/67: 'Quem quer que utilize dinheiros p\u00fablicos ter\u00e1 de justificar seu bom e regular emprego na conformidade das leis, regulamentos e normas emanadas das autoridades administrativas competentes.' </i></p><p class=\"list_Paragraph\"><i>Considerando o princ\u00edpio da verdade real que rege a atua\u00e7\u00e3o desta Corte, ainda que as alega\u00e7\u00f5es de defesa n\u00e3o tenham sido apresentadas pelo respons\u00e1vel, a revelia n\u00e3o afasta a obrigatoriedade da an\u00e1lise dos elementos probat\u00f3rios dispon\u00edveis nos autos, conforme reiterados ac\u00f3rd\u00e3os do Tribunal (<a href=\"https://pesquisa.apps.tcu.gov.br/#/doc/acordao-completo/163/2015/Segunda C\u00e2mara\" target=\"_blank\">Ac\u00f3rd\u00e3o 163/2015-TCU-Segunda C\u00e2mara</a>, Rel.  Min. Subst. Andr\u00e9 de Carvalho; 2.685/2015 - 2\u00aa C\u00e2mara, Rel. Min. Raimundo Carreiro; 2.801/2015 - 1\u00aa C\u00e2mara, Rel. Min. Walton Alencar Rodrigues; 4.340/2015 - 1\u00aa C\u00e2mara, Rel. Min. Subst. Weder de Oliveira e 5.537/2015 - 1\u00aa C\u00e2mara, Rel. Min. Subst. Weder de Oliveira) . Assim, procurou-se buscar, em manifesta\u00e7\u00f5es dos respons\u00e1veis, se havia argumentos que pudessem ser aproveitados em seu favor.</i></p><p class=\"list_Paragraph\"><i>Reexaminando os autos, verifica-se que o Sr. H\u00e9lio Fontenele Magalh\u00e3es foi notificado na fase interna (itens 9 e 11) , tendo permanecido silente. J\u00e1 o Sr. Jos\u00e9 da Silva e a Construtora Frei Dami\u00e3o Ltda. vieram a ser responsabilizados somente na fase externa. Assim, n\u00e3o encontramos nenhum outro argumento nos autos que possa vir a ser analisado e posteriormente utilizado para afastar as irregularidades apontadas. </i></p><p class=\"list_Paragraph\"><i>Vale ressaltar que a pretens\u00e3o punitiva do TCU, conforme <a href=\"https://pesquisa.apps.tcu.gov.br/#/doc/acordao-completo/1441/2016/Plen\u00e1rio\" target=\"_blank\">Ac\u00f3rd\u00e3o 1441/2016-TCU-Plen\u00e1rio</a>, que uniformizou a jurisprud\u00eancia acerca dessa quest\u00e3o, subordina-se ao prazo geral de prescri\u00e7\u00e3o indicado no art. 205 do C\u00f3digo Civil, que \u00e9 de 10 anos, contado da data de ocorr\u00eancia da irregularidade sancionada, nos termos do art. 189 do C\u00f3digo Civil, sendo este prazo interrompido pelo ato que ordenar a cita\u00e7\u00e3o, a audi\u00eancia ou a oitiva do respons\u00e1vel. No caso em exame, por se tratar de execu\u00e7\u00e3o parcial e de omiss\u00e3o da presta\u00e7\u00e3o de contas da 3\u00aa parcela, o marco inicial para contagem do prazo prescricional deve ser o prazo final para apresenta\u00e7\u00e3o da presta\u00e7\u00e3o de contas, ocorrido em 17/8/2012. Tendo sido o ato de ordena\u00e7\u00e3o da cita\u00e7\u00e3o assinado em 20/5/2020 (pe\u00e7a 17) , n\u00e3o houve o decurso de prazo superior a 10 anos. Portanto, n\u00e3o ocorreu a prescri\u00e7\u00e3o da pretens\u00e3o punitiva.</i></p><p class=\"list_Paragraph\"><i>Em se tratando de processo em que as partes interessadas n\u00e3o se manifestaram acerca das irregularidades imputadas, n\u00e3o h\u00e1 elementos para que se possa efetivamente aferir e reconhecer a ocorr\u00eancia de boa-f\u00e9 na conduta dos respons\u00e1veis ou de quaisquer outros excludentes de culpabilidade, podendo o Tribunal, desde logo, proferir o julgamento de m\u00e9rito pela irregularidade das contas, nos termos dos \u00a7\u00a7 2\u00ba e 6\u00ba do art. 202 do Regimento Interno do TCU. (<a href=\"https://pesquisa.apps.tcu.gov.br/#/doc/acordao-completo/133/2015/Primeira C\u00e2mara\" target=\"_blank\">Ac\u00f3rd\u00e3o 133/2015-TCU-Primeira C\u00e2mara</a>, Rel. Min. Bruno Dantas; 2.455/2015 - 1\u00aa C\u00e2mara, Rel. Min. Bruno Dantas; 3.604/2015 - 1\u00aa C\u00e2mara, Rel. Min. Bruno Dantas; 5.070/2015 - 2\u00aa C\u00e2mara, Rel. Min. Subst. Andr\u00e9 de Carvalho e 2.424/2015 - Plen\u00e1rio, Rel. Min. Benjamin Zymler) .</i></p><p class=\"list_Paragraph\"><i>Dessa forma, os respons\u00e1veis H\u00e9lio Fontenele Magalh\u00e3es (CPF: XXX.158.223-XX) , Prefeito Municipal de Granja/CE de 4/4 a 14/11/2012, Jos\u00e9 da Silva (CPF XXX.172.623-XX) , s\u00f3cio administrador da Construtora Frei Dami\u00e3o Ltda. e a Construtora Frei Dami\u00e3o Ltda. (CNPJ 08.681.846/0001-46) devem ser considerados rev\u00e9is, nos termos do art. 12, \u00a73\u00ba, da Lei 8.443/1992.</i></p><p class=\"paragrafo_nivel_1\"><b><i>Cumulatividade de multas </i></b></p><p class=\"list_Paragraph\"><i>Quanto \u00e0 possibilidade de aplica\u00e7\u00e3o cumulativa das multas dos arts. 57 e 58, inciso I, da Lei 8.443/1992, ainda que seja adequada a realiza\u00e7\u00e3o de cita\u00e7\u00e3o e audi\u00eancia do respons\u00e1vel, por for\u00e7a do disposto no art. 209, \u00a74\u00ba, do Regimento Interno do TCU, o Tribunal reconhece que existe rela\u00e7\u00e3o de subordina\u00e7\u00e3o entre as condutas de 'n\u00e3o comprova\u00e7\u00e3o da aplica\u00e7\u00e3o dos recursos' e de 'omiss\u00e3o na presta\u00e7\u00e3o de contas', sendo a primeira consequ\u00eancia da segunda, o que enseja, na verifica\u00e7\u00e3o das duas irregularidades, a aplica\u00e7\u00e3o da multa do art. 57, com o afastamento da multa do art. 58, inciso I, em aten\u00e7\u00e3o ao princ\u00edpio da absor\u00e7\u00e3o (<a href=\"https://pesquisa.apps.tcu.gov.br/#/doc/acordao-completo/9579/2015/Segunda C\u00e2mara\" target=\"_blank\">Ac\u00f3rd\u00e3o 9579/2015-TCU-Segunda C\u00e2mara</a>, Relator Ministro Vital do R\u00eago; <a href=\"https://pesquisa.apps.tcu.gov.br/#/doc/acordao-completo/2469/2019/Primeira C\u00e2mara\" target=\"_blank\">Ac\u00f3rd\u00e3o 2469/2019-TCU-Primeira C\u00e2mara</a>, Relator Ministro Augusto Sherman) .</i></p><p class=\"list_Paragraph\"><i>Conforme leciona Cezar Bitencourt (Tratado de Direito Penal: parte geral - 8\u00aa Edi\u00e7\u00e3o - S\u00e3o Paulo: Saraiva, 2003. Pg. 565) , na absor\u00e7\u00e3o, ' (...) a pena do delito mais grave absorve a pena do delito menos grave, que deve ser desprezada'. No caso concreto, a 'omiss\u00e3o no dever de prestar contas', embora seja uma irregularidade aut\u00f4noma, funciona como fase ou meio para a consecu\u00e7\u00e3o da 'n\u00e3o comprova\u00e7\u00e3o da aplica\u00e7\u00e3o dos recursos', havendo clara rela\u00e7\u00e3o de interdepend\u00eancia entre essas condutas. Dessa forma, recaindo as duas ocorr\u00eancias num mesmo gestor, deve prevalecer a pena do delito mais grave, qual seja, a multa do art. 57, da Lei 8.443/1992.</i></p><p class=\"list_Paragraph\"><i>Cumpre observar, ainda, que a conduta dos respons\u00e1veis, consistente nas irregularidades 'n\u00e3o comprova\u00e7\u00e3o da boa e regular aplica\u00e7\u00e3o dos recursos federais repassados em face da omiss\u00e3o no dever de prestar contas' e 'n\u00e3o cumprimento do prazo para apresenta\u00e7\u00e3o de presta\u00e7\u00e3o de contas pelo gestor dos recursos', configura viola\u00e7\u00e3o n\u00e3o s\u00f3 \u00e0s regras legais, mas tamb\u00e9m aos princ\u00edpios basilares da administra\u00e7\u00e3o p\u00fablica, eis que, em \u00faltima an\u00e1lise, ocorre o comprometimento da necess\u00e1ria satisfa\u00e7\u00e3o \u00e0 sociedade sobre o efetivo emprego dos recursos p\u00fablicos postos \u00e0 disposi\u00e7\u00e3o da municipalidade, por for\u00e7a do instrumento de repasse em quest\u00e3o. Nesses casos, em que fica evidente a falta de transpar\u00eancia e lisura, n\u00e3o h\u00e1 como afastar as suspeitas sempre presentes de que a totalidade dos recursos p\u00fablicos federais, transferida ao munic\u00edpio, tenha sido integralmente desviada, em prol de gestor \u00edmprobo, ou de pessoas por ele determinadas, a revelar grave inobserv\u00e2ncia de dever de cuidado no trato com a coisa p\u00fablica, isto \u00e9, ato praticado com culpa grave, pois, na esp\u00e9cie, a conduta do respons\u00e1vel se distancia daquela que seria esperada de um administrador p\u00fablico minimante diligente, num claro exemplo de erro grosseiro a que alude o art. 28 do Decreto-lei 4.657/1942 (Lei de Introdu\u00e7\u00e3o \u00e0s Normas do Direito Brasileiro) , inclu\u00eddo pela Lei 13.655/2018 (<a href=\"https://pesquisa.apps.tcu.gov.br/#/doc/acordao-completo/1689/2019/Plen\u00e1rio\" target=\"_blank\">Ac\u00f3rd\u00e3o 1689/2019-TCU-Plen\u00e1rio</a>, Relator: Ministro AUGUSTO NARDES; <a href=\"https://pesquisa.apps.tcu.gov.br/#/doc/acordao-completo/2924/2018/Plen\u00e1rio\" target=\"_blank\">Ac\u00f3rd\u00e3o 2924/2018-TCU-Plen\u00e1rio</a>, Relator: Ministro JOS\u00c9 MUCIO MONTEIRO; <a href=\"https://pesquisa.apps.tcu.gov.br/#/doc/acordao-completo/2391/2018/Plen\u00e1rio\" target=\"_blank\">Ac\u00f3rd\u00e3o 2391/2018-TCU-Plen\u00e1rio</a>, Relator: Ministro BENJAMIN ZYMLER) .</i></p><p class=\"list_Paragraph\"><b><i>CONCLUS\u00c3O</i></b></p><p class=\"list_Paragraph\"><i>Em face da an\u00e1lise promovida na se\u00e7\u00e3o 'Exame T\u00e9cnico', verifica-se que os respons\u00e1veis n\u00e3o lograram comprovar a boa e regular aplica\u00e7\u00e3o dos recursos. Instados a se manifestar, optaram pelo sil\u00eancio, configurando a revelia, nos termos do \u00a73\u00ba, do art. 12, da Lei 8.443/1992. </i></p><p class=\"list_Paragraph\"><i>Com efeito, em fun\u00e7\u00e3o da revelia, n\u00e3o foi poss\u00edvel sanear as irregularidades a eles atribu\u00eddas, tampouco elidir o d\u00e9bito a eles imputado. Ademais, inexistem nos autos elementos que demonstrem a boa-f\u00e9 dos respons\u00e1veis ou a ocorr\u00eancia de outros excludentes de ilicitude, punibilidade ou culpabilidade. Desse modo, suas contas devem, desde logo, ser julgadas irregulares, nos termos do art. 202, \u00a7 6\u00ba, do Regimento Interno do TCU, procedendo-se \u00e0 condena\u00e7\u00e3o em d\u00e9bito, abstendo-se de aplicar-lhes a multa prevista no art. 57 da Lei 8.443/1992, em raz\u00e3o da ocorr\u00eancia da prescri\u00e7\u00e3o da pretens\u00e3o punitiva, conforme tratado no item 25.</i></p><p class=\"list_Paragraph\"><i>Vale ressaltar que a jurisprud\u00eancia pac\u00edfica nesta Corte \u00e9 no sentido da imprescritibilidade das a\u00e7\u00f5es de ressarcimento ao er\u00e1rio (S\u00famula TCU 282) . Dessa forma, identificado dano ao er\u00e1rio, devese instaurar e julgar o processo de tomada de contas especial para responsabilizar seus agentes causadores, respeitando o direito ao contradit\u00f3rio e \u00e0 ampla defesa, independentemente de quando ocorreram os atos impugnados.</i></p><p class=\"list_Paragraph\"><i>Conforme tratado no item 29, n\u00e3o ocorreu a prescri\u00e7\u00e3o da pretens\u00e3o punitiva.</i></p><p class=\"list_Paragraph\"><i>Quanto ao Sr. Esmerino Oliveira Arruda Coelho (falecido) , conforme tratado no item 14, deve ser exclu\u00eddo da rela\u00e7\u00e3o processual desta tomada de contas especial.</i></p><p class=\"list_Paragraph\"><b><i>PROPOSTA DE ENCAMINHAMENTO</i></b></p><p class=\"list_Paragraph\"><i>Diante do exposto, submetem-se os autos \u00e0 considera\u00e7\u00e3o superior, propondo-se a ado\u00e7\u00e3o das seguintes medidas:</i></p><p><i>a)\texcluir da rela\u00e7\u00e3o processual o Sr. Esmerino Oliveira Arruda Coelho (CPF XXX.227.217-XX - falecido) , Prefeito Municipal de Granja/CE de 1/1/2009 a 3/4/2012;</i></p><p><i>b)\tconsiderar rev\u00e9is os respons\u00e1veis H\u00e9lio Fontenele Magalh\u00e3es (CPF: XXX.158.223-XX) , Prefeito Municipal de Granja/CE de 4/4 a 14/11/2012, Jos\u00e9 da Silva (CPF: XXX.172.623-XX) , s\u00f3cio administrador da Construtora Frei Dami\u00e3o Ltda. e Construtora Frei Dami\u00e3o Ltda. (CNPJ 08.681.846/0001-46) , com fundamento no \u00a7 3\u00ba, art. 12, Lei 8.443, de 16 de julho de 1992;</i></p><p><i>c)\tcom fundamento nos arts. 1\u00ba, inciso I, 16, inciso III, al\u00edneas 'a' e 'c' e 'd', da Lei 8.443/1992 c/c os arts. 19 e 23, inciso III, da mesma Lei, e com arts. 1\u00ba, inciso I; 209, incisos III e IV; 210 e 214, inciso III, do Regimento Interno, julgar irregulares as contas de H\u00e9lio Fontenele Magalh\u00e3es (CPF: XXX.158.223-XX) , Prefeito Municipal de Granja/CE de 4/4 a 14/11/2012, de Jos\u00e9 da Silva (CPF: XXX.172.623-XX) , s\u00f3cio administrador da Construtora Frei Dami\u00e3o Ltda. e da Construtora Frei Dami\u00e3o Ltda. (CNPJ 08.681.846/0001-46) , e conden\u00e1-los, solidariamente, ao pagamento das quantias a seguir especificadas, com a fixa\u00e7\u00e3o do prazo de quinze dias, a contar da notifica\u00e7\u00e3o, para comprovarem, perante o Tribunal (art. 214, inciso III, al\u00ednea 'a', do Regimento Interno) , o recolhimento da d\u00edvida aos cofres do Tesouro Nacional, atualizada monetariamente e acrescida dos juros de mora, calculados a partir das datas discriminadas, at\u00e9 a data do recolhimento, na forma prevista na legisla\u00e7\u00e3o em vigor.</i></p><p><i>c.1) Sr. H\u00e9lio Fontenele Magalh\u00e3es </i><b><i>individualmente</i></b><i>:</i></p><table><tbody><tr>\t<td><p class=\"body_Text\"><i>VALOR ORIGINAL (R$) </i></p></td>\t<td><p class=\"body_Text\"><i>DATA DA OCORR\u00caNCIA</i></p></td>\t<td><p class=\"body_Text\"><i>D\u00c9BITO/CR\u00c9DITO</i></p></td></tr><tr>\t<td><p class=\"body_Text\"><i>1.060.000,00</i></p></td>\t<td><p class=\"body_Text\"><i>21/9/2009</i></p></td>\t<td><p class=\"body_Text\"><i>D</i></p></td></tr><tr>\t<td><p class=\"body_Text\"><i>530.000,00</i></p></td>\t<td><p class=\"body_Text\"><i>8/9/2010</i></p></td>\t<td><p class=\"body_Text\"><i>D</i></p></td></tr><tr>\t<td><p class=\"body_Text\"><i>1.060.000,00</i></p></td>\t<td><p class=\"body_Text\"><i>1/7/2011</i></p></td>\t<td><p class=\"body_Text\"><i>D</i></p></td></tr><tr>\t<td><p class=\"body_Text\"><i>316.665,74</i></p></td>\t<td><p class=\"body_Text\"><i>11/08/2011</i></p></td>\t<td><p class=\"body_Text\"><i>C</i></p></td></tr><tr>\t<td><p class=\"body_Text\"><i>148.200,08</i></p></td>\t<td><p class=\"body_Text\"><i>06/09/2011</i></p></td>\t<td><p class=\"body_Text\"><i>C</i></p></td></tr><tr>\t<td><p class=\"body_Text\"><i>161.818,91</i></p></td>\t<td><p class=\"body_Text\"><i>03/10/2011</i></p></td>\t<td><p class=\"body_Text\"><i>C</i></p></td></tr><tr>\t<td><p class=\"body_Text\"><i>259.579,43</i></p></td>\t<td><p class=\"body_Text\"><i>27/10/2011</i></p></td>\t<td><p class=\"body_Text\"><i>C</i></p></td></tr><tr>\t<td><p class=\"body_Text\"><i>175.849,57</i></p></td>\t<td><p class=\"body_Text\"><i>22/11/2011</i></p></td>\t<td><p class=\"body_Text\"><i>C</i></p></td></tr><tr>\t<td><p class=\"body_Text\"><i>85.336,27</i></p></td>\t<td><p class=\"body_Text\"><i>09/03/2012</i></p></td>\t<td><p class=\"body_Text\"><i>C</i></p></td></tr></tbody></table><p class=\"list_Paragraph\"><i>c.2) Sr. H\u00e9lio Fontenele Magalh\u00e3es </i><b><i>solidariamente</i></b><i> com a Construtora Frei Dami\u00e3o Ltda. e com o Sr. Jos\u00e9 da Silva (CPF: XXX.172.623-XX) :</i></p><table><tbody><tr>\t<td><p class=\"body_Text\"><i>VALOR ORIGINAL (R$) </i></p></td>\t<td><p class=\"body_Text\"><i>DATA DA OCORR\u00caNCIA</i></p></td>\t<td><p class=\"body_Text\"><i>D\u00c9BITO/CR\u00c9DITO</i></p></td></tr><tr>\t<td><p class=\"body_Text\"><i>316.665,74</i></p></td>\t<td><p class=\"body_Text\"><i>11/08/2011</i></p></td>\t<td><p class=\"body_Text\"><i>D</i></p></td></tr><tr>\t<td><p class=\"body_Text\"><i>148.200,08</i></p></td>\t<td><p class=\"body_Text\"><i>06/09/2011</i></p></td>\t<td><p class=\"body_Text\"><i>D</i></p></td></tr><tr>\t<td><p class=\"body_Text\"><i>161.818,91</i></p></td>\t<td><p class=\"body_Text\"><i>03/10/2011</i></p></td>\t<td><p class=\"body_Text\"><i>D</i></p></td></tr><tr>\t<td><p class=\"body_Text\"><i>259.579,43</i></p></td>\t<td><p class=\"body_Text\"><i>27/10/2011</i></p></td>\t<td><p class=\"body_Text\"><i>D</i></p></td></tr><tr>\t<td><p class=\"body_Text\"><i>175.849,57</i></p></td>\t<td><p class=\"body_Text\"><i>22/11/2011</i></p></td>\t<td><p class=\"body_Text\"><i>D</i></p></td></tr><tr>\t<td><p class=\"body_Text\"><i>85.336,27</i></p></td>\t<td><p class=\"body_Text\"><i>09/03/2012</i></p></td>\t<td><p class=\"body_Text\"><i>D</i></p></td></tr></tbody></table><p><i>d) \taplicar individualmente a H\u00e9lio Fontenele Magalh\u00e3es (CPF: XXX.158.223-XX) , a Jos\u00e9 da Silva (CPF: XXX.172.623-XX) e \u00e0 Construtora Frei Dami\u00e3o Ltda. (CNPJ 08.681.846/0001-46) , a multa prevista no art. 57 da Lei 8.443/92 c/c o art. 267 do RI/TCU, fixando-lhes o prazo de quinze dias, a contar da notifica\u00e7\u00e3o, para que comprovem, perante o Tribunal (art. 214, III, 'a', do Regimento Interno do TCU) , o recolhimento da d\u00edvida aos cofres do Tesouro Nacional, atualizada monetariamente desde a data do ac\u00f3rd\u00e3o que vier a ser proferido por este Tribunal at\u00e9 a do efetivo recolhimento, se pagas ap\u00f3s o vencimento, na forma da legisla\u00e7\u00e3o em vigor;</i></p><p><i>e)\tesclarecer ao Sr. H\u00e9lio Fontenele Magalh\u00e3es que, caso se demonstre a correta aplica\u00e7\u00e3o dos recursos por via recursal, mas n\u00e3o se justifique a omiss\u00e3o da presta\u00e7\u00e3o de contas, o d\u00e9bito poder\u00e1 ser afastado, mas permanecer\u00e1 a irregularidade das contas, dando-se ensejo \u00e0 aplica\u00e7\u00e3o da multa prevista no art. 58, inciso I, da Lei 8.443/1992;</i></p><p><i>f)\tautorizar, desde logo, nos termos do art. 28, inciso II, da Lei 8.443/1992, a cobran\u00e7a judicial da d\u00edvida, caso n\u00e3o atendidas as notifica\u00e7\u00f5es;</i></p><p><i>g)\tautorizar tamb\u00e9m, desde logo, se requerido, com fundamento no art. 26 da Lei 8.443, de 1992 c/c o art. 217, \u00a7\u00a7 1\u00ba e 2\u00ba do Regimento Interno do TCU, o parcelamento da d\u00edvida em at\u00e9 36 parcelas, incidindo, sobre cada parcela, corrigida monetariamente, os correspondentes acr\u00e9scimos legais fixando-lhes o prazo de quinze dias, a contar do recebimento da notifica\u00e7\u00e3o, para comprovarem perante o Tribunal o recolhimento da primeira parcela, e de trinta dias, a contar da parcela anterior, para comprovarem os recolhimentos das demais parcelas, devendo incidir sobre cada valor mensal, atualizado monetariamente, os juros de mora devidos, no caso do d\u00e9bito, na forma prevista na legisla\u00e7\u00e3o em vigor, alertando os respons\u00e1veis que a falta de comprova\u00e7\u00e3o do recolhimento de qualquer parcela importar\u00e1 no vencimento antecipado do saldo devedor, nos termos do art. 217 do Regimento Interno deste Tribunal;</i></p><p><i>h)\tenviar c\u00f3pia do Ac\u00f3rd\u00e3o que vier a ser proferido \u00e0 Funda\u00e7\u00e3o Nacional de Sa\u00fade, ao Munic\u00edpio de Granja/CE e aos respons\u00e1veis, para ci\u00eancia, bem como \u00e0 Procuradoria da Rep\u00fablica no Estado do Cear\u00e1, nos termos do \u00a7 3\u00ba do art. 16 da Lei 8.443/1992, c/c o \u00a7 7\u00ba do art. 209 do Regimento Interno do TCU, para ado\u00e7\u00e3o das medidas cab\u00edveis;</i></p><p><i>i)\tinformar \u00e0 Procuradoria da Rep\u00fablica no Estado do Cear\u00e1, \u00e0 Funda\u00e7\u00e3o Nacional de Sa\u00fade, ao Munic\u00edpio de Granja/CE e aos respons\u00e1veis, que a presente delibera\u00e7\u00e3o, acompanhada do Relat\u00f3rio e do Voto que a fundamenta, est\u00e1 dispon\u00edvel para a consulta no endere\u00e7o www.tcu.gov.br/acordaos, al\u00e9m de esclarecer que, caso requerido, o TCU poder\u00e1 fornecer sem custos as correspondentes c\u00f3pias, de forma impressa; e</i></p><p><i>j)\tinformar \u00e0 Procuradoria da Rep\u00fablica no Estado do Cear\u00e1 que, nos termos do par\u00e1grafo \u00fanico do art. 62 da Resolu\u00e7\u00e3o TCU 259/2014, os procuradores e membros do Minist\u00e9rio P\u00fablico credenciados nesta Corte podem acessar os presentes autos de forma eletr\u00f4nica e autom\u00e1tica, ressalvados apenas os casos de eventuais pe\u00e7as classificadas como sigilosas, as quais requerem solicita\u00e7\u00e3o formal.</i>\"</p><p>\u00c9 o relat\u00f3rio.</p><p class=\"footer\"/>", "ADVOGADO": " n\u00e3o h\u00e1", "REPRESENTANTEMP": "Procurador S\u00e9rgio Ricardo Costa Carib\u00e9", "SITUACAO": "OFICIALIZADO", "SUMARIO": "TOMADA DE CONTAS ESPECIAL. CONV\u00caNIO. CONSTRU\u00c7\u00c3O DE SISTEMAS DE ESGOTAMENTO SANIT\u00c1RIO. EXECU\u00c7\u00c3O PARCIAL. OMISS\u00c3O NO DEVER DE PRESTAR CONTAS DA 3\u00aa PARCELA. CITA\u00c7\u00c3O E AUDI\u00caNCIA. REVELIA. EXCLUS\u00c3O DE UM DOS RESPONS\u00c1VEIS DA RELA\u00c7\u00c3O PROCESSUAL. IRREGULARIDADE DAS CONTAS DOS DEMAIS. IMPUTA\u00c7\u00c3O DE D\u00c9BITO E MULTA.", "TIPOPROCESSO": "TOMADA DE CONTAS ESPECIAL (TCE)", "UNIDADETECNICA": " Secretaria de Controle Externo de Tomada de Contas Especial (SecexTCE)", "VOTO": "<p>\tEsta tomada de contas especial foi instaurada pela Funda\u00e7\u00e3o Nacional de Sa\u00fade em nome de H\u00e9lio Fontenele Magalh\u00e3es, prefeito de Granja/CE de 4/4/2012 a 14/11/2012 e de seu antecessor, Esmerino Oliveira Arruda Coelho, que exerceu o cargo de 1/1/2009 a 3/4/2012, em raz\u00e3o da impugna\u00e7\u00e3o total dos recursos repassados por meio do Termo de Compromisso PAC 283/2007, tendo por objeto a execu\u00e7\u00e3o de sistemas de esgotamento sanit\u00e1rio. O ajuste vigeu de 31/12/2007 a 18/6/2012 e a data final para presta\u00e7\u00e3o de contas foi 17/8/2012.</p><p>\t2. O valor total previsto para a execu\u00e7\u00e3o do objeto foi de R$ 5.583.939,78, sendo R$ 5.300.000,00 oriundos da Funasa e R$ 283.939,78 relativos \u00e0 contrapartida. No entanto, foram efetivamente repassados pela Funasa R$ 2.650.000,00, por meio de ordens banc\u00e1rias emitidas entre setembro de 2009 e julho de 2011.</p><p>\t3. Conforme informa\u00e7\u00f5es dispon\u00edveis no processo, Esmerino Oliveira Arruda Coelho renunciou ao cargo de prefeito em 4/4/2012, tendo assumido o vice-prefeito, H\u00e9lio Fontenele Magalh\u00e3es, que permaneceu no cargo at\u00e9 14/11/2012, quando foi afastado em decorr\u00eancia de decis\u00e3o judicial em processos de A\u00e7\u00e3o Civil de Improbidade Administrativa.</p><p>\t4. Na instru\u00e7\u00e3o inicial foi proposto o afastamento da responsabilidade de Esmerino Oliveira Arruda Coelho, falecido, uma vez que este n\u00e3o havia praticado qualquer ato de gest\u00e3o relacionado ao conv\u00eanio. O ent\u00e3o vice-prefeito H\u00e9lio Fontenele Magalh\u00e3es foi o respons\u00e1vel pela assinatura de todas as notas de empenho e pelo pagamento das despesas do conv\u00eanio. Tamb\u00e9m o 3\u00ba e 4\u00ba termos aditivos foram assinados por ele. Citado devido \u00e0 omiss\u00e3o no dever de prestar contas da 3\u00aa parcela do conv\u00eanio, o gestor n\u00e3o apresentou defesa, devendo ser considerado revel.</p><p>\t5. Al\u00e9m disso, foi proposta a responsabiliza\u00e7\u00e3o solid\u00e1ria de H\u00e9lio Fontenele Magalh\u00e3es, da Construtora Frei Dami\u00e3o Ltda. e de seu s\u00f3cio administrador, Jos\u00e9 da Silva, devido \u00e0 execu\u00e7\u00e3o parcial do objeto, no percentual de 28,35%, com pagamentos equivalentes a 50% do total. Devidamente citados pela diferen\u00e7a, esses respons\u00e1veis permaneceram silentes, configurando-se sua revelia. O chamamento do s\u00f3cio administrador decorreu do fato de a empresa se encontrar na situa\u00e7\u00e3o \"baixada\" na base de dados da Receita Federal desde 17/11/2016.</p><p>\t6. A omiss\u00e3o dos respons\u00e1veis em prestar contas e a aus\u00eancia de qualquer elemento de defesa que lhes possa ser aproveitado impede o estabelecimento do nexo entre os recursos p\u00fablicos recebidos e as despesas efetuadas na consecu\u00e7\u00e3o do ajuste, impondo-se, em consequ\u00eancia, o julgamento pela irregularidade das contas e a condena\u00e7\u00e3o em d\u00e9bito pela totalidade dos recursos federais repassados, nos termos do art. 16, inciso III, al\u00edneas \"a\" e \"c\", e art. 19 da Lei 8.443/1992. Cabe registrar que o respons\u00e1vel que foi notificado na fase interna da TCE, H\u00e9lio Fontenele, tamb\u00e9m permaneceu silente.</p><p>\t7. Anoto n\u00e3o ter ocorrido a prescri\u00e7\u00e3o da pretens\u00e3o punitiva, conforme o entendimento assentado pelo <a href=\"https://pesquisa.apps.tcu.gov.br/#/doc/acordao-completo/1441/2016/Plen\u00e1rio\" target=\"_blank\">Ac\u00f3rd\u00e3o 1441/2016-TCU-Plen\u00e1rio</a>. Em rela\u00e7\u00e3o \u00e0 pretens\u00e3o ressarcit\u00f3ria, em raz\u00e3o da decis\u00e3o proferida pelo Supremo Tribunal Federal no RE 636.886, no sentido de considerar \"<i>prescrit\u00edvel a pretens\u00e3o de ressarcimento ao er\u00e1rio fundada em decis\u00e3o de Tribunal de Contas</i>\" (Tema 899) , registro que, por n\u00e3o ser poss\u00edvel extrapolar os par\u00e2metros normativos empregados pelo STF para solu\u00e7\u00e3o do problema enfrentado no RE 636.886, e dada a imprescindibilidade da fixa\u00e7\u00e3o definitiva de orienta\u00e7\u00f5es acerca da aplica\u00e7\u00e3o do Tema 899, o que s\u00f3 acontecer\u00e1 com o julgamento dos embargos de declara\u00e7\u00e3o opostos naquele Extraordin\u00e1rio, inclino-me, at\u00e9 que isso ocorra, a manter a interpreta\u00e7\u00e3o adotada pela Corte Suprema, em 2008, no Mandado de Seguran\u00e7a - MS 26.210,  oportunidade em que foi fixada tese da imprescritibilidade das a\u00e7\u00f5es de ressarcimento ao er\u00e1rio, e na S\u00famula TCU 282, cujo conte\u00fado \u00e9 no mesmo sentido.</p><p>\t8. Em rela\u00e7\u00e3o \u00e0s multas a serem aplicadas com fundamento no art. 57 da Lei 8.443/92, estabele\u00e7o os valores de R$ 450.000,00, R$ 180.000,00 e R$ 180.000,00, correspondentes a cerca de 10% do valor atualizado do d\u00e9bito, respectivamente a H\u00e9lio Fontenele Magalh\u00e3es, Jos\u00e9 da Silva e Construtora Frei Dami\u00e3o Ltda.</p><p>\tAnte o exposto, em linha com os pareceres da unidade instrutiva e do Minist\u00e9rio P\u00fablico junto ao TCU, VOTO no sentido de que o Tribunal adote o Ac\u00f3rd\u00e3o que ora submeto \u00e0 delibera\u00e7\u00e3o deste Colegiado.</p><p class=\"body_Text\">TCU, Sala das Sess\u00f5es, em 11 de maio de 2021.</p><p class=\"body_Text\"/><p class=\"body_Text\"/><p class=\"body_Text\"/><p class=\"body_Text\">JORGE OLIVEIRA </p><p class=\"body_Text\">Relator</p><p class=\"footer\"/>", "DTATUALIZACAO": "20210619", "URLARQUIVO": "https://contas.tcu.gov.br/sagas/SvlVisualizarRelVotoAcRtf?codFiltro=SAGAS-SESSAO-ENCERRADA&seOcultaPagina=S&item0=752155", "URLARQUIVOPDF": "https://contas.tcu.gov.br/sagas/SvlVisualizarRelVotoAc?codFiltro=SAGAS-SESSAO-ENCERRADA&seOcultaPagina=S&item0=752155", "EXTENSAOARQUIVO": "doc", "CODPROCESSO": "62589281"}